Workbook
Name titulo: Indice!$A$1:$A$18
Name titulos: 'Mis precios'!$B$35,'Mis precios'!$B$22,'Mis precios'!$B$11,'Mis precios'!$B$42,'Mis precios'!$B$71
Name titulos: 'ListaN69 09-02-2025'!$B$33,'ListaN69 09-02-2025'!$B$20,'ListaN69 09-02-2025'!$B$9,'ListaN69 09-02-2025'!$B$40,'ListaN69 09-02-2025'!$B$69

Sheet ListaN69 09-02-2025
B1: DISTRI-SAL
A7: CODIGO | B7: DESCRIPCION | C7: Cantidad x bulto | D7: IVA | E7: PRECIO SIN IVA | F7: variacion respecto a lista anterior (aplicado en lista)
AF8: =IF(AND(ISBLANK(A8),ISBLANK(B8),ISBLANK(E8)),"Blanco",IF(AND(ISBLANK(A8),NOT(ISBLANK(B8))),"Titulo",IF(AND(NOT(ISBLANK(A8)),NOT(ISBLANK(B8)),ISBLANK(E8),IFERROR(FIND("FF--",A8)>1,FALSE)),"F.Comercializacion",IF(AND(NOT(ISBLANK(A8)),NOT(ISBLANK(B8)),NOT(ISBLANK(E8)),ISERROR(VLOOKUP(A8,'ListaN68 02-02-2025'!$A$12:$E$13375,5,0))),"Nuevo",IF(AND(NOT(ISBLANK(A8)),NOT(ISBLANK(B8)),NOT(ISBLANK(E8)),AND(E8-VLOOKUP(A8,'ListaN68 02-02-2025'!$A$12:$E$13375,5,0)>=-2,E8-VLOOKUP(A8,'ListaN68 02-02-2025'!$A$12:$E$13375,5,0)<=2)),"Igual",IF(AND(NOT(ISBLANK(A8)),NOT(ISBLANK(B8)),NOT(ISBLANK(E8)),E8-VLOOKUP(A8,'ListaN68 02-02-2025'!$A$12:$E$13375,5,0)>2),"Aumento",IF(AND(NOT(ISBLANK(A8)),NOT(ISBLANK(B8)),NOT(ISBLANK(E8)),E8-VLOOKUP(A8,'ListaN68 02-02-2025'!$A$12:$E$13375,5,0)<2),"Bajo","Error en codigo"))))))) -> Blanco
B9: ELECTRONICA | AF9: =IF(AND(ISBLANK(A9),ISBLANK(B9),ISBLANK(E9)),"Blanco",IF(AND(ISBLANK(A9),NOT(ISBLANK(B9))),"Titulo",IF(AND(NOT(ISBLANK(A9)),NOT(ISBLANK(B9)),ISBLANK(E9),IFERROR(FIND("FF--",A9)>1,FALSE)),"F.Comercializacion",IF(AND(NOT(ISBLANK(A9)),NOT(ISBLANK(B9)),NOT(ISBLANK(E9)),ISERROR(VLOOKUP(A9,'ListaN68 02-02-2025'!$A$12:$E$13375,5,0))),"Nuevo",IF(AND(NOT(ISBLANK(A9)),NOT(ISBLANK(B9)),NOT(ISBLANK(E9)),AND(E9-VLOOKUP(A9,'ListaN68 02-02-2025'!$A$12:$E$13375,5,0)>=-2,E9-VLOOKUP(A9,'ListaN68 02-02-2025'!$A$12:$E$13375,5,0)<=2)),"Igual",IF(AND(NOT(ISBLANK(A9)),NOT(ISBLANK(B9)),NOT(ISBLANK(E9)),E9-VLOOKUP(A9,'ListaN68 02-02-2025'!$A$12:$E$13375,5,0)>2),"Aumento",IF(AND(NOT(ISBLANK(A9)),NOT(ISBLANK(B9)),NOT(ISBLANK(E9)),E9-VLOOKUP(A9,'ListaN68 02-02-2025'!$A$12:$E$13375,5,0)<2),"Bajo","Error en codigo"))))))) -> Titulo
AF10: =IF(AND(ISBLANK(A10),ISBLANK(B10),ISBLANK(E10)),"Blanco",IF(AND(ISBLANK(A10),NOT(ISBLANK(B10))),"Titulo",IF(AND(NOT(ISBLANK(A10)),NOT(ISBLANK(B10)),ISBLANK(E10),IFERROR(FIND("FF--",A10)>1,FALSE)),"F.Comercializacion",IF(AND(NOT(ISBLANK(A10)),NOT(ISBLANK(B10)),NOT(ISBLANK(E10)),ISERROR(VLOOKUP(A10,'ListaN68 02-02-2025'!$A$12:$E$13375,5,0))),"Nuevo",IF(AND(NOT(ISBLANK(A10)),NOT(ISBLANK(B10)),NOT(ISBLANK(E10)),AND(E10-VLOOKUP(A10,'ListaN68 02-02-2025'!$A$12:$E$13375,5,0)>=-2,E10-VLOOKUP(A10,'ListaN68 02-02-2025'!$A$12:$E$13375,5,0)<=2)),"Igual",IF(AND(NOT(ISBLANK(A10)),NOT(ISBLANK(B10)),NOT(ISBLANK(E10)),E10-VLOOKUP(A10,'ListaN68 02-02-2025'!$A$12:$E$13375,5,0)>2),"Aumento",IF(AND(NOT(ISBLANK(A10)),NOT(ISBLANK(B10)),NOT(ISBLANK(E10)),E10-VLOOKUP(A10,'ListaN68 02-02-2025'!$A$12:$E$13375,5,0)<2),"Bajo","Error en codigo"))))))) -> Blanco
A11: CRJ-11 | B11: CONECTOR MACHO RJ-11 6 CONTACTOS | C11: UM 1u | D11: 21 | E11: 56.26 | AF11: =IF(AND(ISBLANK(A11),ISBLANK(B11),ISBLANK(E11)),"Blanco",IF(AND(ISBLANK(A11),NOT(ISBLANK(B11))),"Titulo",IF(AND(NOT(ISBLANK(A11)),NOT(ISBLANK(B11)),ISBLANK(E11),IFERROR(FIND("FF--",A11)>1,FALSE)),"F.Comercializacion",IF(AND(NOT(ISBLANK(A11)),NOT(ISBLANK(B11)),NOT(ISBLANK(E11)),ISERROR(VLOOKUP(A11,'ListaN68 02-02-2025'!$A$12:$E$13375,5,0))),"Nuevo",IF(AND(NOT(ISBLANK(A11)),NOT(ISBLANK(B11)),NOT(ISBLANK(E11)),AND(E11-VLOOKUP(A11,'ListaN68 02-02-2025'!$A$12:$E$13375,5,0)>=-2,E11-VLOOKUP(A11,'ListaN68 02-02-2025'!$A$12:$E$13375,5,0)<=2)),"Igual",IF(AND(NOT(ISBLANK(A11)),NOT(ISBLANK(B11)),NOT(ISBLANK(E11)),E11-VLOOKUP(A11,'ListaN68 02-02-2025'!$A$12:$E$13375,5,0)>2),"Aumento",IF(AND(NOT(ISBLANK(A11)),NOT(ISBLANK(B11)),NOT(ISBLANK(E11)),E11-VLOOKUP(A11,'ListaN68 02-02-2025'!$A$12:$E$13375,5,0)<2),"Bajo","Error en codigo"))))))) -> Igual
A12: CRJ-45 | B12: CONECTOR MACHO RJ-45 8 CONTACTOS | C12: UM 1u | D12: 21 | E12: 118.77 | AF12: =IF(AND(ISBLANK(A12),ISBLANK(B12),ISBLANK(E12)),"Blanco",IF(AND(ISBLANK(A12),NOT(ISBLANK(B12))),"Titulo",IF(AND(NOT(ISBLANK(A12)),NOT(ISBLANK(B12)),ISBLANK(E12),IFERROR(FIND("FF--",A12)>1,FALSE)),"F.Comercializacion",IF(AND(NOT(ISBLANK(A12)),NOT(ISBLANK(B12)),NOT(ISBLANK(E12)),ISERROR(VLOOKUP(A12,'ListaN68 02-02-2025'!$A$12:$E$13375,5,0))),"Nuevo",IF(AND(NOT(ISBLANK(A12)),NOT(ISBLANK(B12)),NOT(ISBLANK(E12)),AND(E12-VLOOKUP(A12,'ListaN68 02-02-2025'!$A$12:$E$13375,5,0)>=-2,E12-VLOOKUP(A12,'ListaN68 02-02-2025'!$A$12:$E$13375,5,0)<=2)),"Igual",IF(AND(NOT(ISBLANK(A12)),NOT(ISBLANK(B12)),NOT(ISBLANK(E12)),E12-VLOOKUP(A12,'ListaN68 02-02-2025'!$A$12:$E$13375,5,0)>2),"Aumento",IF(AND(NOT(ISBLANK(A12)),NOT(ISBLANK(B12)),NOT(ISBLANK(E12)),E12-VLOOKUP(A12,'ListaN68 02-02-2025'!$A$12:$E$13375,5,0)<2),"Bajo","Error en codigo"))))))) -> Igual
A13: CRJ-9 | B13: CONECTOR MACHO RJ-9 4 CONTACTOS | C13: UM 1u | D13: 21 | E13: 56.26 | AF13: =IF(AND(ISBLANK(A13),ISBLANK(B13),ISBLANK(E13)),"Blanco",IF(AND(ISBLANK(A13),NOT(ISBLANK(B13))),"Titulo",IF(AND(NOT(ISBLANK(A13)),NOT(ISBLANK(B13)),ISBLANK(E13),IFERROR(FIND("FF--",A13)>1,FALSE)),"F.Comercializacion",IF(AND(NOT(ISBLANK(A13)),NOT(ISBLANK(B13)),NOT(ISBLANK(E13)),ISERROR(VLOOKUP(A13,'ListaN68 02-02-2025'!$A$12:$E$13375,5,0))),"Nuevo",IF(AND(NOT(ISBLANK(A13)),NOT(ISBLANK(B13)),NOT(ISBLANK(E13)),AND(E13-VLOOKUP(A13,'ListaN68 02-02-2025'!$A$12:$E$13375,5,0)>=-2,E13-VLOOKUP(A13,'ListaN68 02-02-2025'!$A$12:$E$13375,5,0)<=2)),"Igual",IF(AND(NOT(ISBLANK(A13)),NOT(ISBLANK(B13)),NOT(ISBLANK(E13)),E13-VLOOKUP(A13,'ListaN68 02-02-2025'!$A$12:$E$13375,5,0)>2),"Aumento",IF(AND(NOT(ISBLANK(A13)),NOT(ISBLANK(B13)),NOT(ISBLANK(E13)),E13-VLOOKUP(A13,'ListaN68 02-02-2025'!$A$12:$E$13375,5,0)<2),"Bajo","Error en codigo"))))))) -> Igual
A14: HDMI | B14: CABLE HDMI A HDMI X1.5MTS | C14: UM 1u | 10u | D14: 21 | E14: 3375.54 | AF14: =IF(AND(ISBLANK(A14),ISBLANK(B14),ISBLANK(E14)),"Blanco",IF(AND(ISBLANK(A14),NOT(ISBLANK(B14))),"Titulo",IF(AND(NOT(ISBLANK(A14)),NOT(ISBLANK(B14)),ISBLANK(E14),IFERROR(FIND("FF--",A14)>1,FALSE)),"F.Comercializacion",IF(AND(NOT(ISBLANK(A14)),NOT(ISBLANK(B14)),NOT(ISBLANK(E14)),ISERROR(VLOOKUP(A14,'ListaN68 02-02-2025'!$A$12:$E$13375,5,0))),"Nuevo",IF(AND(NOT(ISBLANK(A14)),NOT(ISBLANK(B14)),NOT(ISBLANK(E14)),AND(E14-VLOOKUP(A14,'ListaN68 02-02-2025'!$A$12:$E$13375,5,0)>=-2,E14-VLOOKUP(A14,'ListaN68 02-02-2025'!$A$12:$E$13375,5,0)<=2)),"Igual",IF(AND(NOT(ISBLANK(A14)),NOT(ISBLANK(B14)),NOT(ISBLANK(E14)),E14-VLOOKUP(A14,'ListaN68 02-02-2025'!$A$12:$E$13375,5,0)>2),"Aumento",IF(AND(NOT(ISBLANK(A14)),NOT(ISBLANK(B14)),NOT(ISBLANK(E14)),E14-VLOOKUP(A14,'ListaN68 02-02-2025'!$A$12:$E$13375,5,0)<2),"Bajo","Error en codigo"))))))) -> Igual
A15: USBM | B15: CABLE USB MACHO A MICRO USB 5 PINES | C15: UM 1u | D15: 21 | E15: 1931.56 | AF15: =IF(AND(ISBLANK(A15),ISBLANK(B15),ISBLANK(E15)),"Blanco",IF(AND(ISBLANK(A15),NOT(ISBLANK(B15))),"Titulo",IF(AND(NOT(ISBLANK(A15)),NOT(ISBLANK(B15)),ISBLANK(E15),IFERROR(FIND("FF--",A15)>1,FALSE)),"F.Comercializacion",IF(AND(NOT(ISBLANK(A15)),NOT(ISBLANK(B15)),NOT(ISBLANK(E15)),ISERROR(VLOOKUP(A15,'ListaN68 02-02-2025'!$A$12:$E$13375,5,0))),"Nuevo",IF(AND(NOT(ISBLANK(A15)),NOT(ISBLANK(B15)),NOT(ISBLANK(E15)),AND(E15-VLOOKUP(A15,'ListaN68 02-02-2025'!$A$12:$E$13375,5,0)>=-2,E15-VLOOKUP(A15,'ListaN68 02-02-2025'!$A$12:$E$13375,5,0)<=2)),"Igual",IF(AND(NOT(ISBLANK(A15)),NOT(ISBLANK(B15)),NOT(ISBLANK(E15)),E15-VLOOKUP(A15,'ListaN68 02-02-2025'!$A$12:$E$13375,5,0)>2),"Aumento",IF(AND(NOT(ISBLANK(A15)),NOT(ISBLANK(B15)),NOT(ISBLANK(E15)),E15-VLOOKUP(A15,'ListaN68 02-02-2025'!$A$12:$E$13375,5,0)<2),"Bajo","Error en codigo"))))))) -> Igual
A16: USBU | B16: CABLE MACHO USB A USB C 1,5MTS | C16: UM 1u | 25u | D16: 21 | E16: 2187.85 | AF16: =IF(AND(ISBLANK(A16),ISBLANK(B16),ISBLANK(E16)),"Blanco",IF(AND(ISBLANK(A16),NOT(ISBLANK(B16))),"Titulo",IF(AND(NOT(ISBLANK(A16)),NOT(ISBLANK(B16)),ISBLANK(E16),IFERROR(FIND("FF--",A16)>1,FALSE)),"F.Comercializacion",IF(AND(NOT(ISBLANK(A16)),NOT(ISBLANK(B16)),NOT(ISBLANK(E16)),ISERROR(VLOOKUP(A16,'ListaN68 02-02-2025'!$A$12:$E$13375,5,0))),"Nuevo",IF(AND(NOT(ISBLANK(A16)),NOT(ISBLANK(B16)),NOT(ISBLANK(E16)),AND(E16-VLOOKUP(A16,'ListaN68 02-02-2025'!$A$12:$E$13375,5,0)>=-2,E16-VLOOKUP(A16,'ListaN68 02-02-2025'!$A$12:$E$13375,5,0)<=2)),"Igual",IF(AND(NOT(ISBLANK(A16)),NOT(ISBLANK(B16)),NOT(ISBLANK(E16)),E16-VLOOKUP(A16,'ListaN68 02-02-2025'!$A$12:$E$13375,5,0)>2),"Aumento",IF(AND(NOT(ISBLANK(A16)),NOT(ISBLANK(B16)),NOT(ISBLANK(E16)),E16-VLOOKUP(A16,'ListaN68 02-02-2025'!$A$12:$E$13375,5,0)<2),"Bajo","Error en codigo"))))))) -> Igual
AF17: =IF(AND(ISBLANK(A17),ISBLANK(B17),ISBLANK(E17)),"Blanco",IF(AND(ISBLANK(A17),NOT(ISBLANK(B17))),"Titulo",IF(AND(NOT(ISBLANK(A17)),NOT(ISBLANK(B17)),ISBLANK(E17),IFERROR(FIND("FF--",A17)>1,FALSE)),"F.Comercializacion",IF(AND(NOT(ISBLANK(A17)),NOT(ISBLANK(B17)),NOT(ISBLANK(E17)),ISERROR(VLOOKUP(A17,'ListaN68 02-02-2025'!$A$12:$E$13375,5,0))),"Nuevo",IF(AND(NOT(ISBLANK(A17)),NOT(ISBLANK(B17)),NOT(ISBLANK(E17)),AND(E17-VLOOKUP(A17,'ListaN68 02-02-2025'!$A$12:$E$13375,5,0)>=-2,E17-VLOOKUP(A17,'ListaN68 02-02-2025'!$A$12:$E$13375,5,0)<=2)),"Igual",IF(AND(NOT(ISBLANK(A17)),NOT(ISBLANK(B17)),NOT(ISBLANK(E17)),E17-VLOOKUP(A17,'ListaN68 02-02-2025'!$A$12:$E$13375,5,0)>2),"Aumento",IF(AND(NOT(ISBLANK(A17)),NOT(ISBLANK(B17)),NOT(ISBLANK(E17)),E17-VLOOKUP(A17,'ListaN68 02-02-2025'!$A$12:$E$13375,5,0)<2),"Bajo","Error en codigo"))))))) -> Blanco
B18: TRIPLES Y ADAPTADORES | AF18: =IF(AND(ISBLANK(A18),ISBLANK(B18),ISBLANK(E18)),"Blanco",IF(AND(ISBLANK(A18),NOT(ISBLANK(B18))),"Titulo",IF(AND(NOT(ISBLANK(A18)),NOT(ISBLANK(B18)),ISBLANK(E18),IFERROR(FIND("FF--",A18)>1,FALSE)),"F.Comercializacion",IF(AND(NOT(ISBLANK(A18)),NOT(ISBLANK(B18)),NOT(ISBLANK(E18)),ISERROR(VLOOKUP(A18,'ListaN68 02-02-2025'!$A$12:$E$13375,5,0))),"Nuevo",IF(AND(NOT(ISBLANK(A18)),NOT(ISBLANK(B18)),NOT(ISBLANK(E18)),AND(E18-VLOOKUP(A18,'ListaN68 02-02-2025'!$A$12:$E$13375,5,0)>=-2,E18-VLOOKUP(A18,'ListaN68 02-02-2025'!$A$12:$E$13375,5,0)<=2)),"Igual",IF(AND(NOT(ISBLANK(A18)),NOT(ISBLANK(B18)),NOT(ISBLANK(E18)),E18-VLOOKUP(A18,'ListaN68 02-02-2025'!$A$12:$E$13375,5,0)>2),"Aumento",IF(AND(NOT(ISBLANK(A18)),NOT(ISBLANK(B18)),NOT(ISBLANK(E18)),E18-VLOOKUP(A18,'ListaN68 02-02-2025'!$A$12:$E$13375,5,0)<2),"Bajo","Error en codigo"))))))) -> Titulo
AF19: =IF(AND(ISBLANK(A19),ISBLANK(B19),ISBLANK(E19)),"Blanco",IF(AND(ISBLANK(A19),NOT(ISBLANK(B19))),"Titulo",IF(AND(NOT(ISBLANK(A19)),NOT(ISBLANK(B19)),ISBLANK(E19),IFERROR(FIND("FF--",A19)>1,FALSE)),"F.Comercializacion",IF(AND(NOT(ISBLANK(A19)),NOT(ISBLANK(B19)),NOT(ISBLANK(E19)),ISERROR(VLOOKUP(A19,'ListaN68 02-02-2025'!$A$12:$E$13375,5,0))),"Nuevo",IF(AND(NOT(ISBLANK(A19)),NOT(ISBLANK(B19)),NOT(ISBLANK(E19)),AND(E19-VLOOKUP(A19,'ListaN68 02-02-2025'!$A$12:$E$13375,5,0)>=-2,E19-VLOOKUP(A19,'ListaN68 02-02-2025'!$A$12:$E$13375,5,0)<=2)),"Igual",IF(AND(NOT(ISBLANK(A19)),NOT(ISBLANK(B19)),NOT(ISBLANK(E19)),E19-VLOOKUP(A19,'ListaN68 02-02-2025'!$A$12:$E$13375,5,0)>2),"Aumento",IF(AND(NOT(ISBLANK(A19)),NOT(ISBLANK(B19)),NOT(ISBLANK(E19)),E19-VLOOKUP(A19,'ListaN68 02-02-2025'!$A$12:$E$13375,5,0)<2),"Bajo","Error en codigo"))))))) -> Blanco
A20: 200 | B20: ADAPTADOR 2A3 T/ KALOP (M 2P - H 3P) | C20: UM 1u | 50u | 500u | D20: 21 | E20: 534.293 | AF20: =IF(AND(ISBLANK(A20),ISBLANK(B20),ISBLANK(E20)),"Blanco",IF(AND(ISBLANK(A20),NOT(ISBLANK(B20))),"Titulo",IF(AND(NOT(ISBLANK(A20)),NOT(ISBLANK(B20)),ISBLANK(E20),IFERROR(FIND("FF--",A20)>1,FALSE)),"F.Comercializacion",IF(AND(NOT(ISBLANK(A20)),NOT(ISBLANK(B20)),NOT(ISBLANK(E20)),ISERROR(VLOOKUP(A20,'ListaN68 02-02-2025'!$A$12:$E$13375,5,0))),"Nuevo",IF(AND(NOT(ISBLANK(A20)),NOT(ISBLANK(B20)),NOT(ISBLANK(E20)),AND(E20-VLOOKUP(A20,'ListaN68 02-02-2025'!$A$12:$E$13375,5,0)>=-2,E20-VLOOKUP(A20,'ListaN68 02-02-2025'!$A$12:$E$13375,5,0)<=2)),"Igual",IF(AND(NOT(ISBLANK(A20)),NOT(ISBLANK(B20)),NOT(ISBLANK(E20)),E20-VLOOKUP(A20,'ListaN68 02-02-2025'!$A$12:$E$13375,5,0)>2),"Aumento",IF(AND(NOT(ISBLANK(A20)),NOT(ISBLANK(B20)),NOT(ISBLANK(E20)),E20-VLOOKUP(A20,'ListaN68 02-02-2025'!$A$12:$E$13375,5,0)<2),"Bajo","Error en codigo"))))))) -> Igual
A21: 201 | B21: ADAPTADOR 2A3 T/ EXULT (M 2P - H 3P) | C21: UM 1u | 100u | D21: 21 | E21: 348.874 | AF21: =IF(AND(ISBLANK(A21),ISBLANK(B21),ISBLANK(E21)),"Blanco",IF(AND(ISBLANK(A21),NOT(ISBLANK(B21))),"Titulo",IF(AND(NOT(ISBLANK(A21)),NOT(ISBLANK(B21)),ISBLANK(E21),IFERROR(FIND("FF--",A21)>1,FALSE)),"F.Comercializacion",IF(AND(NOT(ISBLANK(A21)),NOT(ISBLANK(B21)),NOT(ISBLANK(E21)),ISERROR(VLOOKUP(A21,'ListaN68 02-02-2025'!$A$12:$E$13375,5,0))),"Nuevo",IF(AND(NOT(ISBLANK(A21)),NOT(ISBLANK(B21)),NOT(ISBLANK(E21)),AND(E21-VLOOKUP(A21,'ListaN68 02-02-2025'!$A$12:$E$13375,5,0)>=-2,E21-VLOOKUP(A21,'ListaN68 02-02-2025'!$A$12:$E$13375,5,0)<=2)),"Igual",IF(AND(NOT(ISBLANK(A21)),NOT(ISBLANK(B21)),NOT(ISBLANK(E21)),E21-VLOOKUP(A21,'ListaN68 02-02-2025'!$A$12:$E$13375,5,0)>2),"Aumento",IF(AND(NOT(ISBLANK(A21)),NOT(ISBLANK(B21)),NOT(ISBLANK(E21)),E21-VLOOKUP(A21,'ListaN68 02-02-2025'!$A$12:$E$13375,5,0)<2),"Bajo","Error en codigo"))))))) -> Igual
A22: 210 | B22: ADAPTADOR FICHA TURISTA | C22: UM 1u | 100u | D22: 21 | E22: 972.822 | AF22: =IF(AND(ISBLANK(A22),ISBLANK(B22),ISBLANK(E22)),"Blanco",IF(AND(ISBLANK(A22),NOT(ISBLANK(B22))),"Titulo",IF(AND(NOT(ISBLANK(A22)),NOT(ISBLANK(B22)),ISBLANK(E22),IFERROR(FIND("FF--",A22)>1,FALSE)),"F.Comercializacion",IF(AND(NOT(ISBLANK(A22)),NOT(ISBLANK(B22)),NOT(ISBLANK(E22)),ISERROR(VLOOKUP(A22,'ListaN68 02-02-2025'!$A$12:$E$13375,5,0))),"Nuevo",IF(AND(NOT(ISBLANK(A22)),NOT(ISBLANK(B22)),NOT(ISBLANK(E22)),AND(E22-VLOOKUP(A22,'ListaN68 02-02-2025'!$A$12:$E$13375,5,0)>=-2,E22-VLOOKUP(A22,'ListaN68 02-02-2025'!$A$12:$E$13375,5,0)<=2)),"Igual",IF(AND(NOT(ISBLANK(A22)),NOT(ISBLANK(B22)),NOT(ISBLANK(E22)),E22-VLOOKUP(A22,'ListaN68 02-02-2025'!$A$12:$E$13375,5,0)>2),"Aumento",IF(AND(NOT(ISBLANK(A22)),NOT(ISBLANK(B22)),NOT(ISBLANK(E22)),E22-VLOOKUP(A22,'ListaN68 02-02-2025'!$A$12:$E$13375,5,0)<2),"Bajo","Error en codigo"))))))) -> Igual
A23: 212 | B23: ADAPTADOR 3A2 MIG (PARED A F.MACHO) | C23: UM 1u | 100u | D23: 21 | E23: 919.636 | AF23: =IF(AND(ISBLANK(A23),ISBLANK(B23),ISBLANK(E23)),"Blanco",IF(AND(ISBLANK(A23),NOT(ISBLANK(B23))),"Titulo",IF(AND(NOT(ISBLANK(A23)),NOT(ISBLANK(B23)),ISBLANK(E23),IFERROR(FIND("FF--",A23)>1,FALSE)),"F.Comercializacion",IF(AND(NOT(ISBLANK(A23)),NOT(ISBLANK(B23)),NOT(ISBLANK(E23)),ISERROR(VLOOKUP(A23,'ListaN68 02-02-2025'!$A$12:$E$13375,5,0))),"Nuevo",IF(AND(NOT(ISBLANK(A23)),NOT(ISBLANK(B23)),NOT(ISBLANK(E23)),AND(E23-VLOOKUP(A23,'ListaN68 02-02-2025'!$A$12:$E$13375,5,0)>=-2,E23-VLOOKUP(A23,'ListaN68 02-02-2025'!$A$12:$E$13375,5,0)<=2)),"Igual",IF(AND(NOT(ISBLANK(A23)),NOT(ISBLANK(B23)),NOT(ISBLANK(E23)),E23-VLOOKUP(A23,'ListaN68 02-02-2025'!$A$12:$E$13375,5,0)>2),"Aumento",IF(AND(NOT(ISBLANK(A23)),NOT(ISBLANK(B23)),NOT(ISBLANK(E23)),E23-VLOOKUP(A23,'ListaN68 02-02-2025'!$A$12:$E$13375,5,0)<2),"Bajo","Error en codigo"))))))) -> Igual
A24: 215 | B24: TRIPLE IRROMPIBLE MIG | C24: UM 1u | 50u | D24: 21 | E24: 1249.887 | AF24: =IF(AND(ISBLANK(A24),ISBLANK(B24),ISBLANK(E24)),"Blanco",IF(AND(ISBLANK(A24),NOT(ISBLANK(B24))),"Titulo",IF(AND(NOT(ISBLANK(A24)),NOT(ISBLANK(B24)),ISBLANK(E24),IFERROR(FIND("FF--",A24)>1,FALSE)),"F.Comercializacion",IF(AND(NOT(ISBLANK(A24)),NOT(ISBLANK(B24)),NOT(ISBLANK(E24)),ISERROR(VLOOKUP(A24,'ListaN68 02-02-2025'!$A$12:$E$13375,5,0))),"Nuevo",IF(AND(NOT(ISBLANK(A24)),NOT(ISBLANK(B24)),NOT(ISBLANK(E24)),AND(E24-VLOOKUP(A24,'ListaN68 02-02-2025'!$A$12:$E$13375,5,0)>=-2,E24-VLOOKUP(A24,'ListaN68 02-02-2025'!$A$12:$E$13375,5,0)<=2)),"Igual",IF(AND(NOT(ISBLANK(A24)),NOT(ISBLANK(B24)),NOT(ISBLANK(E24)),E24-VLOOKUP(A24,'ListaN68 02-02-2025'!$A$12:$E$13375,5,0)>2),"Aumento",IF(AND(NOT(ISBLANK(A24)),NOT(ISBLANK(B24)),NOT(ISBLANK(E24)),E24-VLOOKUP(A24,'ListaN68 02-02-2025'!$A$12:$E$13375,5,0)<2),"Bajo","Error en codigo"))))))) -> Igual
A25: 216 | B25: TRIPLE IRROMPIBLE MIG ***CON NEUTRO**** 216 | C25: UM 1u | 50u | D25: 21 | E25: 1249.887 | AF25: =IF(AND(ISBLANK(A25),ISBLANK(B25),ISBLANK(E25)),"Blanco",IF(AND(ISBLANK(A25),NOT(ISBLANK(B25))),"Titulo",IF(AND(NOT(ISBLANK(A25)),NOT(ISBLANK(B25)),ISBLANK(E25),IFERROR(FIND("FF--",A25)>1,FALSE)),"F.Comercializacion",IF(AND(NOT(ISBLANK(A25)),NOT(ISBLANK(B25)),NOT(ISBLANK(E25)),ISERROR(VLOOKUP(A25,'ListaN68 02-02-2025'!$A$12:$E$13375,5,0))),"Nuevo",IF(AND(NOT(ISBLANK(A25)),NOT(ISBLANK(B25)),NOT(ISBLANK(E25)),AND(E25-VLOOKUP(A25,'ListaN68 02-02-2025'!$A$12:$E$13375,5,0)>=-2,E25-VLOOKUP(A25,'ListaN68 02-02-2025'!$A$12:$E$13375,5,0)<=2)),"Igual",IF(AND(NOT(ISBLANK(A25)),NOT(ISBLANK(B25)),NOT(ISBLANK(E25)),E25-VLOOKUP(A25,'ListaN68 02-02-2025'!$A$12:$E$13375,5,0)>2),"Aumento",IF(AND(NOT(ISBLANK(A25)),NOT(ISBLANK(B25)),NOT(ISBLANK(E25)),E25-VLOOKUP(A25,'ListaN68 02-02-2025'!$A$12:$E$13375,5,0)<2),"Bajo","Error en codigo"))))))) -> Igual
A26: 223 | B26: ADAPTADOR AMERICANO/ALEMAN BCO | C26: UM 1u | 100u | D26: 21 | E26: 892.423 | AF26: =IF(AND(ISBLANK(A26),ISBLANK(B26),ISBLANK(E26)),"Blanco",IF(AND(ISBLANK(A26),NOT(ISBLANK(B26))),"Titulo",IF(AND(NOT(ISBLANK(A26)),NOT(ISBLANK(B26)),ISBLANK(E26),IFERROR(FIND("FF--",A26)>1,FALSE)),"F.Comercializacion",IF(AND(NOT(ISBLANK(A26)),NOT(ISBLANK(B26)),NOT(ISBLANK(E26)),ISERROR(VLOOKUP(A26,'ListaN68 02-02-2025'!$A$12:$E$13375,5,0))),"Nuevo",IF(AND(NOT(ISBLANK(A26)),NOT(ISBLANK(B26)),NOT(ISBLANK(E26)),AND(E26-VLOOKUP(A26,'ListaN68 02-02-2025'!$A$12:$E$13375,5,0)>=-2,E26-VLOOKUP(A26,'ListaN68 02-02-2025'!$A$12:$E$13375,5,0)<=2)),"Igual",IF(AND(NOT(ISBLANK(A26)),NOT(ISBLANK(B26)),NOT(ISBLANK(E26)),E26-VLOOKUP(A26,'ListaN68 02-02-2025'!$A$12:$E$13375,5,0)>2),"Aumento",IF(AND(NOT(ISBLANK(A26)),NOT(ISBLANK(B26)),NOT(ISBLANK(E26)),E26-VLOOKUP(A26,'ListaN68 02-02-2025'!$A$12:$E$13375,5,0)<2),"Bajo","Error en codigo"))))))) -> Igual
A27: 223-N | B27: ADAPTADOR AMERICANO/ALEMAN NEGRO | C27: UM 1u | 100u | D27: 21 | E27: 892.423 | AF27: =IF(AND(ISBLANK(A27),ISBLANK(B27),ISBLANK(E27)),"Blanco",IF(AND(ISBLANK(A27),NOT(ISBLANK(B27))),"Titulo",IF(AND(NOT(ISBLANK(A27)),NOT(ISBLANK(B27)),ISBLANK(E27),IFERROR(FIND("FF--",A27)>1,FALSE)),"F.Comercializacion",IF(AND(NOT(ISBLANK(A27)),NOT(ISBLANK(B27)),NOT(ISBLANK(E27)),ISERROR(VLOOKUP(A27,'ListaN68 02-02-2025'!$A$12:$E$13375,5,0))),"Nuevo",IF(AND(NOT(ISBLANK(A27)),NOT(ISBLANK(B27)),NOT(ISBLANK(E27)),AND(E27-VLOOKUP(A27,'ListaN68 02-02-2025'!$A$12:$E$13375,5,0)>=-2,E27-VLOOKUP(A27,'ListaN68 02-02-2025'!$A$12:$E$13375,5,0)<=2)),"Igual",IF(AND(NOT(ISBLANK(A27)),NOT(ISBLANK(B27)),NOT(ISBLANK(E27)),E27-VLOOKUP(A27,'ListaN68 02-02-2025'!$A$12:$E$13375,5,0)>2),"Aumento",IF(AND(NOT(ISBLANK(A27)),NOT(ISBLANK(B27)),NOT(ISBLANK(E27)),E27-VLOOKUP(A27,'ListaN68 02-02-2025'!$A$12:$E$13375,5,0)<2),"Bajo","Error en codigo"))))))) -> Igual
A28: 224 | B28: ADAPTADOR AMERICANO/ALEMAN P/PLANA BCO | C28: UM 1u | 100u | D28: 21 | E28: 919.636 | AF28: =IF(AND(ISBLANK(A28),ISBLANK(B28),ISBLANK(E28)),"Blanco",IF(AND(ISBLANK(A28),NOT(ISBLANK(B28))),"Titulo",IF(AND(NOT(ISBLANK(A28)),NOT(ISBLANK(B28)),ISBLANK(E28),IFERROR(FIND("FF--",A28)>1,FALSE)),"F.Comercializacion",IF(AND(NOT(ISBLANK(A28)),NOT(ISBLANK(B28)),NOT(ISBLANK(E28)),ISERROR(VLOOKUP(A28,'ListaN68 02-02-2025'!$A$12:$E$13375,5,0))),"Nuevo",IF(AND(NOT(ISBLANK(A28)),NOT(ISBLANK(B28)),NOT(ISBLANK(E28)),AND(E28-VLOOKUP(A28,'ListaN68 02-02-2025'!$A$12:$E$13375,5,0)>=-2,E28-VLOOKUP(A28,'ListaN68 02-02-2025'!$A$12:$E$13375,5,0)<=2)),"Igual",IF(AND(NOT(ISBLANK(A28)),NOT(ISBLANK(B28)),NOT(ISBLANK(E28)),E28-VLOOKUP(A28,'ListaN68 02-02-2025'!$A$12:$E$13375,5,0)>2),"Aumento",IF(AND(NOT(ISBLANK(A28)),NOT(ISBLANK(B28)),NOT(ISBLANK(E28)),E28-VLOOKUP(A28,'ListaN68 02-02-2025'!$A$12:$E$13375,5,0)<2),"Bajo","Error en codigo"))))))) -> Igual
A29: 224-N | B29: ADAPTADOR AMERICANO/ALEMAN P/PLANA NEGRO | C29: UM 1u | 100u | D29: 21 | E29: 919.636 | AF29: =IF(AND(ISBLANK(A29),ISBLANK(B29),ISBLANK(E29)),"Blanco",IF(AND(ISBLANK(A29),NOT(ISBLANK(B29))),"Titulo",IF(AND(NOT(ISBLANK(A29)),NOT(ISBLANK(B29)),ISBLANK(E29),IFERROR(FIND("FF--",A29)>1,FALSE)),"F.Comercializacion",IF(AND(NOT(ISBLANK(A29)),NOT(ISBLANK(B29)),NOT(ISBLANK(E29)),ISERROR(VLOOKUP(A29,'ListaN68 02-02-2025'!$A$12:$E$13375,5,0))),"Nuevo",IF(AND(NOT(ISBLANK(A29)),NOT(ISBLANK(B29)),NOT(ISBLANK(E29)),AND(E29-VLOOKUP(A29,'ListaN68 02-02-2025'!$A$12:$E$13375,5,0)>=-2,E29-VLOOKUP(A29,'ListaN68 02-02-2025'!$A$12:$E$13375,5,0)<=2)),"Igual",IF(AND(NOT(ISBLANK(A29)),NOT(ISBLANK(B29)),NOT(ISBLANK(E29)),E29-VLOOKUP(A29,'ListaN68 02-02-2025'!$A$12:$E$13375,5,0)>2),"Aumento",IF(AND(NOT(ISBLANK(A29)),NOT(ISBLANK(B29)),NOT(ISBLANK(E29)),E29-VLOOKUP(A29,'ListaN68 02-02-2025'!$A$12:$E$13375,5,0)<2),"Bajo","Error en codigo"))))))) -> Igual
A30: 230 | B30: ADAPTADOR MULTIFUNCION | C30: UM 1u | 100u | D30: 21 | E30: 941.899 | AF30: =IF(AND(ISBLANK(A30),ISBLANK(B30),ISBLANK(E30)),"Blanco",IF(AND(ISBLANK(A30),NOT(ISBLANK(B30))),"Titulo",IF(AND(NOT(ISBLANK(A30)),NOT(ISBLANK(B30)),ISBLANK(E30),IFERROR(FIND("FF--",A30)>1,FALSE)),"F.Comercializacion",IF(AND(NOT(ISBLANK(A30)),NOT(ISBLANK(B30)),NOT(ISBLANK(E30)),ISERROR(VLOOKUP(A30,'ListaN68 02-02-2025'!$A$12:$E$13375,5,0))),"Nuevo",IF(AND(NOT(ISBLANK(A30)),NOT(ISBLANK(B30)),NOT(ISBLANK(E30)),AND(E30-VLOOKUP(A30,'ListaN68 02-02-2025'!$A$12:$E$13375,5,0)>=-2,E30-VLOOKUP(A30,'ListaN68 02-02-2025'!$A$12:$E$13375,5,0)<=2)),"Igual",IF(AND(NOT(ISBLANK(A30)),NOT(ISBLANK(B30)),NOT(ISBLANK(E30)),E30-VLOOKUP(A30,'ListaN68 02-02-2025'!$A$12:$E$13375,5,0)>2),"Aumento",IF(AND(NOT(ISBLANK(A30)),NOT(ISBLANK(B30)),NOT(ISBLANK(E30)),E30-VLOOKUP(A30,'ListaN68 02-02-2025'!$A$12:$E$13375,5,0)<2),"Bajo","Error en codigo"))))))) -> Igual
A31: LWW-K3 | B31: ADAPTADOR VIAJERO UNIVERSAL C/ FICHA | C31: UM 1u | 20u | 600u | D31: 21 | E31: 1561.215 | F31: -0.0068259386 | AF31: =IF(AND(ISBLANK(A31),ISBLANK(B31),ISBLANK(E31)),"Blanco",IF(AND(ISBLANK(A31),NOT(ISBLANK(B31))),"Titulo",IF(AND(NOT(ISBLANK(A31)),NOT(ISBLANK(B31)),ISBLANK(E31),IFERROR(FIND("FF--",A31)>1,FALSE)),"F.Comercializacion",IF(AND(NOT(ISBLANK(A31)),NOT(ISBLANK(B31)),NOT(ISBLANK(E31)),ISERROR(VLOOKUP(A31,'ListaN68 02-02-2025'!$A$12:$E$13375,5,0))),"Nuevo",IF(AND(NOT(ISBLANK(A31)),NOT(ISBLANK(B31)),NOT(ISBLANK(E31)),AND(E31-VLOOKUP(A31,'ListaN68 02-02-2025'!$A$12:$E$13375,5,0)>=-2,E31-VLOOKUP(A31,'ListaN68 02-02-2025'!$A$12:$E$13375,5,0)<=2)),"Igual",IF(AND(NOT(ISBLANK(A31)),NOT(ISBLANK(B31)),NOT(ISBLANK(E31)),E31-VLOOKUP(A31,'ListaN68 02-02-2025'!$A$12:$E$13375,5,0)>2),"Aumento",IF(AND(NOT(ISBLANK(A31)),NOT(ISBLANK(B31)),NOT(ISBLANK(E31)),E31-VLOOKUP(A31,'ListaN68 02-02-2025'!$A$12:$E$13375,5,0)<2),"Bajo","Error en codigo"))))))) -> Bajo
A32: MU-A3 | B32: ADAPTADOR VIAJERO S/USB | C32: UM 1u | 20u | 200u | D32: 21 | E32: 3417.795 | F32: -0.0068259386 | AF32: =IF(AND(ISBLANK(A32),ISBLANK(B32),ISBLANK(E32)),"Blanco",IF(AND(ISBLANK(A32),NOT(ISBLANK(B32))),"Titulo",IF(AND(NOT(ISBLANK(A32)),NOT(ISBLANK(B32)),ISBLANK(E32),IFERROR(FIND("FF--",A32)>1,FALSE)),"F.Comercializacion",IF(AND(NOT(ISBLANK(A32)),NOT(ISBLANK(B32)),NOT(ISBLANK(E32)),ISERROR(VLOOKUP(A32,'ListaN68 02-02-2025'!$A$12:$E$13375,5,0))),"Nuevo",IF(AND(NOT(ISBLANK(A32)),NOT(ISBLANK(B32)),NOT(ISBLANK(E32)),AND(E32-VLOOKUP(A32,'ListaN68 02-02-2025'!$A$12:$E$13375,5,0)>=-2,E32-VLOOKUP(A32,'ListaN68 02-02-2025'!$A$12:$E$13375,5,0)<=2)),"Igual",IF(AND(NOT(ISBLANK(A32)),NOT(ISBLANK(B32)),NOT(ISBLANK(E32)),E32-VLOOKUP(A32,'ListaN68 02-02-2025'!$A$12:$E$13375,5,0)>2),"Aumento",IF(AND(NOT(ISBLANK(A32)),NOT(ISBLANK(B32)),NOT(ISBLANK(E32)),E32-VLOOKUP(A32,'ListaN68 02-02-2025'!$A$12:$E$13375,5,0)<2),"Bajo","Error en codigo"))))))) -> Bajo
A33: MU-A4 | B33: ADAPTADOR VIAJERO C/USB | C33: UM 1u | 20u | 200u | D33: 21 | E33: 8523.39 | F33: -0.0068259386 | AF33: =IF(AND(ISBLANK(A33),ISBLANK(B33),ISBLANK(E33)),"Blanco",IF(AND(ISBLANK(A33),NOT(ISBLANK(B33))),"Titulo",IF(AND(NOT(ISBLANK(A33)),NOT(ISBLANK(B33)),ISBLANK(E33),IFERROR(FIND("FF--",A33)>1,FALSE)),"F.Comercializacion",IF(AND(NOT(ISBLANK(A33)),NOT(ISBLANK(B33)),NOT(ISBLANK(E33)),ISERROR(VLOOKUP(A33,'ListaN68 02-02-2025'!$A$12:$E$13375,5,0))),"Nuevo",IF(AND(NOT(ISBLANK(A33)),NOT(ISBLANK(B33)),NOT(ISBLANK(E33)),AND(E33-VLOOKUP(A33,'ListaN68 02-02-2025'!$A$12:$E$13375,5,0)>=-2,E33-VLOOKUP(A33,'ListaN68 02-02-2025'!$A$12:$E$13375,5,0)<=2)),"Igual",IF(AND(NOT(ISBLANK(A33)),NOT(ISBLANK(B33)),NOT(ISBLANK(E33)),E33-VLOOKUP(A33,'ListaN68 02-02-2025'!$A$12:$E$13375,5,0)>2),"Aumento",IF(AND(NOT(ISBLANK(A33)),NOT(ISBLANK(B33)),NOT(ISBLANK(E33)),E33-VLOOKUP(A33,'ListaN68 02-02-2025'!$A$12:$E$13375,5,0)<2),"Bajo","Error en codigo"))))))) -> Bajo
A34: PE-727 | B34: ADAPTADOR VIAJERO UNIVERSAL | C34: UM 1u | 20u | 1000u | D34: 21 | E34: 593.64 | F34: -0.0068259386 | AF34: =IF(AND(ISBLANK(A34),ISBLANK(B34),ISBLANK(E34)),"Blanco",IF(AND(ISBLANK(A34),NOT(ISBLANK(B34))),"Titulo",IF(AND(NOT(ISBLANK(A34)),NOT(ISBLANK(B34)),ISBLANK(E34),IFERROR(FIND("FF--",A34)>1,FALSE)),"F.Comercializacion",IF(AND(NOT(ISBLANK(A34)),NOT(ISBLANK(B34)),NOT(ISBLANK(E34)),ISERROR(VLOOKUP(A34,'ListaN68 02-02-2025'!$A$12:$E$13375,5,0))),"Nuevo",IF(AND(NOT(ISBLANK(A34)),NOT(ISBLANK(B34)),NOT(ISBLANK(E34)),AND(E34-VLOOKUP(A34,'ListaN68 02-02-2025'!$A$12:$E$13375,5,0)>=-2,E34-VLOOKUP(A34,'ListaN68 02-02-2025'!$A$12:$E$13375,5,0)<=2)),"Igual",IF(AND(NOT(ISBLANK(A34)),NOT(ISBLANK(B34)),NOT(ISBLANK(E34)),E34-VLOOKUP(A34,'ListaN68 02-02-2025'!$A$12:$E$13375,5,0)>2),"Aumento",IF(AND(NOT(ISBLANK(A34)),NOT(ISBLANK(B34)),NOT(ISBLANK(E34)),E34-VLOOKUP(A34,'ListaN68 02-02-2025'!$A$12:$E$13375,5,0)<2),"Bajo","Error en codigo"))))))) -> Bajo
AF35: =IF(AND(ISBLANK(A35),ISBLANK(B35),ISBLANK(E35)),"Blanco",IF(AND(ISBLANK(A35),NOT(ISBLANK(B35))),"Titulo",IF(AND(NOT(ISBLANK(A35)),NOT(ISBLANK(B35)),ISBLANK(E35),IFERROR(FIND("FF--",A35)>1,FALSE)),"F.Comercializacion",IF(AND(NOT(ISBLANK(A35)),NOT(ISBLANK(B35)),NOT(ISBLANK(E35)),ISERROR(VLOOKUP(A35,'ListaN68 02-02-2025'!$A$12:$E$13375,5,0))),"Nuevo",IF(AND(NOT(ISBLANK(A35)),NOT(ISBLANK(B35)),NOT(ISBLANK(E35)),AND(E35-VLOOKUP(A35,'ListaN68 02-02-2025'!$A$12:$E$13375,5,0)>=-2,E35-VLOOKUP(A35,'ListaN68 02-02-2025'!$A$12:$E$13375,5,0)<=2)),"Igual",IF(AND(NOT(ISBLANK(A35)),NOT(ISBLANK(B35)),NOT(ISBLANK(E35)),E35-VLOOKUP(A35,'ListaN68 02-02-2025'!$A$12:$E$13375,5,0)>2),"Aumento",IF(AND(NOT(ISBLANK(A35)),NOT(ISBLANK(B35)),NOT(ISBLANK(E35)),E35-VLOOKUP(A35,'ListaN68 02-02-2025'!$A$12:$E$13375,5,0)<2),"Bajo","Error en codigo"))))))) -> Blanco
B36: MULTI-FICHAS | AF36: =IF(AND(ISBLANK(A36),ISBLANK(B36),ISBLANK(E36)),"Blanco",IF(AND(ISBLANK(A36),NOT(ISBLANK(B36))),"Titulo",IF(AND(NOT(ISBLANK(A36)),NOT(ISBLANK(B36)),ISBLANK(E36),IFERROR(FIND("FF--",A36)>1,FALSE)),"F.Comercializacion",IF(AND(NOT(ISBLANK(A36)),NOT(ISBLANK(B36)),NOT(ISBLANK(E36)),ISERROR(VLOOKUP(A36,'ListaN68 02-02-2025'!$A$12:$E$13375,5,0))),"Nuevo",IF(AND(NOT(ISBLANK(A36)),NOT(ISBLANK(B36)),NOT(ISBLANK(E36)),AND(E36-VLOOKUP(A36,'ListaN68 02-02-2025'!$A$12:$E$13375,5,0)>=-2,E36-VLOOKUP(A36,'ListaN68 02-02-2025'!$A$12:$E$13375,5,0)<=2)),"Igual",IF(AND(NOT(ISBLANK(A36)),NOT(ISBLANK(B36)),NOT(ISBLANK(E36)),E36-VLOOKUP(A36,'ListaN68 02-02-2025'!$A$12:$E$13375,5,0)>2),"Aumento",IF(AND(NOT(ISBLANK(A36)),NOT(ISBLANK(B36)),NOT(ISBLANK(E36)),E36-VLOOKUP(A36,'ListaN68 02-02-2025'!$A$12:$E$13375,5,0)<2),"Bajo","Error en codigo"))))))) -> Titulo
AF37: =IF(AND(ISBLANK(A37),ISBLANK(B37),ISBLANK(E37)),"Blanco",IF(AND(ISBLANK(A37),NOT(ISBLANK(B37))),"Titulo",IF(AND(NOT(ISBLANK(A37)),NOT(ISBLANK(B37)),ISBLANK(E37),IFERROR(FIND("FF--",A37)>1,FALSE)),"F.Comercializacion",IF(AND(NOT(ISBLANK(A37)),NOT(ISBLANK(B37)),NOT(ISBLANK(E37)),ISERROR(VLOOKUP(A37,'ListaN68 02-02-2025'!$A$12:$E$13375,5,0))),"Nuevo",IF(AND(NOT(ISBLANK(A37)),NOT(ISBLANK(B37)),NOT(ISBLANK(E37)),AND(E37-VLOOKUP(A37,'ListaN68 02-02-2025'!$A$12:$E$13375,5,0)>=-2,E37-VLOOKUP(A37,'ListaN68 02-02-2025'!$A$12:$E$13375,5,0)<=2)),"Igual",IF(AND(NOT(ISBLANK(A37)),NOT(ISBLANK(B37)),NOT(ISBLANK(E37)),E37-VLOOKUP(A37,'ListaN68 02-02-2025'!$A$12:$E$13375,5,0)>2),"Aumento",IF(AND(NOT(ISBLANK(A37)),NOT(ISBLANK(B37)),NOT(ISBLANK(E37)),E37-VLOOKUP(A37,'ListaN68 02-02-2025'!$A$12:$E$13375,5,0)<2),"Bajo","Error en codigo"))))))) -> Blanco
A38: 127-60001 | B38: TOMA MULTIPLE DOBLE PATA CHATA BLANCA RICHI | C38: UM 1u | 150u | D38: 21 | E38: 1598.136 | AF38: =IF(AND(ISBLANK(A38),ISBLANK(B38),ISBLANK(E38)),"Blanco",IF(AND(ISBLANK(A38),NOT(ISBLANK(B38))),"Titulo",IF(AND(NOT(ISBLANK(A38)),NOT(ISBLANK(B38)),ISBLANK(E38),IFERROR(FIND("FF--",A38)>1,FALSE)),"F.Comercializacion",IF(AND(NOT(ISBLANK(A38)),NOT(ISBLANK(B38)),NOT(ISBLANK(E38)),ISERROR(VLOOKUP(A38,'ListaN68 02-02-2025'!$A$12:$E$13375,5,0))),"Nuevo",IF(AND(NOT(ISBLANK(A38)),NOT(ISBLANK(B38)),NOT(ISBLANK(E38)),AND(E38-VLOOKUP(A38,'ListaN68 02-02-2025'!$A$12:$E$13375,5,0)>=-2,E38-VLOOKUP(A38,'ListaN68 02-02-2025'!$A$12:$E$13375,5,0)<=2)),"Igual",IF(AND(NOT(ISBLANK(A38)),NOT(ISBLANK(B38)),NOT(ISBLANK(E38)),E38-VLOOKUP(A38,'ListaN68 02-02-2025'!$A$12:$E$13375,5,0)>2),"Aumento",IF(AND(NOT(ISBLANK(A38)),NOT(ISBLANK(B38)),NOT(ISBLANK(E38)),E38-VLOOKUP(A38,'ListaN68 02-02-2025'!$A$12:$E$13375,5,0)<2),"Bajo","Error en codigo"))))))) -> Igual
A39: 127-61001 | B39: TOMA MULTIPLE DOBLE PATA REDONDA BLANCA RICHI | C39: UM 1u | 150u | D39: 21 | E39: 1598.136 | AF39: =IF(AND(ISBLANK(A39),ISBLANK(B39),ISBLANK(E39)),"Blanco",IF(AND(ISBLANK(A39),NOT(ISBLANK(B39))),"Titulo",IF(AND(NOT(ISBLANK(A39)),NOT(ISBLANK(B39)),ISBLANK(E39),IFERROR(FIND("FF--",A39)>1,FALSE)),"F.Comercializacion",IF(AND(NOT(ISBLANK(A39)),NOT(ISBLANK(B39)),NOT(ISBLANK(E39)),ISERROR(VLOOKUP(A39,'ListaN68 02-02-2025'!$A$12:$E$13375,5,0))),"Nuevo",IF(AND(NOT(ISBLANK(A39)),NOT(ISBLANK(B39)),NOT(ISBLANK(E39)),AND(E39-VLOOKUP(A39,'ListaN68 02-02-2025'!$A$12:$E$13375,5,0)>=-2,E39-VLOOKUP(A39,'ListaN68 02-02-2025'!$A$12:$E$13375,5,0)<=2)),"Igual",IF(AND(NOT(ISBLANK(A39)),NOT(ISBLANK(B39)),NOT(ISBLANK(E39)),E39-VLOOKUP(A39,'ListaN68 02-02-2025'!$A$12:$E$13375,5,0)>2),"Aumento",IF(AND(NOT(ISBLANK(A39)),NOT(ISBLANK(B39)),NOT(ISBLANK(E39)),E39-VLOOKUP(A39,'ListaN68 02-02-2025'!$A$12:$E$13375,5,0)<2),"Bajo","Error en codigo"))))))) -> Igual
A40: 3001 | B40: MULTIFICHA TRIPLE PIRAMIDE PREMIUM C/NEU | C40: UM 1u | 100u | D40: 21 | E40: 2707.25 | AF40: =IF(AND(ISBLANK(A40),ISBLANK(B40),ISBLANK(E40)),"Blanco",IF(AND(ISBLANK(A40),NOT(ISBLANK(B40))),"Titulo",IF(AND(NOT(ISBLANK(A40)),NOT(ISBLANK(B40)),ISBLANK(E40),IFERROR(FIND("FF--",A40)>1,FALSE)),"F.Comercializacion",IF(AND(NOT(ISBLANK(A40)),NOT(ISBLANK(B40)),NOT(ISBLANK(E40)),ISERROR(VLOOKUP(A40,'ListaN68 02-02-2025'!$A$12:$E$13375,5,0))),"Nuevo",IF(AND(NOT(ISBLANK(A40)),NOT(ISBLANK(B40)),NOT(ISBLANK(E40)),AND(E40-VLOOKUP(A40,'ListaN68 02-02-2025'!$A$12:$E$13375,5,0)>=-2,E40-VLOOKUP(A40,'ListaN68 02-02-2025'!$A$12:$E$13375,5,0)<=2)),"Igual",IF(AND(NOT(ISBLANK(A40)),NOT(ISBLANK(B40)),NOT(ISBLANK(E40)),E40-VLOOKUP(A40,'ListaN68 02-02-2025'!$A$12:$E$13375,5,0)>2),"Aumento",IF(AND(NOT(ISBLANK(A40)),NOT(ISBLANK(B40)),NOT(ISBLANK(E40)),E40-VLOOKUP(A40,'ListaN68 02-02-2025'!$A$12:$E$13375,5,0)<2),"Bajo","Error en codigo"))))))) -> Igual
A41: 3002 | B41: MULTIFICHA TRIPLE PIRAMIDE PREMIUM | C41: UM 1u | 100u | D41: 21 | E41: 2436 | AF41: =IF(AND(ISBLANK(A41),ISBLANK(B41),ISBLANK(E41)),"Blanco",IF(AND(ISBLANK(A41),NOT(ISBLANK(B41))),"Titulo",IF(AND(NOT(ISBLANK(A41)),NOT(ISBLANK(B41)),ISBLANK(E41),IFERROR(FIND("FF--",A41)>1,FALSE)),"F.Comercializacion",IF(AND(NOT(ISBLANK(A41)),NOT(ISBLANK(B41)),NOT(ISBLANK(E41)),ISERROR(VLOOKUP(A41,'ListaN68 02-02-2025'!$A$12:$E$13375,5,0))),"Nuevo",IF(AND(NOT(ISBLANK(A41)),NOT(ISBLANK(B41)),NOT(ISBLANK(E41)),AND(E41-VLOOKUP(A41,'ListaN68 02-02-2025'!$A$12:$E$13375,5,0)>=-2,E41-VLOOKUP(A41,'ListaN68 02-02-2025'!$A$12:$E$13375,5,0)<=2)),"Igual",IF(AND(NOT(ISBLANK(A41)),NOT(ISBLANK(B41)),NOT(ISBLANK(E41)),E41-VLOOKUP(A41,'ListaN68 02-02-2025'!$A$12:$E$13375,5,0)>2),"Aumento",IF(AND(NOT(ISBLANK(A41)),NOT(ISBLANK(B41)),NOT(ISBLANK(E41)),E41-VLOOKUP(A41,'ListaN68 02-02-2025'!$A$12:$E$13375,5,0)<2),"Bajo","Error en codigo"))))))) -> Igual
A42: MF2 | B42: MULTI-FICHA DOBLE | C42: UM 1u | 80u | D42: 21 | E42: 1551.919 | AF42: =IF(AND(ISBLANK(A42),ISBLANK(B42),ISBLANK(E42)),"Blanco",IF(AND(ISBLANK(A42),NOT(ISBLANK(B42))),"Titulo",IF(AND(NOT(ISBLANK(A42)),NOT(ISBLANK(B42)),ISBLANK(E42),IFERROR(FIND("FF--",A42)>1,FALSE)),"F.Comercializacion",IF(AND(NOT(ISBLANK(A42)),NOT(ISBLANK(B42)),NOT(ISBLANK(E42)),ISERROR(VLOOKUP(A42,'ListaN68 02-02-2025'!$A$12:$E$13375,5,0))),"Nuevo",IF(AND(NOT(ISBLANK(A42)),NOT(ISBLANK(B42)),NOT(ISBLANK(E42)),AND(E42-VLOOKUP(A42,'ListaN68 02-02-2025'!$A$12:$E$13375,5,0)>=-2,E42-VLOOKUP(A42,'ListaN68 02-02-2025'!$A$12:$E$13375,5,0)<=2)),"Igual",IF(AND(NOT(ISBLANK(A42)),NOT(ISBLANK(B42)),NOT(ISBLANK(E42)),E42-VLOOKUP(A42,'ListaN68 02-02-2025'!$A$12:$E$13375,5,0)>2),"Aumento",IF(AND(NOT(ISBLANK(A42)),NOT(ISBLANK(B42)),NOT(ISBLANK(E42)),E42-VLOOKUP(A42,'ListaN68 02-02-2025'!$A$12:$E$13375,5,0)<2),"Bajo","Error en codigo"))))))) -> Nuevo
A43: MF2C | B43: MULTI-FICHA DOBLE C/NEU | C43: UM 1u | 80u | D43: 21 | E43: 1551.919 | AF43: =IF(AND(ISBLANK(A43),ISBLANK(B43),ISBLANK(E43)),"Blanco",IF(AND(ISBLANK(A43),NOT(ISBLANK(B43))),"Titulo",IF(AND(NOT(ISBLANK(A43)),NOT(ISBLANK(B43)),ISBLANK(E43),IFERROR(FIND("FF--",A43)>1,FALSE)),"F.Comercializacion",IF(AND(NOT(ISBLANK(A43)),NOT(ISBLANK(B43)),NOT(ISBLANK(E43)),ISERROR(VLOOKUP(A43,'ListaN68 02-02-2025'!$A$12:$E$13375,5,0))),"Nuevo",IF(AND(NOT(ISBLANK(A43)),NOT(ISBLANK(B43)),NOT(ISBLANK(E43)),AND(E43-VLOOKUP(A43,'ListaN68 02-02-2025'!$A$12:$E$13375,5,0)>=-2,E43-VLOOKUP(A43,'ListaN68 02-02-2025'!$A$12:$E$13375,5,0)<=2)),"Igual",IF(AND(NOT(ISBLANK(A43)),NOT(ISBLANK(B43)),NOT(ISBLANK(E43)),E43-VLOOKUP(A43,'ListaN68 02-02-2025'!$A$12:$E$13375,5,0)>2),"Aumento",IF(AND(NOT(ISBLANK(A43)),NOT(ISBLANK(B43)),NOT(ISBLANK(E43)),E43-VLOOKUP(A43,'ListaN68 02-02-2025'!$A$12:$E$13375,5,0)<2),"Bajo","Error en codigo"))))))) -> Nuevo
AF44: =IF(AND(ISBLANK(A44),ISBLANK(B44),ISBLANK(E44)),"Blanco",IF(AND(ISBLANK(A44),NOT(ISBLANK(B44))),"Titulo",IF(AND(NOT(ISBLANK(A44)),NOT(ISBLANK(B44)),ISBLANK(E44),IFERROR(FIND("FF--",A44)>1,FALSE)),"F.Comercializacion",IF(AND(NOT(ISBLANK(A44)),NOT(ISBLANK(B44)),NOT(ISBLANK(E44)),ISERROR(VLOOKUP(A44,'ListaN68 02-02-2025'!$A$12:$E$13375,5,0))),"Nuevo",IF(AND(NOT(ISBLANK(A44)),NOT(ISBLANK(B44)),NOT(ISBLANK(E44)),AND(E44-VLOOKUP(A44,'ListaN68 02-02-2025'!$A$12:$E$13375,5,0)>=-2,E44-VLOOKUP(A44,'ListaN68 02-02-2025'!$A$12:$E$13375,5,0)<=2)),"Igual",IF(AND(NOT(ISBLANK(A44)),NOT(ISBLANK(B44)),NOT(ISBLANK(E44)),E44-VLOOKUP(A44,'ListaN68 02-02-2025'!$A$12:$E$13375,5,0)>2),"Aumento",IF(AND(NOT(ISBLANK(A44)),NOT(ISBLANK(B44)),NOT(ISBLANK(E44)),E44-VLOOKUP(A44,'ListaN68 02-02-2025'!$A$12:$E$13375,5,0)<2),"Bajo","Error en codigo"))))))) -> Blanco
B45: FICHAS | AF45: =IF(AND(ISBLANK(A45),ISBLANK(B45),ISBLANK(E45)),"Blanco",IF(AND(ISBLANK(A45),NOT(ISBLANK(B45))),"Titulo",IF(AND(NOT(ISBLANK(A45)),NOT(ISBLANK(B45)),ISBLANK(E45),IFERROR(FIND("FF--",A45)>1,FALSE)),"F.Comercializacion",IF(AND(NOT(ISBLANK(A45)),NOT(ISBLANK(B45)),NOT(ISBLANK(E45)),ISERROR(VLOOKUP(A45,'ListaN68 02-02-2025'!$A$12:$E$13375,5,0))),"Nuevo",IF(AND(NOT(ISBLANK(A45)),NOT(ISBLANK(B45)),NOT(ISBLANK(E45)),AND(E45-VLOOKUP(A45,'ListaN68 02-02-2025'!$A$12:$E$13375,5,0)>=-2,E45-VLOOKUP(A45,'ListaN68 02-02-2025'!$A$12:$E$13375,5,0)<=2)),"Igual",IF(AND(NOT(ISBLANK(A45)),NOT(ISBLANK(B45)),NOT(ISBLANK(E45)),E45-VLOOKUP(A45,'ListaN68 02-02-2025'!$A$12:$E$13375,5,0)>2),"Aumento",IF(AND(NOT(ISBLANK(A45)),NOT(ISBLANK(B45)),NOT(ISBLANK(E45)),E45-VLOOKUP(A45,'ListaN68 02-02-2025'!$A$12:$E$13375,5,0)<2),"Bajo","Error en codigo"))))))) -> Titulo
AF46: =IF(AND(ISBLANK(A46),ISBLANK(B46),ISBLANK(E46)),"Blanco",IF(AND(ISBLANK(A46),NOT(ISBLANK(B46))),"Titulo",IF(AND(NOT(ISBLANK(A46)),NOT(ISBLANK(B46)),ISBLANK(E46),IFERROR(FIND("FF--",A46)>1,FALSE)),"F.Comercializacion",IF(AND(NOT(ISBLANK(A46)),NOT(ISBLANK(B46)),NOT(ISBLANK(E46)),ISERROR(VLOOKUP(A46,'ListaN68 02-02-2025'!$A$12:$E$13375,5,0))),"Nuevo",IF(AND(NOT(ISBLANK(A46)),NOT(ISBLANK(B46)),NOT(ISBLANK(E46)),AND(E46-VLOOKUP(A46,'ListaN68 02-02-2025'!$A$12:$E$13375,5,0)>=-2,E46-VLOOKUP(A46,'ListaN68 02-02-2025'!$A$12:$E$13375,5,0)<=2)),"Igual",IF(AND(NOT(ISBLANK(A46)),NOT(ISBLANK(B46)),NOT(ISBLANK(E46)),E46-VLOOKUP(A46,'ListaN68 02-02-2025'!$A$12:$E$13375,5,0)>2),"Aumento",IF(AND(NOT(ISBLANK(A46)),NOT(ISBLANK(B46)),NOT(ISBLANK(E46)),E46-VLOOKUP(A46,'ListaN68 02-02-2025'!$A$12:$E$13375,5,0)<2),"Bajo","Error en codigo"))))))) -> Blanco
A47: 121 | B47: FICHA LONGITUDINAL C/NEU MACHO BLANCO MIG | C47: UM 1u | 50u | D47: 21 | E47: 957.856 | AF47: =IF(AND(ISBLANK(A47),ISBLANK(B47),ISBLANK(E47)),"Blanco",IF(AND(ISBLANK(A47),NOT(ISBLANK(B47))),"Titulo",IF(AND(NOT(ISBLANK(A47)),NOT(ISBLANK(B47)),ISBLANK(E47),IFERROR(FIND("FF--",A47)>1,FALSE)),"F.Comercializacion",IF(AND(NOT(ISBLANK(A47)),NOT(ISBLANK(B47)),NOT(ISBLANK(E47)),ISERROR(VLOOKUP(A47,'ListaN68 02-02-2025'!$A$12:$E$13375,5,0))),"Nuevo",IF(AND(NOT(ISBLANK(A47)),NOT(ISBLANK(B47)),NOT(ISBLANK(E47)),AND(E47-VLOOKUP(A47,'ListaN68 02-02-2025'!$A$12:$E$13375,5,0)>=-2,E47-VLOOKUP(A47,'ListaN68 02-02-2025'!$A$12:$E$13375,5,0)<=2)),"Igual",IF(AND(NOT(ISBLANK(A47)),NOT(ISBLANK(B47)),NOT(ISBLANK(E47)),E47-VLOOKUP(A47,'ListaN68 02-02-2025'!$A$12:$E$13375,5,0)>2),"Aumento",IF(AND(NOT(ISBLANK(A47)),NOT(ISBLANK(B47)),NOT(ISBLANK(E47)),E47-VLOOKUP(A47,'ListaN68 02-02-2025'!$A$12:$E$13375,5,0)<2),"Bajo","Error en codigo"))))))) -> Igual
A48: 121/N | B48: FICHA LONGITUDINAL C/NEU MACHO NEGRO MIG | C48: UM 1u | 50u | D48: 21 | E48: 957.856 | AF48: =IF(AND(ISBLANK(A48),ISBLANK(B48),ISBLANK(E48)),"Blanco",IF(AND(ISBLANK(A48),NOT(ISBLANK(B48))),"Titulo",IF(AND(NOT(ISBLANK(A48)),NOT(ISBLANK(B48)),ISBLANK(E48),IFERROR(FIND("FF--",A48)>1,FALSE)),"F.Comercializacion",IF(AND(NOT(ISBLANK(A48)),NOT(ISBLANK(B48)),NOT(ISBLANK(E48)),ISERROR(VLOOKUP(A48,'ListaN68 02-02-2025'!$A$12:$E$13375,5,0))),"Nuevo",IF(AND(NOT(ISBLANK(A48)),NOT(ISBLANK(B48)),NOT(ISBLANK(E48)),AND(E48-VLOOKUP(A48,'ListaN68 02-02-2025'!$A$12:$E$13375,5,0)>=-2,E48-VLOOKUP(A48,'ListaN68 02-02-2025'!$A$12:$E$13375,5,0)<=2)),"Igual",IF(AND(NOT(ISBLANK(A48)),NOT(ISBLANK(B48)),NOT(ISBLANK(E48)),E48-VLOOKUP(A48,'ListaN68 02-02-2025'!$A$12:$E$13375,5,0)>2),"Aumento",IF(AND(NOT(ISBLANK(A48)),NOT(ISBLANK(B48)),NOT(ISBLANK(E48)),E48-VLOOKUP(A48,'ListaN68 02-02-2025'!$A$12:$E$13375,5,0)<2),"Bajo","Error en codigo"))))))) -> Igual
A49: 227 | B49: FICHA LONGITUDINAL C/NEU HEMBRA BLANCO MIG | C49: UM 1u | 50u | D49: 21 | E49: 1030.586 | AF49: =IF(AND(ISBLANK(A49),ISBLANK(B49),ISBLANK(E49)),"Blanco",IF(AND(ISBLANK(A49),NOT(ISBLANK(B49))),"Titulo",IF(AND(NOT(ISBLANK(A49)),NOT(ISBLANK(B49)),ISBLANK(E49),IFERROR(FIND("FF--",A49)>1,FALSE)),"F.Comercializacion",IF(AND(NOT(ISBLANK(A49)),NOT(ISBLANK(B49)),NOT(ISBLANK(E49)),ISERROR(VLOOKUP(A49,'ListaN68 02-02-2025'!$A$12:$E$13375,5,0))),"Nuevo",IF(AND(NOT(ISBLANK(A49)),NOT(ISBLANK(B49)),NOT(ISBLANK(E49)),AND(E49-VLOOKUP(A49,'ListaN68 02-02-2025'!$A$12:$E$13375,5,0)>=-2,E49-VLOOKUP(A49,'ListaN68 02-02-2025'!$A$12:$E$13375,5,0)<=2)),"Igual",IF(AND(NOT(ISBLANK(A49)),NOT(ISBLANK(B49)),NOT(ISBLANK(E49)),E49-VLOOKUP(A49,'ListaN68 02-02-2025'!$A$12:$E$13375,5,0)>2),"Aumento",IF(AND(NOT(ISBLANK(A49)),NOT(ISBLANK(B49)),NOT(ISBLANK(E49)),E49-VLOOKUP(A49,'ListaN68 02-02-2025'!$A$12:$E$13375,5,0)<2),"Bajo","Error en codigo"))))))) -> Igual
A50: 227/N | B50: FICHA LONGITUDINAL C/NEU HEMBRA NEGRO MIG | C50: UM 1u | 50u | D50: 21 | E50: 1030.586 | AF50: =IF(AND(ISBLANK(A50),ISBLANK(B50),ISBLANK(E50)),"Blanco",IF(AND(ISBLANK(A50),NOT(ISBLANK(B50))),"Titulo",IF(AND(NOT(ISBLANK(A50)),NOT(ISBLANK(B50)),ISBLANK(E50),IFERROR(FIND("FF--",A50)>1,FALSE)),"F.Comercializacion",IF(AND(NOT(ISBLANK(A50)),NOT(ISBLANK(B50)),NOT(ISBLANK(E50)),ISERROR(VLOOKUP(A50,'ListaN68 02-02-2025'!$A$12:$E$13375,5,0))),"Nuevo",IF(AND(NOT(ISBLANK(A50)),NOT(ISBLANK(B50)),NOT(ISBLANK(E50)),AND(E50-VLOOKUP(A50,'ListaN68 02-02-2025'!$A$12:$E$13375,5,0)>=-2,E50-VLOOKUP(A50,'ListaN68 02-02-2025'!$A$12:$E$13375,5,0)<=2)),"Igual",IF(AND(NOT(ISBLANK(A50)),NOT(ISBLANK(B50)),NOT(ISBLANK(E50)),E50-VLOOKUP(A50,'ListaN68 02-02-2025'!$A$12:$E$13375,5,0)>2),"Aumento",IF(AND(NOT(ISBLANK(A50)),NOT(ISBLANK(B50)),NOT(ISBLANK(E50)),E50-VLOOKUP(A50,'ListaN68 02-02-2025'!$A$12:$E$13375,5,0)<2),"Bajo","Error en codigo"))))))) -> Igual
A51: 103-27302 | B51: FICHA LONGITUDINAL C/NEU MACHO GRAFITO RICHI | C51: UM 1u | 50u | 150u | D51: 21 | E51: 1012.52 | AF51: =IF(AND(ISBLANK(A51),ISBLANK(B51),ISBLANK(E51)),"Blanco",IF(AND(ISBLANK(A51),NOT(ISBLANK(B51))),"Titulo",IF(AND(NOT(ISBLANK(A51)),NOT(ISBLANK(B51)),ISBLANK(E51),IFERROR(FIND("FF--",A51)>1,FALSE)),"F.Comercializacion",IF(AND(NOT(ISBLANK(A51)),NOT(ISBLANK(B51)),NOT(ISBLANK(E51)),ISERROR(VLOOKUP(A51,'ListaN68 02-02-2025'!$A$12:$E$13375,5,0))),"Nuevo",IF(AND(NOT(ISBLANK(A51)),NOT(ISBLANK(B51)),NOT(ISBLANK(E51)),AND(E51-VLOOKUP(A51,'ListaN68 02-02-2025'!$A$12:$E$13375,5,0)>=-2,E51-VLOOKUP(A51,'ListaN68 02-02-2025'!$A$12:$E$13375,5,0)<=2)),"Igual",IF(AND(NOT(ISBLANK(A51)),NOT(ISBLANK(B51)),NOT(ISBLANK(E51)),E51-VLOOKUP(A51,'ListaN68 02-02-2025'!$A$12:$E$13375,5,0)>2),"Aumento",IF(AND(NOT(ISBLANK(A51)),NOT(ISBLANK(B51)),NOT(ISBLANK(E51)),E51-VLOOKUP(A51,'ListaN68 02-02-2025'!$A$12:$E$13375,5,0)<2),"Bajo","Error en codigo"))))))) -> Igual
A52: 125-27702 | B52: FICHA LONGITUDINAL C/NEU HEMBRA GRAFITO RICHI | C52: UM 1u | 50u | 150u | D52: 21 | E52: 1012.52 | AF52: =IF(AND(ISBLANK(A52),ISBLANK(B52),ISBLANK(E52)),"Blanco",IF(AND(ISBLANK(A52),NOT(ISBLANK(B52))),"Titulo",IF(AND(NOT(ISBLANK(A52)),NOT(ISBLANK(B52)),ISBLANK(E52),IFERROR(FIND("FF--",A52)>1,FALSE)),"F.Comercializacion",IF(AND(NOT(ISBLANK(A52)),NOT(ISBLANK(B52)),NOT(ISBLANK(E52)),ISERROR(VLOOKUP(A52,'ListaN68 02-02-2025'!$A$12:$E$13375,5,0))),"Nuevo",IF(AND(NOT(ISBLANK(A52)),NOT(ISBLANK(B52)),NOT(ISBLANK(E52)),AND(E52-VLOOKUP(A52,'ListaN68 02-02-2025'!$A$12:$E$13375,5,0)>=-2,E52-VLOOKUP(A52,'ListaN68 02-02-2025'!$A$12:$E$13375,5,0)<=2)),"Igual",IF(AND(NOT(ISBLANK(A52)),NOT(ISBLANK(B52)),NOT(ISBLANK(E52)),E52-VLOOKUP(A52,'ListaN68 02-02-2025'!$A$12:$E$13375,5,0)>2),"Aumento",IF(AND(NOT(ISBLANK(A52)),NOT(ISBLANK(B52)),NOT(ISBLANK(E52)),E52-VLOOKUP(A52,'ListaN68 02-02-2025'!$A$12:$E$13375,5,0)<2),"Bajo","Error en codigo"))))))) -> Igual
A53: K-3 | B53: FICHA LONGITUDINAL C/NEU MACHO T/K-3 ECO | C53: UM 1u | 100u | D53: 21 | E53: 490.05 | AF53: =IF(AND(ISBLANK(A53),ISBLANK(B53),ISBLANK(E53)),"Blanco",IF(AND(ISBLANK(A53),NOT(ISBLANK(B53))),"Titulo",IF(AND(NOT(ISBLANK(A53)),NOT(ISBLANK(B53)),ISBLANK(E53),IFERROR(FIND("FF--",A53)>1,FALSE)),"F.Comercializacion",IF(AND(NOT(ISBLANK(A53)),NOT(ISBLANK(B53)),NOT(ISBLANK(E53)),ISERROR(VLOOKUP(A53,'ListaN68 02-02-2025'!$A$12:$E$13375,5,0))),"Nuevo",IF(AND(NOT(ISBLANK(A53)),NOT(ISBLANK(B53)),NOT(ISBLANK(E53)),AND(E53-VLOOKUP(A53,'ListaN68 02-02-2025'!$A$12:$E$13375,5,0)>=-2,E53-VLOOKUP(A53,'ListaN68 02-02-2025'!$A$12:$E$13375,5,0)<=2)),"Igual",IF(AND(NOT(ISBLANK(A53)),NOT(ISBLANK(B53)),NOT(ISBLANK(E53)),E53-VLOOKUP(A53,'ListaN68 02-02-2025'!$A$12:$E$13375,5,0)>2),"Aumento",IF(AND(NOT(ISBLANK(A53)),NOT(ISBLANK(B53)),NOT(ISBLANK(E53)),E53-VLOOKUP(A53,'ListaN68 02-02-2025'!$A$12:$E$13375,5,0)<2),"Bajo","Error en codigo"))))))) -> Igual
A54: K-3H | B54: FICHA LONGITUDINAL C/NEU HEMBRA T/K-3 ECO | C54: UM 1u | 100u | D54: 21 | E54: 490.05 | AF54: =IF(AND(ISBLANK(A54),ISBLANK(B54),ISBLANK(E54)),"Blanco",IF(AND(ISBLANK(A54),NOT(ISBLANK(B54))),"Titulo",IF(AND(NOT(ISBLANK(A54)),NOT(ISBLANK(B54)),ISBLANK(E54),IFERROR(FIND("FF--",A54)>1,FALSE)),"F.Comercializacion",IF(AND(NOT(ISBLANK(A54)),NOT(ISBLANK(B54)),NOT(ISBLANK(E54)),ISERROR(VLOOKUP(A54,'ListaN68 02-02-2025'!$A$12:$E$13375,5,0))),"Nuevo",IF(AND(NOT(ISBLANK(A54)),NOT(ISBLANK(B54)),NOT(ISBLANK(E54)),AND(E54-VLOOKUP(A54,'ListaN68 02-02-2025'!$A$12:$E$13375,5,0)>=-2,E54-VLOOKUP(A54,'ListaN68 02-02-2025'!$A$12:$E$13375,5,0)<=2)),"Igual",IF(AND(NOT(ISBLANK(A54)),NOT(ISBLANK(B54)),NOT(ISBLANK(E54)),E54-VLOOKUP(A54,'ListaN68 02-02-2025'!$A$12:$E$13375,5,0)>2),"Aumento",IF(AND(NOT(ISBLANK(A54)),NOT(ISBLANK(B54)),NOT(ISBLANK(E54)),E54-VLOOKUP(A54,'ListaN68 02-02-2025'!$A$12:$E$13375,5,0)<2),"Bajo","Error en codigo"))))))) -> Igual
A55: F160 | B55: FICHA LONGITUDINAL C/NEU MACHO T/RICHI ECO | C55: UM 1u | 200u | D55: 21 | E55: 616.996 | AF55: =IF(AND(ISBLANK(A55),ISBLANK(B55),ISBLANK(E55)),"Blanco",IF(AND(ISBLANK(A55),NOT(ISBLANK(B55))),"Titulo",IF(AND(NOT(ISBLANK(A55)),NOT(ISBLANK(B55)),ISBLANK(E55),IFERROR(FIND("FF--",A55)>1,FALSE)),"F.Comercializacion",IF(AND(NOT(ISBLANK(A55)),NOT(ISBLANK(B55)),NOT(ISBLANK(E55)),ISERROR(VLOOKUP(A55,'ListaN68 02-02-2025'!$A$12:$E$13375,5,0))),"Nuevo",IF(AND(NOT(ISBLANK(A55)),NOT(ISBLANK(B55)),NOT(ISBLANK(E55)),AND(E55-VLOOKUP(A55,'ListaN68 02-02-2025'!$A$12:$E$13375,5,0)>=-2,E55-VLOOKUP(A55,'ListaN68 02-02-2025'!$A$12:$E$13375,5,0)<=2)),"Igual",IF(AND(NOT(ISBLANK(A55)),NOT(ISBLANK(B55)),NOT(ISBLANK(E55)),E55-VLOOKUP(A55,'ListaN68 02-02-2025'!$A$12:$E$13375,5,0)>2),"Aumento",IF(AND(NOT(ISBLANK(A55)),NOT(ISBLANK(B55)),NOT(ISBLANK(E55)),E55-VLOOKUP(A55,'ListaN68 02-02-2025'!$A$12:$E$13375,5,0)<2),"Bajo","Error en codigo"))))))) -> Igual
A56: F161 | B56: FICHA LONGITUDINAL C/NEU HEMBRA T/RICHI ECO | C56: UM 1u | 200u | D56: 21 | E56: 616.996 | AF56: =IF(AND(ISBLANK(A56),ISBLANK(B56),ISBLANK(E56)),"Blanco",IF(AND(ISBLANK(A56),NOT(ISBLANK(B56))),"Titulo",IF(AND(NOT(ISBLANK(A56)),NOT(ISBLANK(B56)),ISBLANK(E56),IFERROR(FIND("FF--",A56)>1,FALSE)),"F.Comercializacion",IF(AND(NOT(ISBLANK(A56)),NOT(ISBLANK(B56)),NOT(ISBLANK(E56)),ISERROR(VLOOKUP(A56,'ListaN68 02-02-2025'!$A$12:$E$13375,5,0))),"Nuevo",IF(AND(NOT(ISBLANK(A56)),NOT(ISBLANK(B56)),NOT(ISBLANK(E56)),AND(E56-VLOOKUP(A56,'ListaN68 02-02-2025'!$A$12:$E$13375,5,0)>=-2,E56-VLOOKUP(A56,'ListaN68 02-02-2025'!$A$12:$E$13375,5,0)<=2)),"Igual",IF(AND(NOT(ISBLANK(A56)),NOT(ISBLANK(B56)),NOT(ISBLANK(E56)),E56-VLOOKUP(A56,'ListaN68 02-02-2025'!$A$12:$E$13375,5,0)>2),"Aumento",IF(AND(NOT(ISBLANK(A56)),NOT(ISBLANK(B56)),NOT(ISBLANK(E56)),E56-VLOOKUP(A56,'ListaN68 02-02-2025'!$A$12:$E$13375,5,0)<2),"Bajo","Error en codigo"))))))) -> Igual
A57: F170N | B57: FICHA AXIAL C/NEU MACHO ECO NEGRA ALAN | C57: UM 1u | 300u | D57: 21 | E57: 430.064 | AF57: =IF(AND(ISBLANK(A57),ISBLANK(B57),ISBLANK(E57)),"Blanco",IF(AND(ISBLANK(A57),NOT(ISBLANK(B57))),"Titulo",IF(AND(NOT(ISBLANK(A57)),NOT(ISBLANK(B57)),ISBLANK(E57),IFERROR(FIND("FF--",A57)>1,FALSE)),"F.Comercializacion",IF(AND(NOT(ISBLANK(A57)),NOT(ISBLANK(B57)),NOT(ISBLANK(E57)),ISERROR(VLOOKUP(A57,'ListaN68 02-02-2025'!$A$12:$E$13375,5,0))),"Nuevo",IF(AND(NOT(ISBLANK(A57)),NOT(ISBLANK(B57)),NOT(ISBLANK(E57)),AND(E57-VLOOKUP(A57,'ListaN68 02-02-2025'!$A$12:$E$13375,5,0)>=-2,E57-VLOOKUP(A57,'ListaN68 02-02-2025'!$A$12:$E$13375,5,0)<=2)),"Igual",IF(AND(NOT(ISBLANK(A57)),NOT(ISBLANK(B57)),NOT(ISBLANK(E57)),E57-VLOOKUP(A57,'ListaN68 02-02-2025'!$A$12:$E$13375,5,0)>2),"Aumento",IF(AND(NOT(ISBLANK(A57)),NOT(ISBLANK(B57)),NOT(ISBLANK(E57)),E57-VLOOKUP(A57,'ListaN68 02-02-2025'!$A$12:$E$13375,5,0)<2),"Bajo","Error en codigo"))))))) -> Igual
A58: F171N | B58: FICHA AXIAL C/NEU HEMBRA ECO NEGRA ALAN | C58: UM 1u | 300u | D58: 21 | E58: 430.064 | AF58: =IF(AND(ISBLANK(A58),ISBLANK(B58),ISBLANK(E58)),"Blanco",IF(AND(ISBLANK(A58),NOT(ISBLANK(B58))),"Titulo",IF(AND(NOT(ISBLANK(A58)),NOT(ISBLANK(B58)),ISBLANK(E58),IFERROR(FIND("FF--",A58)>1,FALSE)),"F.Comercializacion",IF(AND(NOT(ISBLANK(A58)),NOT(ISBLANK(B58)),NOT(ISBLANK(E58)),ISERROR(VLOOKUP(A58,'ListaN68 02-02-2025'!$A$12:$E$13375,5,0))),"Nuevo",IF(AND(NOT(ISBLANK(A58)),NOT(ISBLANK(B58)),NOT(ISBLANK(E58)),AND(E58-VLOOKUP(A58,'ListaN68 02-02-2025'!$A$12:$E$13375,5,0)>=-2,E58-VLOOKUP(A58,'ListaN68 02-02-2025'!$A$12:$E$13375,5,0)<=2)),"Igual",IF(AND(NOT(ISBLANK(A58)),NOT(ISBLANK(B58)),NOT(ISBLANK(E58)),E58-VLOOKUP(A58,'ListaN68 02-02-2025'!$A$12:$E$13375,5,0)>2),"Aumento",IF(AND(NOT(ISBLANK(A58)),NOT(ISBLANK(B58)),NOT(ISBLANK(E58)),E58-VLOOKUP(A58,'ListaN68 02-02-2025'!$A$12:$E$13375,5,0)<2),"Bajo","Error en codigo"))))))) -> Igual
A59: 113 | B59: FICHA S/90º MACHO C/NEU BLANCO MIG | C59: UM 1u | 100u | D59: 21 | E59: 1074.866 | AF59: =IF(AND(ISBLANK(A59),ISBLANK(B59),ISBLANK(E59)),"Blanco",IF(AND(ISBLANK(A59),NOT(ISBLANK(B59))),"Titulo",IF(AND(NOT(ISBLANK(A59)),NOT(ISBLANK(B59)),ISBLANK(E59),IFERROR(FIND("FF--",A59)>1,FALSE)),"F.Comercializacion",IF(AND(NOT(ISBLANK(A59)),NOT(ISBLANK(B59)),NOT(ISBLANK(E59)),ISERROR(VLOOKUP(A59,'ListaN68 02-02-2025'!$A$12:$E$13375,5,0))),"Nuevo",IF(AND(NOT(ISBLANK(A59)),NOT(ISBLANK(B59)),NOT(ISBLANK(E59)),AND(E59-VLOOKUP(A59,'ListaN68 02-02-2025'!$A$12:$E$13375,5,0)>=-2,E59-VLOOKUP(A59,'ListaN68 02-02-2025'!$A$12:$E$13375,5,0)<=2)),"Igual",IF(AND(NOT(ISBLANK(A59)),NOT(ISBLANK(B59)),NOT(ISBLANK(E59)),E59-VLOOKUP(A59,'ListaN68 02-02-2025'!$A$12:$E$13375,5,0)>2),"Aumento",IF(AND(NOT(ISBLANK(A59)),NOT(ISBLANK(B59)),NOT(ISBLANK(E59)),E59-VLOOKUP(A59,'ListaN68 02-02-2025'!$A$12:$E$13375,5,0)<2),"Bajo","Error en codigo"))))))) -> Igual
A60: 113N | B60: FICHA S/90º MACHO C/NEU NEGRA MIG | C60: UM 1u | 100u | D60: 21 | E60: 1074.866 | AF60: =IF(AND(ISBLANK(A60),ISBLANK(B60),ISBLANK(E60)),"Blanco",IF(AND(ISBLANK(A60),NOT(ISBLANK(B60))),"Titulo",IF(AND(NOT(ISBLANK(A60)),NOT(ISBLANK(B60)),ISBLANK(E60),IFERROR(FIND("FF--",A60)>1,FALSE)),"F.Comercializacion",IF(AND(NOT(ISBLANK(A60)),NOT(ISBLANK(B60)),NOT(ISBLANK(E60)),ISERROR(VLOOKUP(A60,'ListaN68 02-02-2025'!$A$12:$E$13375,5,0))),"Nuevo",IF(AND(NOT(ISBLANK(A60)),NOT(ISBLANK(B60)),NOT(ISBLANK(E60)),AND(E60-VLOOKUP(A60,'ListaN68 02-02-2025'!$A$12:$E$13375,5,0)>=-2,E60-VLOOKUP(A60,'ListaN68 02-02-2025'!$A$12:$E$13375,5,0)<=2)),"Igual",IF(AND(NOT(ISBLANK(A60)),NOT(ISBLANK(B60)),NOT(ISBLANK(E60)),E60-VLOOKUP(A60,'ListaN68 02-02-2025'!$A$12:$E$13375,5,0)>2),"Aumento",IF(AND(NOT(ISBLANK(A60)),NOT(ISBLANK(B60)),NOT(ISBLANK(E60)),E60-VLOOKUP(A60,'ListaN68 02-02-2025'!$A$12:$E$13375,5,0)<2),"Bajo","Error en codigo"))))))) -> Igual
A61: 120 | B61: FICHA S/90º HEMBRA C/NEU BLANCO MIG | C61: UM 1u | 100u | D61: 21 | E61: 916.543 | AF61: =IF(AND(ISBLANK(A61),ISBLANK(B61),ISBLANK(E61)),"Blanco",IF(AND(ISBLANK(A61),NOT(ISBLANK(B61))),"Titulo",IF(AND(NOT(ISBLANK(A61)),NOT(ISBLANK(B61)),ISBLANK(E61),IFERROR(FIND("FF--",A61)>1,FALSE)),"F.Comercializacion",IF(AND(NOT(ISBLANK(A61)),NOT(ISBLANK(B61)),NOT(ISBLANK(E61)),ISERROR(VLOOKUP(A61,'ListaN68 02-02-2025'!$A$12:$E$13375,5,0))),"Nuevo",IF(AND(NOT(ISBLANK(A61)),NOT(ISBLANK(B61)),NOT(ISBLANK(E61)),AND(E61-VLOOKUP(A61,'ListaN68 02-02-2025'!$A$12:$E$13375,5,0)>=-2,E61-VLOOKUP(A61,'ListaN68 02-02-2025'!$A$12:$E$13375,5,0)<=2)),"Igual",IF(AND(NOT(ISBLANK(A61)),NOT(ISBLANK(B61)),NOT(ISBLANK(E61)),E61-VLOOKUP(A61,'ListaN68 02-02-2025'!$A$12:$E$13375,5,0)>2),"Aumento",IF(AND(NOT(ISBLANK(A61)),NOT(ISBLANK(B61)),NOT(ISBLANK(E61)),E61-VLOOKUP(A61,'ListaN68 02-02-2025'!$A$12:$E$13375,5,0)<2),"Bajo","Error en codigo"))))))) -> Igual
A62: 120N | B62: FICHA S/90º HEMBRA C/NEU NEGRA MIG | C62: UM 1u | 100u | D62: 21 | E62: 916.543 | AF62: =IF(AND(ISBLANK(A62),ISBLANK(B62),ISBLANK(E62)),"Blanco",IF(AND(ISBLANK(A62),NOT(ISBLANK(B62))),"Titulo",IF(AND(NOT(ISBLANK(A62)),NOT(ISBLANK(B62)),ISBLANK(E62),IFERROR(FIND("FF--",A62)>1,FALSE)),"F.Comercializacion",IF(AND(NOT(ISBLANK(A62)),NOT(ISBLANK(B62)),NOT(ISBLANK(E62)),ISERROR(VLOOKUP(A62,'ListaN68 02-02-2025'!$A$12:$E$13375,5,0))),"Nuevo",IF(AND(NOT(ISBLANK(A62)),NOT(ISBLANK(B62)),NOT(ISBLANK(E62)),AND(E62-VLOOKUP(A62,'ListaN68 02-02-2025'!$A$12:$E$13375,5,0)>=-2,E62-VLOOKUP(A62,'ListaN68 02-02-2025'!$A$12:$E$13375,5,0)<=2)),"Igual",IF(AND(NOT(ISBLANK(A62)),NOT(ISBLANK(B62)),NOT(ISBLANK(E62)),E62-VLOOKUP(A62,'ListaN68 02-02-2025'!$A$12:$E$13375,5,0)>2),"Aumento",IF(AND(NOT(ISBLANK(A62)),NOT(ISBLANK(B62)),NOT(ISBLANK(E62)),E62-VLOOKUP(A62,'ListaN68 02-02-2025'!$A$12:$E$13375,5,0)<2),"Bajo","Error en codigo"))))))) -> Igual
A63: F137B | B63: FICHA S/90º MACHO C/NEU BLANCO ALAN ECO | C63: UM 1u | 100u | D63: 21 | E63: 456.962 | AF63: =IF(AND(ISBLANK(A63),ISBLANK(B63),ISBLANK(E63)),"Blanco",IF(AND(ISBLANK(A63),NOT(ISBLANK(B63))),"Titulo",IF(AND(NOT(ISBLANK(A63)),NOT(ISBLANK(B63)),ISBLANK(E63),IFERROR(FIND("FF--",A63)>1,FALSE)),"F.Comercializacion",IF(AND(NOT(ISBLANK(A63)),NOT(ISBLANK(B63)),NOT(ISBLANK(E63)),ISERROR(VLOOKUP(A63,'ListaN68 02-02-2025'!$A$12:$E$13375,5,0))),"Nuevo",IF(AND(NOT(ISBLANK(A63)),NOT(ISBLANK(B63)),NOT(ISBLANK(E63)),AND(E63-VLOOKUP(A63,'ListaN68 02-02-2025'!$A$12:$E$13375,5,0)>=-2,E63-VLOOKUP(A63,'ListaN68 02-02-2025'!$A$12:$E$13375,5,0)<=2)),"Igual",IF(AND(NOT(ISBLANK(A63)),NOT(ISBLANK(B63)),NOT(ISBLANK(E63)),E63-VLOOKUP(A63,'ListaN68 02-02-2025'!$A$12:$E$13375,5,0)>2),"Aumento",IF(AND(NOT(ISBLANK(A63)),NOT(ISBLANK(B63)),NOT(ISBLANK(E63)),E63-VLOOKUP(A63,'ListaN68 02-02-2025'!$A$12:$E$13375,5,0)<2),"Bajo","Error en codigo"))))))) -> Igual
A64: F138B | B64: FICHA S/90º HEMBRA C/NEU BLANCO ALAN ECO BINORMA | C64: UM 1u | 100u | D64: 21 | E64: 456.962 | AF64: =IF(AND(ISBLANK(A64),ISBLANK(B64),ISBLANK(E64)),"Blanco",IF(AND(ISBLANK(A64),NOT(ISBLANK(B64))),"Titulo",IF(AND(NOT(ISBLANK(A64)),NOT(ISBLANK(B64)),ISBLANK(E64),IFERROR(FIND("FF--",A64)>1,FALSE)),"F.Comercializacion",IF(AND(NOT(ISBLANK(A64)),NOT(ISBLANK(B64)),NOT(ISBLANK(E64)),ISERROR(VLOOKUP(A64,'ListaN68 02-02-2025'!$A$12:$E$13375,5,0))),"Nuevo",IF(AND(NOT(ISBLANK(A64)),NOT(ISBLANK(B64)),NOT(ISBLANK(E64)),AND(E64-VLOOKUP(A64,'ListaN68 02-02-2025'!$A$12:$E$13375,5,0)>=-2,E64-VLOOKUP(A64,'ListaN68 02-02-2025'!$A$12:$E$13375,5,0)<=2)),"Igual",IF(AND(NOT(ISBLANK(A64)),NOT(ISBLANK(B64)),NOT(ISBLANK(E64)),E64-VLOOKUP(A64,'ListaN68 02-02-2025'!$A$12:$E$13375,5,0)>2),"Aumento",IF(AND(NOT(ISBLANK(A64)),NOT(ISBLANK(B64)),NOT(ISBLANK(E64)),E64-VLOOKUP(A64,'ListaN68 02-02-2025'!$A$12:$E$13375,5,0)<2),"Bajo","Error en codigo"))))))) -> Igual
A65: 103-28302 | B65: FICHA S/90º MACHO C/NEU GRAFITO 10A RICHI | C65: UM 1u | 200u | D65: 21 | E65: 1110.148 | AF65: =IF(AND(ISBLANK(A65),ISBLANK(B65),ISBLANK(E65)),"Blanco",IF(AND(ISBLANK(A65),NOT(ISBLANK(B65))),"Titulo",IF(AND(NOT(ISBLANK(A65)),NOT(ISBLANK(B65)),ISBLANK(E65),IFERROR(FIND("FF--",A65)>1,FALSE)),"F.Comercializacion",IF(AND(NOT(ISBLANK(A65)),NOT(ISBLANK(B65)),NOT(ISBLANK(E65)),ISERROR(VLOOKUP(A65,'ListaN68 02-02-2025'!$A$12:$E$13375,5,0))),"Nuevo",IF(AND(NOT(ISBLANK(A65)),NOT(ISBLANK(B65)),NOT(ISBLANK(E65)),AND(E65-VLOOKUP(A65,'ListaN68 02-02-2025'!$A$12:$E$13375,5,0)>=-2,E65-VLOOKUP(A65,'ListaN68 02-02-2025'!$A$12:$E$13375,5,0)<=2)),"Igual",IF(AND(NOT(ISBLANK(A65)),NOT(ISBLANK(B65)),NOT(ISBLANK(E65)),E65-VLOOKUP(A65,'ListaN68 02-02-2025'!$A$12:$E$13375,5,0)>2),"Aumento",IF(AND(NOT(ISBLANK(A65)),NOT(ISBLANK(B65)),NOT(ISBLANK(E65)),E65-VLOOKUP(A65,'ListaN68 02-02-2025'!$A$12:$E$13375,5,0)<2),"Bajo","Error en codigo"))))))) -> Igual
A66: 103-28305 | B66: FICHA S/90º MACHO C/NEU MARFIL 10A RICHI | C66: UM 1u | 200u | D66: 21 | E66: 1110.148 | AF66: =IF(AND(ISBLANK(A66),ISBLANK(B66),ISBLANK(E66)),"Blanco",IF(AND(ISBLANK(A66),NOT(ISBLANK(B66))),"Titulo",IF(AND(NOT(ISBLANK(A66)),NOT(ISBLANK(B66)),ISBLANK(E66),IFERROR(FIND("FF--",A66)>1,FALSE)),"F.Comercializacion",IF(AND(NOT(ISBLANK(A66)),NOT(ISBLANK(B66)),NOT(ISBLANK(E66)),ISERROR(VLOOKUP(A66,'ListaN68 02-02-2025'!$A$12:$E$13375,5,0))),"Nuevo",IF(AND(NOT(ISBLANK(A66)),NOT(ISBLANK(B66)),NOT(ISBLANK(E66)),AND(E66-VLOOKUP(A66,'ListaN68 02-02-2025'!$A$12:$E$13375,5,0)>=-2,E66-VLOOKUP(A66,'ListaN68 02-02-2025'!$A$12:$E$13375,5,0)<=2)),"Igual",IF(AND(NOT(ISBLANK(A66)),NOT(ISBLANK(B66)),NOT(ISBLANK(E66)),E66-VLOOKUP(A66,'ListaN68 02-02-2025'!$A$12:$E$13375,5,0)>2),"Aumento",IF(AND(NOT(ISBLANK(A66)),NOT(ISBLANK(B66)),NOT(ISBLANK(E66)),E66-VLOOKUP(A66,'ListaN68 02-02-2025'!$A$12:$E$13375,5,0)<2),"Bajo","Error en codigo"))))))) -> Igual
A67: 125-28702 | B67: FICHA S/90º HEMBRA GRAFITO 10A RICHI | C67: UM 1u | 200u | D67: 21 | E67: 1110.148 | AF67: =IF(AND(ISBLANK(A67),ISBLANK(B67),ISBLANK(E67)),"Blanco",IF(AND(ISBLANK(A67),NOT(ISBLANK(B67))),"Titulo",IF(AND(NOT(ISBLANK(A67)),NOT(ISBLANK(B67)),ISBLANK(E67),IFERROR(FIND("FF--",A67)>1,FALSE)),"F.Comercializacion",IF(AND(NOT(ISBLANK(A67)),NOT(ISBLANK(B67)),NOT(ISBLANK(E67)),ISERROR(VLOOKUP(A67,'ListaN68 02-02-2025'!$A$12:$E$13375,5,0))),"Nuevo",IF(AND(NOT(ISBLANK(A67)),NOT(ISBLANK(B67)),NOT(ISBLANK(E67)),AND(E67-VLOOKUP(A67,'ListaN68 02-02-2025'!$A$12:$E$13375,5,0)>=-2,E67-VLOOKUP(A67,'ListaN68 02-02-2025'!$A$12:$E$13375,5,0)<=2)),"Igual",IF(AND(NOT(ISBLANK(A67)),NOT(ISBLANK(B67)),NOT(ISBLANK(E67)),E67-VLOOKUP(A67,'ListaN68 02-02-2025'!$A$12:$E$13375,5,0)>2),"Aumento",IF(AND(NOT(ISBLANK(A67)),NOT(ISBLANK(B67)),NOT(ISBLANK(E67)),E67-VLOOKUP(A67,'ListaN68 02-02-2025'!$A$12:$E$13375,5,0)<2),"Bajo","Error en codigo"))))))) -> Igual
A68: 125-28705 | B68: FICHA S/90º HEMBRA MARFIL 10A RICHI | C68: UM 1u | 200u | D68: 21 | E68: 1110.148 | AF68: =IF(AND(ISBLANK(A68),ISBLANK(B68),ISBLANK(E68)),"Blanco",IF(AND(ISBLANK(A68),NOT(ISBLANK(B68))),"Titulo",IF(AND(NOT(ISBLANK(A68)),NOT(ISBLANK(B68)),ISBLANK(E68),IFERROR(FIND("FF--",A68)>1,FALSE)),"F.Comercializacion",IF(AND(NOT(ISBLANK(A68)),NOT(ISBLANK(B68)),NOT(ISBLANK(E68)),ISERROR(VLOOKUP(A68,'ListaN68 02-02-2025'!$A$12:$E$13375,5,0))),"Nuevo",IF(AND(NOT(ISBLANK(A68)),NOT(ISBLANK(B68)),NOT(ISBLANK(E68)),AND(E68-VLOOKUP(A68,'ListaN68 02-02-2025'!$A$12:$E$13375,5,0)>=-2,E68-VLOOKUP(A68,'ListaN68 02-02-2025'!$A$12:$E$13375,5,0)<=2)),"Igual",IF(AND(NOT(ISBLANK(A68)),NOT(ISBLANK(B68)),NOT(ISBLANK(E68)),E68-VLOOKUP(A68,'ListaN68 02-02-2025'!$A$12:$E$13375,5,0)>2),"Aumento",IF(AND(NOT(ISBLANK(A68)),NOT(ISBLANK(B68)),NOT(ISBLANK(E68)),E68-VLOOKUP(A68,'ListaN68 02-02-2025'!$A$12:$E$13375,5,0)<2),"Bajo","Error en codigo"))))))) -> Igual
A69: 141 | B69: FICHA S/90º MACHO C/AZA C/NEU | C69: UM 1u | 40u | D69: 21 | E69: 1366.157 | AF69: =IF(AND(ISBLANK(A69),ISBLANK(B69),ISBLANK(E69)),"Blanco",IF(AND(ISBLANK(A69),NOT(ISBLANK(B69))),"Titulo",IF(AND(NOT(ISBLANK(A69)),NOT(ISBLANK(B69)),ISBLANK(E69),IFERROR(FIND("FF--",A69)>1,FALSE)),"F.Comercializacion",IF(AND(NOT(ISBLANK(A69)),NOT(ISBLANK(B69)),NOT(ISBLANK(E69)),ISERROR(VLOOKUP(A69,'ListaN68 02-02-2025'!$A$12:$E$13375,5,0))),"Nuevo",IF(AND(NOT(ISBLANK(A69)),NOT(ISBLANK(B69)),NOT(ISBLANK(E69)),AND(E69-VLOOKUP(A69,'ListaN68 02-02-2025'!$A$12:$E$13375,5,0)>=-2,E69-VLOOKUP(A69,'ListaN68 02-02-2025'!$A$12:$E$13375,5,0)<=2)),"Igual",IF(AND(NOT(ISBLANK(A69)),NOT(ISBLANK(B69)),NOT(ISBLANK(E69)),E69-VLOOKUP(A69,'ListaN68 02-02-2025'!$A$12:$E$13375,5,0)>2),"Aumento",IF(AND(NOT(ISBLANK(A69)),NOT(ISBLANK(B69)),NOT(ISBLANK(E69)),E69-VLOOKUP(A69,'ListaN68 02-02-2025'!$A$12:$E$13375,5,0)<2),"Bajo","Error en codigo"))))))) -> Igual
A70: 142 | B70: FICHA S/90º MACHO C/AZA C/NEU 20A | C70: UM 1u | 40u | D70: 21 | E70: 1636.418 | AF70: =IF(AND(ISBLANK(A70),ISBLANK(B70),ISBLANK(E70)),"Blanco",IF(AND(ISBLANK(A70),NOT(ISBLANK(B70))),"Titulo",IF(AND(NOT(ISBLANK(A70)),NOT(ISBLANK(B70)),ISBLANK(E70),IFERROR(FIND("FF--",A70)>1,FALSE)),"F.Comercializacion",IF(AND(NOT(ISBLANK(A70)),NOT(ISBLANK(B70)),NOT(ISBLANK(E70)),ISERROR(VLOOKUP(A70,'ListaN68 02-02-2025'!$A$12:$E$13375,5,0))),"Nuevo",IF(AND(NOT(ISBLANK(A70)),NOT(ISBLANK(B70)),NOT(ISBLANK(E70)),AND(E70-VLOOKUP(A70,'ListaN68 02-02-2025'!$A$12:$E$13375,5,0)>=-2,E70-VLOOKUP(A70,'ListaN68 02-02-2025'!$A$12:$E$13375,5,0)<=2)),"Igual",IF(AND(NOT(ISBLANK(A70)),NOT(ISBLANK(B70)),NOT(ISBLANK(E70)),E70-VLOOKUP(A70,'ListaN68 02-02-2025'!$A$12:$E$13375,5,0)>2),"Aumento",IF(AND(NOT(ISBLANK(A70)),NOT(ISBLANK(B70)),NOT(ISBLANK(E70)),E70-VLOOKUP(A70,'ListaN68 02-02-2025'!$A$12:$E$13375,5,0)<2),"Bajo","Error en codigo"))))))) -> Igual
A71: 218 | B71: FICHA S/90º MACHO CON AZA PERNO REDONDO | C71: UM 1u | 40u | D71: 21 | E71: 1299.363 | AF71: =IF(AND(ISBLANK(A71),ISBLANK(B71),ISBLANK(E71)),"Blanco",IF(AND(ISBLANK(A71),NOT(ISBLANK(B71))),"Titulo",IF(AND(NOT(ISBLANK(A71)),NOT(ISBLANK(B71)),ISBLANK(E71),IFERROR(FIND("FF--",A71)>1,FALSE)),"F.Comercializacion",IF(AND(NOT(ISBLANK(A71)),NOT(ISBLANK(B71)),NOT(ISBLANK(E71)),ISERROR(VLOOKUP(A71,'ListaN68 02-02-2025'!$A$12:$E$13375,5,0))),"Nuevo",IF(AND(NOT(ISBLANK(A71)),NOT(ISBLANK(B71)),NOT(ISBLANK(E71)),AND(E71-VLOOKUP(A71,'ListaN68 02-02-2025'!$A$12:$E$13375,5,0)>=-2,E71-VLOOKUP(A71,'ListaN68 02-02-2025'!$A$12:$E$13375,5,0)<=2)),"Igual",IF(AND(NOT(ISBLANK(A71)),NOT(ISBLANK(B71)),NOT(ISBLANK(E71)),E71-VLOOKUP(A71,'ListaN68 02-02-2025'!$A$12:$E$13375,5,0)>2),"Aumento",IF(AND(NOT(ISBLANK(A71)),NOT(ISBLANK(B71)),NOT(ISBLANK(E71)),E71-VLOOKUP(A71,'ListaN68 02-02-2025'!$A$12:$E$13375,5,0)<2),"Bajo","Error en codigo"))))))) -> Igual
A72: 242 | B72: FICHA S/90º HEMBRA C/AZA C/NEU 20A | C72: UM 1u | 40u | D72: 21 | E72: 1653.736 | AF72: =IF(AND(ISBLANK(A72),ISBLANK(B72),ISBLANK(E72)),"Blanco",IF(AND(ISBLANK(A72),NOT(ISBLANK(B72))),"Titulo",IF(AND(NOT(ISBLANK(A72)),NOT(ISBLANK(B72)),ISBLANK(E72),IFERROR(FIND("FF--",A72)>1,FALSE)),"F.Comercializacion",IF(AND(NOT(ISBLANK(A72)),NOT(ISBLANK(B72)),NOT(ISBLANK(E72)),ISERROR(VLOOKUP(A72,'ListaN68 02-02-2025'!$A$12:$E$13375,5,0))),"Nuevo",IF(AND(NOT(ISBLANK(A72)),NOT(ISBLANK(B72)),NOT(ISBLANK(E72)),AND(E72-VLOOKUP(A72,'ListaN68 02-02-2025'!$A$12:$E$13375,5,0)>=-2,E72-VLOOKUP(A72,'ListaN68 02-02-2025'!$A$12:$E$13375,5,0)<=2)),"Igual",IF(AND(NOT(ISBLANK(A72)),NOT(ISBLANK(B72)),NOT(ISBLANK(E72)),E72-VLOOKUP(A72,'ListaN68 02-02-2025'!$A$12:$E$13375,5,0)>2),"Aumento",IF(AND(NOT(ISBLANK(A72)),NOT(ISBLANK(B72)),NOT(ISBLANK(E72)),E72-VLOOKUP(A72,'ListaN68 02-02-2025'!$A$12:$E$13375,5,0)<2),"Bajo","Error en codigo"))))))) -> Igual
A73: 250 | B73: FICHA S/90º HEMBRA C/AZA (BINORMA) | C73: UM 1u | 40u | D73: 21 | E73: 1270.915 | AF73: =IF(AND(ISBLANK(A73),ISBLANK(B73),ISBLANK(E73)),"Blanco",IF(AND(ISBLANK(A73),NOT(ISBLANK(B73))),"Titulo",IF(AND(NOT(ISBLANK(A73)),NOT(ISBLANK(B73)),ISBLANK(E73),IFERROR(FIND("FF--",A73)>1,FALSE)),"F.Comercializacion",IF(AND(NOT(ISBLANK(A73)),NOT(ISBLANK(B73)),NOT(ISBLANK(E73)),ISERROR(VLOOKUP(A73,'ListaN68 02-02-2025'!$A$12:$E$13375,5,0))),"Nuevo",IF(AND(NOT(ISBLANK(A73)),NOT(ISBLANK(B73)),NOT(ISBLANK(E73)),AND(E73-VLOOKUP(A73,'ListaN68 02-02-2025'!$A$12:$E$13375,5,0)>=-2,E73-VLOOKUP(A73,'ListaN68 02-02-2025'!$A$12:$E$13375,5,0)<=2)),"Igual",IF(AND(NOT(ISBLANK(A73)),NOT(ISBLANK(B73)),NOT(ISBLANK(E73)),E73-VLOOKUP(A73,'ListaN68 02-02-2025'!$A$12:$E$13375,5,0)>2),"Aumento",IF(AND(NOT(ISBLANK(A73)),NOT(ISBLANK(B73)),NOT(ISBLANK(E73)),E73-VLOOKUP(A73,'ListaN68 02-02-2025'!$A$12:$E$13375,5,0)<2),"Bajo","Error en codigo"))))))) -> Igual
A74: 219 | B74: INTERRUPTOR P/VELADOR BCO | C74: UM 1u | 100u | D74: 21 | E74: 716.165 | AF74: =IF(AND(ISBLANK(A74),ISBLANK(B74),ISBLANK(E74)),"Blanco",IF(AND(ISBLANK(A74),NOT(ISBLANK(B74))),"Titulo",IF(AND(NOT(ISBLANK(A74)),NOT(ISBLANK(B74)),ISBLANK(E74),IFERROR(FIND("FF--",A74)>1,FALSE)),"F.Comercializacion",IF(AND(NOT(ISBLANK(A74)),NOT(ISBLANK(B74)),NOT(ISBLANK(E74)),ISERROR(VLOOKUP(A74,'ListaN68 02-02-2025'!$A$12:$E$13375,5,0))),"Nuevo",IF(AND(NOT(ISBLANK(A74)),NOT(ISBLANK(B74)),NOT(ISBLANK(E74)),AND(E74-VLOOKUP(A74,'ListaN68 02-02-2025'!$A$12:$E$13375,5,0)>=-2,E74-VLOOKUP(A74,'ListaN68 02-02-2025'!$A$12:$E$13375,5,0)<=2)),"Igual",IF(AND(NOT(ISBLANK(A74)),NOT(ISBLANK(B74)),NOT(ISBLANK(E74)),E74-VLOOKUP(A74,'ListaN68 02-02-2025'!$A$12:$E$13375,5,0)>2),"Aumento",IF(AND(NOT(ISBLANK(A74)),NOT(ISBLANK(B74)),NOT(ISBLANK(E74)),E74-VLOOKUP(A74,'ListaN68 02-02-2025'!$A$12:$E$13375,5,0)<2),"Bajo","Error en codigo"))))))) -> Igual
A75: 219-N | B75: INTERRUPTOR P/VELADOR NEGRO | C75: UM 1u | 100u | D75: 21 | E75: 716.165 | AF75: =IF(AND(ISBLANK(A75),ISBLANK(B75),ISBLANK(E75)),"Blanco",IF(AND(ISBLANK(A75),NOT(ISBLANK(B75))),"Titulo",IF(AND(NOT(ISBLANK(A75)),NOT(ISBLANK(B75)),ISBLANK(E75),IFERROR(FIND("FF--",A75)>1,FALSE)),"F.Comercializacion",IF(AND(NOT(ISBLANK(A75)),NOT(ISBLANK(B75)),NOT(ISBLANK(E75)),ISERROR(VLOOKUP(A75,'ListaN68 02-02-2025'!$A$12:$E$13375,5,0))),"Nuevo",IF(AND(NOT(ISBLANK(A75)),NOT(ISBLANK(B75)),NOT(ISBLANK(E75)),AND(E75-VLOOKUP(A75,'ListaN68 02-02-2025'!$A$12:$E$13375,5,0)>=-2,E75-VLOOKUP(A75,'ListaN68 02-02-2025'!$A$12:$E$13375,5,0)<=2)),"Igual",IF(AND(NOT(ISBLANK(A75)),NOT(ISBLANK(B75)),NOT(ISBLANK(E75)),E75-VLOOKUP(A75,'ListaN68 02-02-2025'!$A$12:$E$13375,5,0)>2),"Aumento",IF(AND(NOT(ISBLANK(A75)),NOT(ISBLANK(B75)),NOT(ISBLANK(E75)),E75-VLOOKUP(A75,'ListaN68 02-02-2025'!$A$12:$E$13375,5,0)<2),"Bajo","Error en codigo"))))))) -> Igual
A76: 102-25502 | B76: FICHA VELADOR GRAFITO 10A RICHI | C76: UM 1u | 300u | D76: 21 | E76: 781.85 | AF76: =IF(AND(ISBLANK(A76),ISBLANK(B76),ISBLANK(E76)),"Blanco",IF(AND(ISBLANK(A76),NOT(ISBLANK(B76))),"Titulo",IF(AND(NOT(ISBLANK(A76)),NOT(ISBLANK(B76)),ISBLANK(E76),IFERROR(FIND("FF--",A76)>1,FALSE)),"F.Comercializacion",IF(AND(NOT(ISBLANK(A76)),NOT(ISBLANK(B76)),NOT(ISBLANK(E76)),ISERROR(VLOOKUP(A76,'ListaN68 02-02-2025'!$A$12:$E$13375,5,0))),"Nuevo",IF(AND(NOT(ISBLANK(A76)),NOT(ISBLANK(B76)),NOT(ISBLANK(E76)),AND(E76-VLOOKUP(A76,'ListaN68 02-02-2025'!$A$12:$E$13375,5,0)>=-2,E76-VLOOKUP(A76,'ListaN68 02-02-2025'!$A$12:$E$13375,5,0)<=2)),"Igual",IF(AND(NOT(ISBLANK(A76)),NOT(ISBLANK(B76)),NOT(ISBLANK(E76)),E76-VLOOKUP(A76,'ListaN68 02-02-2025'!$A$12:$E$13375,5,0)>2),"Aumento",IF(AND(NOT(ISBLANK(A76)),NOT(ISBLANK(B76)),NOT(ISBLANK(E76)),E76-VLOOKUP(A76,'ListaN68 02-02-2025'!$A$12:$E$13375,5,0)<2),"Bajo","Error en codigo"))))))) -> Igual
A77: 102-25505 | B77: FICHA VELADOR MARFIL 10A RICHI | C77: UM 1u | 300u | D77: 21 | E77: 781.85 | AF77: =IF(AND(ISBLANK(A77),ISBLANK(B77),ISBLANK(E77)),"Blanco",IF(AND(ISBLANK(A77),NOT(ISBLANK(B77))),"Titulo",IF(AND(NOT(ISBLANK(A77)),NOT(ISBLANK(B77)),ISBLANK(E77),IFERROR(FIND("FF--",A77)>1,FALSE)),"F.Comercializacion",IF(AND(NOT(ISBLANK(A77)),NOT(ISBLANK(B77)),NOT(ISBLANK(E77)),ISERROR(VLOOKUP(A77,'ListaN68 02-02-2025'!$A$12:$E$13375,5,0))),"Nuevo",IF(AND(NOT(ISBLANK(A77)),NOT(ISBLANK(B77)),NOT(ISBLANK(E77)),AND(E77-VLOOKUP(A77,'ListaN68 02-02-2025'!$A$12:$E$13375,5,0)>=-2,E77-VLOOKUP(A77,'ListaN68 02-02-2025'!$A$12:$E$13375,5,0)<=2)),"Igual",IF(AND(NOT(ISBLANK(A77)),NOT(ISBLANK(B77)),NOT(ISBLANK(E77)),E77-VLOOKUP(A77,'ListaN68 02-02-2025'!$A$12:$E$13375,5,0)>2),"Aumento",IF(AND(NOT(ISBLANK(A77)),NOT(ISBLANK(B77)),NOT(ISBLANK(E77)),E77-VLOOKUP(A77,'ListaN68 02-02-2025'!$A$12:$E$13375,5,0)<2),"Bajo","Error en codigo"))))))) -> Igual
A78: 115-25002 | B78: INTERRUPTOR VELADOR GRIS 4A RICHI | C78: UM 1u | 300u | D78: 10.5 | E78: 621.435 | AF78: =IF(AND(ISBLANK(A78),ISBLANK(B78),ISBLANK(E78)),"Blanco",IF(AND(ISBLANK(A78),NOT(ISBLANK(B78))),"Titulo",IF(AND(NOT(ISBLANK(A78)),NOT(ISBLANK(B78)),ISBLANK(E78),IFERROR(FIND("FF--",A78)>1,FALSE)),"F.Comercializacion",IF(AND(NOT(ISBLANK(A78)),NOT(ISBLANK(B78)),NOT(ISBLANK(E78)),ISERROR(VLOOKUP(A78,'ListaN68 02-02-2025'!$A$12:$E$13375,5,0))),"Nuevo",IF(AND(NOT(ISBLANK(A78)),NOT(ISBLANK(B78)),NOT(ISBLANK(E78)),AND(E78-VLOOKUP(A78,'ListaN68 02-02-2025'!$A$12:$E$13375,5,0)>=-2,E78-VLOOKUP(A78,'ListaN68 02-02-2025'!$A$12:$E$13375,5,0)<=2)),"Igual",IF(AND(NOT(ISBLANK(A78)),NOT(ISBLANK(B78)),NOT(ISBLANK(E78)),E78-VLOOKUP(A78,'ListaN68 02-02-2025'!$A$12:$E$13375,5,0)>2),"Aumento",IF(AND(NOT(ISBLANK(A78)),NOT(ISBLANK(B78)),NOT(ISBLANK(E78)),E78-VLOOKUP(A78,'ListaN68 02-02-2025'!$A$12:$E$13375,5,0)<2),"Bajo","Error en codigo"))))))) -> Igual
A79: 115-25005 | B79: INTERRUPTOR VELADOR MARFIL 4A RICHI | C79: UM 1u | 300u | D79: 21 | E79: 621.435 | AF79: =IF(AND(ISBLANK(A79),ISBLANK(B79),ISBLANK(E79)),"Blanco",IF(AND(ISBLANK(A79),NOT(ISBLANK(B79))),"Titulo",IF(AND(NOT(ISBLANK(A79)),NOT(ISBLANK(B79)),ISBLANK(E79),IFERROR(FIND("FF--",A79)>1,FALSE)),"F.Comercializacion",IF(AND(NOT(ISBLANK(A79)),NOT(ISBLANK(B79)),NOT(ISBLANK(E79)),ISERROR(VLOOKUP(A79,'ListaN68 02-02-2025'!$A$12:$E$13375,5,0))),"Nuevo",IF(AND(NOT(ISBLANK(A79)),NOT(ISBLANK(B79)),NOT(ISBLANK(E79)),AND(E79-VLOOKUP(A79,'ListaN68 02-02-2025'!$A$12:$E$13375,5,0)>=-2,E79-VLOOKUP(A79,'ListaN68 02-02-2025'!$A$12:$E$13375,5,0)<=2)),"Igual",IF(AND(NOT(ISBLANK(A79)),NOT(ISBLANK(B79)),NOT(ISBLANK(E79)),E79-VLOOKUP(A79,'ListaN68 02-02-2025'!$A$12:$E$13375,5,0)>2),"Aumento",IF(AND(NOT(ISBLANK(A79)),NOT(ISBLANK(B79)),NOT(ISBLANK(E79)),E79-VLOOKUP(A79,'ListaN68 02-02-2025'!$A$12:$E$13375,5,0)<2),"Bajo","Error en codigo"))))))) -> Igual
A80: T-131 | B80: FICHA MACHO P/VELADOR REDONDO BCO | C80: UM 1u | 100u | D80: 21 | E80: 1020.367 | AF80: =IF(AND(ISBLANK(A80),ISBLANK(B80),ISBLANK(E80)),"Blanco",IF(AND(ISBLANK(A80),NOT(ISBLANK(B80))),"Titulo",IF(AND(NOT(ISBLANK(A80)),NOT(ISBLANK(B80)),ISBLANK(E80),IFERROR(FIND("FF--",A80)>1,FALSE)),"F.Comercializacion",IF(AND(NOT(ISBLANK(A80)),NOT(ISBLANK(B80)),NOT(ISBLANK(E80)),ISERROR(VLOOKUP(A80,'ListaN68 02-02-2025'!$A$12:$E$13375,5,0))),"Nuevo",IF(AND(NOT(ISBLANK(A80)),NOT(ISBLANK(B80)),NOT(ISBLANK(E80)),AND(E80-VLOOKUP(A80,'ListaN68 02-02-2025'!$A$12:$E$13375,5,0)>=-2,E80-VLOOKUP(A80,'ListaN68 02-02-2025'!$A$12:$E$13375,5,0)<=2)),"Igual",IF(AND(NOT(ISBLANK(A80)),NOT(ISBLANK(B80)),NOT(ISBLANK(E80)),E80-VLOOKUP(A80,'ListaN68 02-02-2025'!$A$12:$E$13375,5,0)>2),"Aumento",IF(AND(NOT(ISBLANK(A80)),NOT(ISBLANK(B80)),NOT(ISBLANK(E80)),E80-VLOOKUP(A80,'ListaN68 02-02-2025'!$A$12:$E$13375,5,0)<2),"Bajo","Error en codigo"))))))) -> Igual
A81: T132 | B81: FICHA MACHO P/VELADOR P/CHATA BCO | C81: UM 1u | 100 | D81: 21 | E81: 783.377 | AF81: =IF(AND(ISBLANK(A81),ISBLANK(B81),ISBLANK(E81)),"Blanco",IF(AND(ISBLANK(A81),NOT(ISBLANK(B81))),"Titulo",IF(AND(NOT(ISBLANK(A81)),NOT(ISBLANK(B81)),ISBLANK(E81),IFERROR(FIND("FF--",A81)>1,FALSE)),"F.Comercializacion",IF(AND(NOT(ISBLANK(A81)),NOT(ISBLANK(B81)),NOT(ISBLANK(E81)),ISERROR(VLOOKUP(A81,'ListaN68 02-02-2025'!$A$12:$E$13375,5,0))),"Nuevo",IF(AND(NOT(ISBLANK(A81)),NOT(ISBLANK(B81)),NOT(ISBLANK(E81)),AND(E81-VLOOKUP(A81,'ListaN68 02-02-2025'!$A$12:$E$13375,5,0)>=-2,E81-VLOOKUP(A81,'ListaN68 02-02-2025'!$A$12:$E$13375,5,0)<=2)),"Igual",IF(AND(NOT(ISBLANK(A81)),NOT(ISBLANK(B81)),NOT(ISBLANK(E81)),E81-VLOOKUP(A81,'ListaN68 02-02-2025'!$A$12:$E$13375,5,0)>2),"Aumento",IF(AND(NOT(ISBLANK(A81)),NOT(ISBLANK(B81)),NOT(ISBLANK(E81)),E81-VLOOKUP(A81,'ListaN68 02-02-2025'!$A$12:$E$13375,5,0)<2),"Bajo","Error en codigo"))))))) -> Igual
A82: T132-N | B82: FICHA MACHO P/VELADOR P/CHATA NEGRO | C82: UM 1u | 100 | D82: 21 | E82: 783.377 | AF82: =IF(AND(ISBLANK(A82),ISBLANK(B82),ISBLANK(E82)),"Blanco",IF(AND(ISBLANK(A82),NOT(ISBLANK(B82))),"Titulo",IF(AND(NOT(ISBLANK(A82)),NOT(ISBLANK(B82)),ISBLANK(E82),IFERROR(FIND("FF--",A82)>1,FALSE)),"F.Comercializacion",IF(AND(NOT(ISBLANK(A82)),NOT(ISBLANK(B82)),NOT(ISBLANK(E82)),ISERROR(VLOOKUP(A82,'ListaN68 02-02-2025'!$A$12:$E$13375,5,0))),"Nuevo",IF(AND(NOT(ISBLANK(A82)),NOT(ISBLANK(B82)),NOT(ISBLANK(E82)),AND(E82-VLOOKUP(A82,'ListaN68 02-02-2025'!$A$12:$E$13375,5,0)>=-2,E82-VLOOKUP(A82,'ListaN68 02-02-2025'!$A$12:$E$13375,5,0)<=2)),"Igual",IF(AND(NOT(ISBLANK(A82)),NOT(ISBLANK(B82)),NOT(ISBLANK(E82)),E82-VLOOKUP(A82,'ListaN68 02-02-2025'!$A$12:$E$13375,5,0)>2),"Aumento",IF(AND(NOT(ISBLANK(A82)),NOT(ISBLANK(B82)),NOT(ISBLANK(E82)),E82-VLOOKUP(A82,'ListaN68 02-02-2025'!$A$12:$E$13375,5,0)<2),"Bajo","Error en codigo"))))))) -> Igual
A83: 974310 | B83: FICHA MACHO MARFIL 10A | C83: UM 1u | 100u | 1000u | D83: 21 | E83: 348.867 | AF83: =IF(AND(ISBLANK(A83),ISBLANK(B83),ISBLANK(E83)),"Blanco",IF(AND(ISBLANK(A83),NOT(ISBLANK(B83))),"Titulo",IF(AND(NOT(ISBLANK(A83)),NOT(ISBLANK(B83)),ISBLANK(E83),IFERROR(FIND("FF--",A83)>1,FALSE)),"F.Comercializacion",IF(AND(NOT(ISBLANK(A83)),NOT(ISBLANK(B83)),NOT(ISBLANK(E83)),ISERROR(VLOOKUP(A83,'ListaN68 02-02-2025'!$A$12:$E$13375,5,0))),"Nuevo",IF(AND(NOT(ISBLANK(A83)),NOT(ISBLANK(B83)),NOT(ISBLANK(E83)),AND(E83-VLOOKUP(A83,'ListaN68 02-02-2025'!$A$12:$E$13375,5,0)>=-2,E83-VLOOKUP(A83,'ListaN68 02-02-2025'!$A$12:$E$13375,5,0)<=2)),"Igual",IF(AND(NOT(ISBLANK(A83)),NOT(ISBLANK(B83)),NOT(ISBLANK(E83)),E83-VLOOKUP(A83,'ListaN68 02-02-2025'!$A$12:$E$13375,5,0)>2),"Aumento",IF(AND(NOT(ISBLANK(A83)),NOT(ISBLANK(B83)),NOT(ISBLANK(E83)),E83-VLOOKUP(A83,'ListaN68 02-02-2025'!$A$12:$E$13375,5,0)<2),"Bajo","Error en codigo"))))))) -> Igual
A84: 974315 | B84: FICHA HEMBRA MARFIL 10A | C84: UM 1u | 100u | 1000u | D84: 21 | E84: 348.867 | AF84: =IF(AND(ISBLANK(A84),ISBLANK(B84),ISBLANK(E84)),"Blanco",IF(AND(ISBLANK(A84),NOT(ISBLANK(B84))),"Titulo",IF(AND(NOT(ISBLANK(A84)),NOT(ISBLANK(B84)),ISBLANK(E84),IFERROR(FIND("FF--",A84)>1,FALSE)),"F.Comercializacion",IF(AND(NOT(ISBLANK(A84)),NOT(ISBLANK(B84)),NOT(ISBLANK(E84)),ISERROR(VLOOKUP(A84,'ListaN68 02-02-2025'!$A$12:$E$13375,5,0))),"Nuevo",IF(AND(NOT(ISBLANK(A84)),NOT(ISBLANK(B84)),NOT(ISBLANK(E84)),AND(E84-VLOOKUP(A84,'ListaN68 02-02-2025'!$A$12:$E$13375,5,0)>=-2,E84-VLOOKUP(A84,'ListaN68 02-02-2025'!$A$12:$E$13375,5,0)<=2)),"Igual",IF(AND(NOT(ISBLANK(A84)),NOT(ISBLANK(B84)),NOT(ISBLANK(E84)),E84-VLOOKUP(A84,'ListaN68 02-02-2025'!$A$12:$E$13375,5,0)>2),"Aumento",IF(AND(NOT(ISBLANK(A84)),NOT(ISBLANK(B84)),NOT(ISBLANK(E84)),E84-VLOOKUP(A84,'ListaN68 02-02-2025'!$A$12:$E$13375,5,0)<2),"Bajo","Error en codigo"))))))) -> Igual
A85: F104B | B85: FICHA MACHO 2 PATAS PLANAS ECO | C85: UM 1u | 200u | D85: 21 | E85: 312.93 | AF85: =IF(AND(ISBLANK(A85),ISBLANK(B85),ISBLANK(E85)),"Blanco",IF(AND(ISBLANK(A85),NOT(ISBLANK(B85))),"Titulo",IF(AND(NOT(ISBLANK(A85)),NOT(ISBLANK(B85)),ISBLANK(E85),IFERROR(FIND("FF--",A85)>1,FALSE)),"F.Comercializacion",IF(AND(NOT(ISBLANK(A85)),NOT(ISBLANK(B85)),NOT(ISBLANK(E85)),ISERROR(VLOOKUP(A85,'ListaN68 02-02-2025'!$A$12:$E$13375,5,0))),"Nuevo",IF(AND(NOT(ISBLANK(A85)),NOT(ISBLANK(B85)),NOT(ISBLANK(E85)),AND(E85-VLOOKUP(A85,'ListaN68 02-02-2025'!$A$12:$E$13375,5,0)>=-2,E85-VLOOKUP(A85,'ListaN68 02-02-2025'!$A$12:$E$13375,5,0)<=2)),"Igual",IF(AND(NOT(ISBLANK(A85)),NOT(ISBLANK(B85)),NOT(ISBLANK(E85)),E85-VLOOKUP(A85,'ListaN68 02-02-2025'!$A$12:$E$13375,5,0)>2),"Aumento",IF(AND(NOT(ISBLANK(A85)),NOT(ISBLANK(B85)),NOT(ISBLANK(E85)),E85-VLOOKUP(A85,'ListaN68 02-02-2025'!$A$12:$E$13375,5,0)<2),"Bajo","Error en codigo"))))))) -> Igual
A86: F106B | B86: FICHA MACHO BIPOLAR ECO | C86: UM 1u | 300u | D86: 21 | E86: 309.548 | AF86: =IF(AND(ISBLANK(A86),ISBLANK(B86),ISBLANK(E86)),"Blanco",IF(AND(ISBLANK(A86),NOT(ISBLANK(B86))),"Titulo",IF(AND(NOT(ISBLANK(A86)),NOT(ISBLANK(B86)),ISBLANK(E86),IFERROR(FIND("FF--",A86)>1,FALSE)),"F.Comercializacion",IF(AND(NOT(ISBLANK(A86)),NOT(ISBLANK(B86)),NOT(ISBLANK(E86)),ISERROR(VLOOKUP(A86,'ListaN68 02-02-2025'!$A$12:$E$13375,5,0))),"Nuevo",IF(AND(NOT(ISBLANK(A86)),NOT(ISBLANK(B86)),NOT(ISBLANK(E86)),AND(E86-VLOOKUP(A86,'ListaN68 02-02-2025'!$A$12:$E$13375,5,0)>=-2,E86-VLOOKUP(A86,'ListaN68 02-02-2025'!$A$12:$E$13375,5,0)<=2)),"Igual",IF(AND(NOT(ISBLANK(A86)),NOT(ISBLANK(B86)),NOT(ISBLANK(E86)),E86-VLOOKUP(A86,'ListaN68 02-02-2025'!$A$12:$E$13375,5,0)>2),"Aumento",IF(AND(NOT(ISBLANK(A86)),NOT(ISBLANK(B86)),NOT(ISBLANK(E86)),E86-VLOOKUP(A86,'ListaN68 02-02-2025'!$A$12:$E$13375,5,0)<2),"Bajo","Error en codigo"))))))) -> Igual
A87: F107B | B87: FICHA HEMBRA BIPOLAR ECO | C87: UM 1u | 300u | D87: 21 | E87: 309.548 | AF87: =IF(AND(ISBLANK(A87),ISBLANK(B87),ISBLANK(E87)),"Blanco",IF(AND(ISBLANK(A87),NOT(ISBLANK(B87))),"Titulo",IF(AND(NOT(ISBLANK(A87)),NOT(ISBLANK(B87)),ISBLANK(E87),IFERROR(FIND("FF--",A87)>1,FALSE)),"F.Comercializacion",IF(AND(NOT(ISBLANK(A87)),NOT(ISBLANK(B87)),NOT(ISBLANK(E87)),ISERROR(VLOOKUP(A87,'ListaN68 02-02-2025'!$A$12:$E$13375,5,0))),"Nuevo",IF(AND(NOT(ISBLANK(A87)),NOT(ISBLANK(B87)),NOT(ISBLANK(E87)),AND(E87-VLOOKUP(A87,'ListaN68 02-02-2025'!$A$12:$E$13375,5,0)>=-2,E87-VLOOKUP(A87,'ListaN68 02-02-2025'!$A$12:$E$13375,5,0)<=2)),"Igual",IF(AND(NOT(ISBLANK(A87)),NOT(ISBLANK(B87)),NOT(ISBLANK(E87)),E87-VLOOKUP(A87,'ListaN68 02-02-2025'!$A$12:$E$13375,5,0)>2),"Aumento",IF(AND(NOT(ISBLANK(A87)),NOT(ISBLANK(B87)),NOT(ISBLANK(E87)),E87-VLOOKUP(A87,'ListaN68 02-02-2025'!$A$12:$E$13375,5,0)<2),"Bajo","Error en codigo"))))))) -> Igual
A88: PCT-840 | B88: PONCHITO C/NEU | C88: UM 1u | 100u | D88: 21 | E88: 154.613 | AF88: =IF(AND(ISBLANK(A88),ISBLANK(B88),ISBLANK(E88)),"Blanco",IF(AND(ISBLANK(A88),NOT(ISBLANK(B88))),"Titulo",IF(AND(NOT(ISBLANK(A88)),NOT(ISBLANK(B88)),ISBLANK(E88),IFERROR(FIND("FF--",A88)>1,FALSE)),"F.Comercializacion",IF(AND(NOT(ISBLANK(A88)),NOT(ISBLANK(B88)),NOT(ISBLANK(E88)),ISERROR(VLOOKUP(A88,'ListaN68 02-02-2025'!$A$12:$E$13375,5,0))),"Nuevo",IF(AND(NOT(ISBLANK(A88)),NOT(ISBLANK(B88)),NOT(ISBLANK(E88)),AND(E88-VLOOKUP(A88,'ListaN68 02-02-2025'!$A$12:$E$13375,5,0)>=-2,E88-VLOOKUP(A88,'ListaN68 02-02-2025'!$A$12:$E$13375,5,0)<=2)),"Igual",IF(AND(NOT(ISBLANK(A88)),NOT(ISBLANK(B88)),NOT(ISBLANK(E88)),E88-VLOOKUP(A88,'ListaN68 02-02-2025'!$A$12:$E$13375,5,0)>2),"Aumento",IF(AND(NOT(ISBLANK(A88)),NOT(ISBLANK(B88)),NOT(ISBLANK(E88)),E88-VLOOKUP(A88,'ListaN68 02-02-2025'!$A$12:$E$13375,5,0)<2),"Bajo","Error en codigo"))))))) -> Igual
AF89: =IF(AND(ISBLANK(A89),ISBLANK(B89),ISBLANK(E89)),"Blanco",IF(AND(ISBLANK(A89),NOT(ISBLANK(B89))),"Titulo",IF(AND(NOT(ISBLANK(A89)),NOT(ISBLANK(B89)),ISBLANK(E89),IFERROR(FIND("FF--",A89)>1,FALSE)),"F.Comercializacion",IF(AND(NOT(ISBLANK(A89)),NOT(ISBLANK(B89)),NOT(ISBLANK(E89)),ISERROR(VLOOKUP(A89,'ListaN68 02-02-2025'!$A$12:$E$13375,5,0))),"Nuevo",IF(AND(NOT(ISBLANK(A89)),NOT(ISBLANK(B89)),NOT(ISBLANK(E89)),AND(E89-VLOOKUP(A89,'ListaN68 02-02-2025'!$A$12:$E$13375,5,0)>=-2,E89-VLOOKUP(A89,'ListaN68 02-02-2025'!$A$12:$E$13375,5,0)<=2)),"Igual",IF(AND(NOT(ISBLANK(A89)),NOT(ISBLANK(B89)),NOT(ISBLANK(E89)),E89-VLOOKUP(A89,'ListaN68 02-02-2025'!$A$12:$E$13375,5,0)>2),"Aumento",IF(AND(NOT(ISBLANK(A89)),NOT(ISBLANK(B89)),NOT(ISBLANK(E89)),E89-VLOOKUP(A89,'ListaN68 02-02-2025'!$A$12:$E$13375,5,0)<2),"Bajo","Error en codigo"))))))) -> Blanco
B90: PORTALAMPARAS | AF90: =IF(AND(ISBLANK(A90),ISBLANK(B90),ISBLANK(E90)),"Blanco",IF(AND(ISBLANK(A90),NOT(ISBLANK(B90))),"Titulo",IF(AND(NOT(ISBLANK(A90)),NOT(ISBLANK(B90)),ISBLANK(E90),IFERROR(FIND("FF--",A90)>1,FALSE)),"F.Comercializacion",IF(AND(NOT(ISBLANK(A90)),NOT(ISBLANK(B90)),NOT(ISBLANK(E90)),ISERROR(VLOOKUP(A90,'ListaN68 02-02-2025'!$A$12:$E$13375,5,0))),"Nuevo",IF(AND(NOT(ISBLANK(A90)),NOT(ISBLANK(B90)),NOT(ISBLANK(E90)),AND(E90-VLOOKUP(A90,'ListaN68 02-02-2025'!$A$12:$E$13375,5,0)>=-2,E90-VLOOKUP(A90,'ListaN68 02-02-2025'!$A$12:$E$13375,5,0)<=2)),"Igual",IF(AND(NOT(ISBLANK(A90)),NOT(ISBLANK(B90)),NOT(ISBLANK(E90)),E90-VLOOKUP(A90,'ListaN68 02-02-2025'!$A$12:$E$13375,5,0)>2),"Aumento",IF(AND(NOT(ISBLANK(A90)),NOT(ISBLANK(B90)),NOT(ISBLANK(E90)),E90-VLOOKUP(A90,'ListaN68 02-02-2025'!$A$12:$E$13375,5,0)<2),"Bajo","Error en codigo"))))))) -> Titulo
AF91: =IF(AND(ISBLANK(A91),ISBLANK(B91),ISBLANK(E91)),"Blanco",IF(AND(ISBLANK(A91),NOT(ISBLANK(B91))),"Titulo",IF(AND(NOT(ISBLANK(A91)),NOT(ISBLANK(B91)),ISBLANK(E91),IFERROR(FIND("FF--",A91)>1,FALSE)),"F.Comercializacion",IF(AND(NOT(ISBLANK(A91)),NOT(ISBLANK(B91)),NOT(ISBLANK(E91)),ISERROR(VLOOKUP(A91,'ListaN68 02-02-2025'!$A$12:$E$13375,5,0))),"Nuevo",IF(AND(NOT(ISBLANK(A91)),NOT(ISBLANK(B91)),NOT(ISBLANK(E91)),AND(E91-VLOOKUP(A91,'ListaN68 02-02-2025'!$A$12:$E$13375,5,0)>=-2,E91-VLOOKUP(A91,'ListaN68 02-02-2025'!$A$12:$E$13375,5,0)<=2)),"Igual",IF(AND(NOT(ISBLANK(A91)),NOT(ISBLANK(B91)),NOT(ISBLANK(E91)),E91-VLOOKUP(A91,'ListaN68 02-02-2025'!$A$12:$E$13375,5,0)>2),"Aumento",IF(AND(NOT(ISBLANK(A91)),NOT(ISBLANK(B91)),NOT(ISBLANK(E91)),E91-VLOOKUP(A91,'ListaN68 02-02-2025'!$A$12:$E$13375,5,0)<2),"Bajo","Error en codigo"))))))) -> Blanco
A92: P-224P | B92: PORTALAMPARAS CON CHICOTE PREMIUM | C92: UM 1u | 100u | D92: 21 | E92: 363.248 | AF92: =IF(AND(ISBLANK(A92),ISBLANK(B92),ISBLANK(E92)),"Blanco",IF(AND(ISBLANK(A92),NOT(ISBLANK(B92))),"Titulo",IF(AND(NOT(ISBLANK(A92)),NOT(ISBLANK(B92)),ISBLANK(E92),IFERROR(FIND("FF--",A92)>1,FALSE)),"F.Comercializacion",IF(AND(NOT(ISBLANK(A92)),NOT(ISBLANK(B92)),NOT(ISBLANK(E92)),ISERROR(VLOOKUP(A92,'ListaN68 02-02-2025'!$A$12:$E$13375,5,0))),"Nuevo",IF(AND(NOT(ISBLANK(A92)),NOT(ISBLANK(B92)),NOT(ISBLANK(E92)),AND(E92-VLOOKUP(A92,'ListaN68 02-02-2025'!$A$12:$E$13375,5,0)>=-2,E92-VLOOKUP(A92,'ListaN68 02-02-2025'!$A$12:$E$13375,5,0)<=2)),"Igual",IF(AND(NOT(ISBLANK(A92)),NOT(ISBLANK(B92)),NOT(ISBLANK(E92)),E92-VLOOKUP(A92,'ListaN68 02-02-2025'!$A$12:$E$13375,5,0)>2),"Aumento",IF(AND(NOT(ISBLANK(A92)),NOT(ISBLANK(B92)),NOT(ISBLANK(E92)),E92-VLOOKUP(A92,'ListaN68 02-02-2025'!$A$12:$E$13375,5,0)<2),"Bajo","Error en codigo"))))))) -> Igual
A93: PCC-E27 | B93: PORTALAMPARAS CON CHICOTE | C93: UM 1u | 12u | 300u | D93: 21 | E93: 672.0645 | F93: -0.0068259386 | AF93: =IF(AND(ISBLANK(A93),ISBLANK(B93),ISBLANK(E93)),"Blanco",IF(AND(ISBLANK(A93),NOT(ISBLANK(B93))),"Titulo",IF(AND(NOT(ISBLANK(A93)),NOT(ISBLANK(B93)),ISBLANK(E93),IFERROR(FIND("FF--",A93)>1,FALSE)),"F.Comercializacion",IF(AND(NOT(ISBLANK(A93)),NOT(ISBLANK(B93)),NOT(ISBLANK(E93)),ISERROR(VLOOKUP(A93,'ListaN68 02-02-2025'!$A$12:$E$13375,5,0))),"Nuevo",IF(AND(NOT(ISBLANK(A93)),NOT(ISBLANK(B93)),NOT(ISBLANK(E93)),AND(E93-VLOOKUP(A93,'ListaN68 02-02-2025'!$A$12:$E$13375,5,0)>=-2,E93-VLOOKUP(A93,'ListaN68 02-02-2025'!$A$12:$E$13375,5,0)<=2)),"Igual",IF(AND(NOT(ISBLANK(A93)),NOT(ISBLANK(B93)),NOT(ISBLANK(E93)),E93-VLOOKUP(A93,'ListaN68 02-02-2025'!$A$12:$E$13375,5,0)>2),"Aumento",IF(AND(NOT(ISBLANK(A93)),NOT(ISBLANK(B93)),NOT(ISBLANK(E93)),E93-VLOOKUP(A93,'ListaN68 02-02-2025'!$A$12:$E$13375,5,0)<2),"Bajo","Error en codigo"))))))) -> Bajo
A94: P-P2P | B94: PORTALAMPARAS 2 PIEZAS NEGRO | C94: UM 1u | 100u | D94: 21 | E94: 385.487 | AF94: =IF(AND(ISBLANK(A94),ISBLANK(B94),ISBLANK(E94)),"Blanco",IF(AND(ISBLANK(A94),NOT(ISBLANK(B94))),"Titulo",IF(AND(NOT(ISBLANK(A94)),NOT(ISBLANK(B94)),ISBLANK(E94),IFERROR(FIND("FF--",A94)>1,FALSE)),"F.Comercializacion",IF(AND(NOT(ISBLANK(A94)),NOT(ISBLANK(B94)),NOT(ISBLANK(E94)),ISERROR(VLOOKUP(A94,'ListaN68 02-02-2025'!$A$12:$E$13375,5,0))),"Nuevo",IF(AND(NOT(ISBLANK(A94)),NOT(ISBLANK(B94)),NOT(ISBLANK(E94)),AND(E94-VLOOKUP(A94,'ListaN68 02-02-2025'!$A$12:$E$13375,5,0)>=-2,E94-VLOOKUP(A94,'ListaN68 02-02-2025'!$A$12:$E$13375,5,0)<=2)),"Igual",IF(AND(NOT(ISBLANK(A94)),NOT(ISBLANK(B94)),NOT(ISBLANK(E94)),E94-VLOOKUP(A94,'ListaN68 02-02-2025'!$A$12:$E$13375,5,0)>2),"Aumento",IF(AND(NOT(ISBLANK(A94)),NOT(ISBLANK(B94)),NOT(ISBLANK(E94)),E94-VLOOKUP(A94,'ListaN68 02-02-2025'!$A$12:$E$13375,5,0)<2),"Bajo","Error en codigo"))))))) -> Igual
A95: P-P3P | B95: PORTALAMPARAS 3 PIEZAS SUPER NEGRO | C95: UM 1u | 100u | D95: 21 | E95: 606.798 | AF95: =IF(AND(ISBLANK(A95),ISBLANK(B95),ISBLANK(E95)),"Blanco",IF(AND(ISBLANK(A95),NOT(ISBLANK(B95))),"Titulo",IF(AND(NOT(ISBLANK(A95)),NOT(ISBLANK(B95)),ISBLANK(E95),IFERROR(FIND("FF--",A95)>1,FALSE)),"F.Comercializacion",IF(AND(NOT(ISBLANK(A95)),NOT(ISBLANK(B95)),NOT(ISBLANK(E95)),ISERROR(VLOOKUP(A95,'ListaN68 02-02-2025'!$A$12:$E$13375,5,0))),"Nuevo",IF(AND(NOT(ISBLANK(A95)),NOT(ISBLANK(B95)),NOT(ISBLANK(E95)),AND(E95-VLOOKUP(A95,'ListaN68 02-02-2025'!$A$12:$E$13375,5,0)>=-2,E95-VLOOKUP(A95,'ListaN68 02-02-2025'!$A$12:$E$13375,5,0)<=2)),"Igual",IF(AND(NOT(ISBLANK(A95)),NOT(ISBLANK(B95)),NOT(ISBLANK(E95)),E95-VLOOKUP(A95,'ListaN68 02-02-2025'!$A$12:$E$13375,5,0)>2),"Aumento",IF(AND(NOT(ISBLANK(A95)),NOT(ISBLANK(B95)),NOT(ISBLANK(E95)),E95-VLOOKUP(A95,'ListaN68 02-02-2025'!$A$12:$E$13375,5,0)<2),"Bajo","Error en codigo"))))))) -> Igual
A96: P-P3PB | B96: PORTALAMPARAS 3 PIEZAS BLANCO | C96: UM 1u | 100u | D96: 21 | E96: 767.934 | AF96: =IF(AND(ISBLANK(A96),ISBLANK(B96),ISBLANK(E96)),"Blanco",IF(AND(ISBLANK(A96),NOT(ISBLANK(B96))),"Titulo",IF(AND(NOT(ISBLANK(A96)),NOT(ISBLANK(B96)),ISBLANK(E96),IFERROR(FIND("FF--",A96)>1,FALSE)),"F.Comercializacion",IF(AND(NOT(ISBLANK(A96)),NOT(ISBLANK(B96)),NOT(ISBLANK(E96)),ISERROR(VLOOKUP(A96,'ListaN68 02-02-2025'!$A$12:$E$13375,5,0))),"Nuevo",IF(AND(NOT(ISBLANK(A96)),NOT(ISBLANK(B96)),NOT(ISBLANK(E96)),AND(E96-VLOOKUP(A96,'ListaN68 02-02-2025'!$A$12:$E$13375,5,0)>=-2,E96-VLOOKUP(A96,'ListaN68 02-02-2025'!$A$12:$E$13375,5,0)<=2)),"Igual",IF(AND(NOT(ISBLANK(A96)),NOT(ISBLANK(B96)),NOT(ISBLANK(E96)),E96-VLOOKUP(A96,'ListaN68 02-02-2025'!$A$12:$E$13375,5,0)>2),"Aumento",IF(AND(NOT(ISBLANK(A96)),NOT(ISBLANK(B96)),NOT(ISBLANK(E96)),E96-VLOOKUP(A96,'ListaN68 02-02-2025'!$A$12:$E$13375,5,0)<2),"Bajo","Error en codigo"))))))) -> Igual
A97: P-P3PM | B97: PORTALAMPARAS 3 PIEZAS MIGNON NEGRO | C97: UM 1u | 200 | D97: 21 | E97: 884.998 | AF97: =IF(AND(ISBLANK(A97),ISBLANK(B97),ISBLANK(E97)),"Blanco",IF(AND(ISBLANK(A97),NOT(ISBLANK(B97))),"Titulo",IF(AND(NOT(ISBLANK(A97)),NOT(ISBLANK(B97)),ISBLANK(E97),IFERROR(FIND("FF--",A97)>1,FALSE)),"F.Comercializacion",IF(AND(NOT(ISBLANK(A97)),NOT(ISBLANK(B97)),NOT(ISBLANK(E97)),ISERROR(VLOOKUP(A97,'ListaN68 02-02-2025'!$A$12:$E$13375,5,0))),"Nuevo",IF(AND(NOT(ISBLANK(A97)),NOT(ISBLANK(B97)),NOT(ISBLANK(E97)),AND(E97-VLOOKUP(A97,'ListaN68 02-02-2025'!$A$12:$E$13375,5,0)>=-2,E97-VLOOKUP(A97,'ListaN68 02-02-2025'!$A$12:$E$13375,5,0)<=2)),"Igual",IF(AND(NOT(ISBLANK(A97)),NOT(ISBLANK(B97)),NOT(ISBLANK(E97)),E97-VLOOKUP(A97,'ListaN68 02-02-2025'!$A$12:$E$13375,5,0)>2),"Aumento",IF(AND(NOT(ISBLANK(A97)),NOT(ISBLANK(B97)),NOT(ISBLANK(E97)),E97-VLOOKUP(A97,'ListaN68 02-02-2025'!$A$12:$E$13375,5,0)<2),"Bajo","Error en codigo"))))))) -> Igual
A98: P-P3PMB | B98: PORTALAMPARAS 3 PIEZAS MIGNON BLANCO MARFIL | C98: UM 1u | 200 | D98: 21 | E98: 962.897 | AF98: =IF(AND(ISBLANK(A98),ISBLANK(B98),ISBLANK(E98)),"Blanco",IF(AND(ISBLANK(A98),NOT(ISBLANK(B98))),"Titulo",IF(AND(NOT(ISBLANK(A98)),NOT(ISBLANK(B98)),ISBLANK(E98),IFERROR(FIND("FF--",A98)>1,FALSE)),"F.Comercializacion",IF(AND(NOT(ISBLANK(A98)),NOT(ISBLANK(B98)),NOT(ISBLANK(E98)),ISERROR(VLOOKUP(A98,'ListaN68 02-02-2025'!$A$12:$E$13375,5,0))),"Nuevo",IF(AND(NOT(ISBLANK(A98)),NOT(ISBLANK(B98)),NOT(ISBLANK(E98)),AND(E98-VLOOKUP(A98,'ListaN68 02-02-2025'!$A$12:$E$13375,5,0)>=-2,E98-VLOOKUP(A98,'ListaN68 02-02-2025'!$A$12:$E$13375,5,0)<=2)),"Igual",IF(AND(NOT(ISBLANK(A98)),NOT(ISBLANK(B98)),NOT(ISBLANK(E98)),E98-VLOOKUP(A98,'ListaN68 02-02-2025'!$A$12:$E$13375,5,0)>2),"Aumento",IF(AND(NOT(ISBLANK(A98)),NOT(ISBLANK(B98)),NOT(ISBLANK(E98)),E98-VLOOKUP(A98,'ListaN68 02-02-2025'!$A$12:$E$13375,5,0)<2),"Bajo","Error en codigo"))))))) -> Igual
A99: P-P560 | B99: PORTALAMPARAS CON FICHA | C99: UM 1u | 85u | D99: 21 | E99: 1271.393 | AF99: =IF(AND(ISBLANK(A99),ISBLANK(B99),ISBLANK(E99)),"Blanco",IF(AND(ISBLANK(A99),NOT(ISBLANK(B99))),"Titulo",IF(AND(NOT(ISBLANK(A99)),NOT(ISBLANK(B99)),ISBLANK(E99),IFERROR(FIND("FF--",A99)>1,FALSE)),"F.Comercializacion",IF(AND(NOT(ISBLANK(A99)),NOT(ISBLANK(B99)),NOT(ISBLANK(E99)),ISERROR(VLOOKUP(A99,'ListaN68 02-02-2025'!$A$12:$E$13375,5,0))),"Nuevo",IF(AND(NOT(ISBLANK(A99)),NOT(ISBLANK(B99)),NOT(ISBLANK(E99)),AND(E99-VLOOKUP(A99,'ListaN68 02-02-2025'!$A$12:$E$13375,5,0)>=-2,E99-VLOOKUP(A99,'ListaN68 02-02-2025'!$A$12:$E$13375,5,0)<=2)),"Igual",IF(AND(NOT(ISBLANK(A99)),NOT(ISBLANK(B99)),NOT(ISBLANK(E99)),E99-VLOOKUP(A99,'ListaN68 02-02-2025'!$A$12:$E$13375,5,0)>2),"Aumento",IF(AND(NOT(ISBLANK(A99)),NOT(ISBLANK(B99)),NOT(ISBLANK(E99)),E99-VLOOKUP(A99,'ListaN68 02-02-2025'!$A$12:$E$13375,5,0)<2),"Bajo","Error en codigo"))))))) -> Igual
A100: PE-E27 | B100: PORTALAMPARAS CON FICHA MOVIBLE Y LLAVE | C100: UM 1u | 20u | 800u | D100: 21 | E100: 708.1485 | F100: -0.0068259386 | AF100: =IF(AND(ISBLANK(A100),ISBLANK(B100),ISBLANK(E100)),"Blanco",IF(AND(ISBLANK(A100),NOT(ISBLANK(B100))),"Titulo",IF(AND(NOT(ISBLANK(A100)),NOT(ISBLANK(B100)),ISBLANK(E100),IFERROR(FIND("FF--",A100)>1,FALSE)),"F.Comercializacion",IF(AND(NOT(ISBLANK(A100)),NOT(ISBLANK(B100)),NOT(ISBLANK(E100)),ISERROR(VLOOKUP(A100,'ListaN68 02-02-2025'!$A$12:$E$13375,5,0))),"Nuevo",IF(AND(NOT(ISBLANK(A100)),NOT(ISBLANK(B100)),NOT(ISBLANK(E100)),AND(E100-VLOOKUP(A100,'ListaN68 02-02-2025'!$A$12:$E$13375,5,0)>=-2,E100-VLOOKUP(A100,'ListaN68 02-02-2025'!$A$12:$E$13375,5,0)<=2)),"Igual",IF(AND(NOT(ISBLANK(A100)),NOT(ISBLANK(B100)),NOT(ISBLANK(E100)),E100-VLOOKUP(A100,'ListaN68 02-02-2025'!$A$12:$E$13375,5,0)>2),"Aumento",IF(AND(NOT(ISBLANK(A100)),NOT(ISBLANK(B100)),NOT(ISBLANK(E100)),E100-VLOOKUP(A100,'ListaN68 02-02-2025'!$A$12:$E$13375,5,0)<2),"Bajo","Error en codigo"))))))) -> Bajo
A101: PP-E14 | B101: PORTALAMPARAS CON CLIP E14 | C101: UM 25u | 1000u | D101: 21 | E101: 432.135 | F101: -0.0068259386 | AF101: =IF(AND(ISBLANK(A101),ISBLANK(B101),ISBLANK(E101)),"Blanco",IF(AND(ISBLANK(A101),NOT(ISBLANK(B101))),"Titulo",IF(AND(NOT(ISBLANK(A101)),NOT(ISBLANK(B101)),ISBLANK(E101),IFERROR(FIND("FF--",A101)>1,FALSE)),"F.Comercializacion",IF(AND(NOT(ISBLANK(A101)),NOT(ISBLANK(B101)),NOT(ISBLANK(E101)),ISERROR(VLOOKUP(A101,'ListaN68 02-02-2025'!$A$12:$E$13375,5,0))),"Nuevo",IF(AND(NOT(ISBLANK(A101)),NOT(ISBLANK(B101)),NOT(ISBLANK(E101)),AND(E101-VLOOKUP(A101,'ListaN68 02-02-2025'!$A$12:$E$13375,5,0)>=-2,E101-VLOOKUP(A101,'ListaN68 02-02-2025'!$A$12:$E$13375,5,0)<=2)),"Igual",IF(AND(NOT(ISBLANK(A101)),NOT(ISBLANK(B101)),NOT(ISBLANK(E101)),E101-VLOOKUP(A101,'ListaN68 02-02-2025'!$A$12:$E$13375,5,0)>2),"Aumento",IF(AND(NOT(ISBLANK(A101)),NOT(ISBLANK(B101)),NOT(ISBLANK(E101)),E101-VLOOKUP(A101,'ListaN68 02-02-2025'!$A$12:$E$13375,5,0)<2),"Bajo","Error en codigo"))))))) -> Bajo
A102: PP-E27 | B102: PORTALAMPARAS CON CLIP E27 | C102: UM 25u | 500u | D102: 21 | E102: 376.845 | F102: -0.0068259386 | AF102: =IF(AND(ISBLANK(A102),ISBLANK(B102),ISBLANK(E102)),"Blanco",IF(AND(ISBLANK(A102),NOT(ISBLANK(B102))),"Titulo",IF(AND(NOT(ISBLANK(A102)),NOT(ISBLANK(B102)),ISBLANK(E102),IFERROR(FIND("FF--",A102)>1,FALSE)),"F.Comercializacion",IF(AND(NOT(ISBLANK(A102)),NOT(ISBLANK(B102)),NOT(ISBLANK(E102)),ISERROR(VLOOKUP(A102,'ListaN68 02-02-2025'!$A$12:$E$13375,5,0))),"Nuevo",IF(AND(NOT(ISBLANK(A102)),NOT(ISBLANK(B102)),NOT(ISBLANK(E102)),AND(E102-VLOOKUP(A102,'ListaN68 02-02-2025'!$A$12:$E$13375,5,0)>=-2,E102-VLOOKUP(A102,'ListaN68 02-02-2025'!$A$12:$E$13375,5,0)<=2)),"Igual",IF(AND(NOT(ISBLANK(A102)),NOT(ISBLANK(B102)),NOT(ISBLANK(E102)),E102-VLOOKUP(A102,'ListaN68 02-02-2025'!$A$12:$E$13375,5,0)>2),"Aumento",IF(AND(NOT(ISBLANK(A102)),NOT(ISBLANK(B102)),NOT(ISBLANK(E102)),E102-VLOOKUP(A102,'ListaN68 02-02-2025'!$A$12:$E$13375,5,0)<2),"Bajo","Error en codigo"))))))) -> Bajo
A103: CR-E27 | B103: PORTALAMPARAS CERAMICO "L" | C103: UM 1u | 400u | D103: 21 | E103: 544.8975 | F103: -0.0068259386 | AF103: =IF(AND(ISBLANK(A103),ISBLANK(B103),ISBLANK(E103)),"Blanco",IF(AND(ISBLANK(A103),NOT(ISBLANK(B103))),"Titulo",IF(AND(NOT(ISBLANK(A103)),NOT(ISBLANK(B103)),ISBLANK(E103),IFERROR(FIND("FF--",A103)>1,FALSE)),"F.Comercializacion",IF(AND(NOT(ISBLANK(A103)),NOT(ISBLANK(B103)),NOT(ISBLANK(E103)),ISERROR(VLOOKUP(A103,'ListaN68 02-02-2025'!$A$12:$E$13375,5,0))),"Nuevo",IF(AND(NOT(ISBLANK(A103)),NOT(ISBLANK(B103)),NOT(ISBLANK(E103)),AND(E103-VLOOKUP(A103,'ListaN68 02-02-2025'!$A$12:$E$13375,5,0)>=-2,E103-VLOOKUP(A103,'ListaN68 02-02-2025'!$A$12:$E$13375,5,0)<=2)),"Igual",IF(AND(NOT(ISBLANK(A103)),NOT(ISBLANK(B103)),NOT(ISBLANK(E103)),E103-VLOOKUP(A103,'ListaN68 02-02-2025'!$A$12:$E$13375,5,0)>2),"Aumento",IF(AND(NOT(ISBLANK(A103)),NOT(ISBLANK(B103)),NOT(ISBLANK(E103)),E103-VLOOKUP(A103,'ListaN68 02-02-2025'!$A$12:$E$13375,5,0)<2),"Bajo","Error en codigo"))))))) -> Bajo
A104: CRP-E27 | B104: PORTALAMPARAS CERAMICO C/PUENTE | C104: UM 1u | 400u | D104: 21 | E104: 544.8975 | F104: -0.0068259386 | AF104: =IF(AND(ISBLANK(A104),ISBLANK(B104),ISBLANK(E104)),"Blanco",IF(AND(ISBLANK(A104),NOT(ISBLANK(B104))),"Titulo",IF(AND(NOT(ISBLANK(A104)),NOT(ISBLANK(B104)),ISBLANK(E104),IFERROR(FIND("FF--",A104)>1,FALSE)),"F.Comercializacion",IF(AND(NOT(ISBLANK(A104)),NOT(ISBLANK(B104)),NOT(ISBLANK(E104)),ISERROR(VLOOKUP(A104,'ListaN68 02-02-2025'!$A$12:$E$13375,5,0))),"Nuevo",IF(AND(NOT(ISBLANK(A104)),NOT(ISBLANK(B104)),NOT(ISBLANK(E104)),AND(E104-VLOOKUP(A104,'ListaN68 02-02-2025'!$A$12:$E$13375,5,0)>=-2,E104-VLOOKUP(A104,'ListaN68 02-02-2025'!$A$12:$E$13375,5,0)<=2)),"Igual",IF(AND(NOT(ISBLANK(A104)),NOT(ISBLANK(B104)),NOT(ISBLANK(E104)),E104-VLOOKUP(A104,'ListaN68 02-02-2025'!$A$12:$E$13375,5,0)>2),"Aumento",IF(AND(NOT(ISBLANK(A104)),NOT(ISBLANK(B104)),NOT(ISBLANK(E104)),E104-VLOOKUP(A104,'ListaN68 02-02-2025'!$A$12:$E$13375,5,0)<2),"Bajo","Error en codigo"))))))) -> Bajo
A105: PC-E40 | B105: PORTALAMPARAS CERAMICO E40 COMUN | C105: UM 1u | 120u | D105: 21 | E105: 2353.026 | F105: -0.0068259386 | AF105: =IF(AND(ISBLANK(A105),ISBLANK(B105),ISBLANK(E105)),"Blanco",IF(AND(ISBLANK(A105),NOT(ISBLANK(B105))),"Titulo",IF(AND(NOT(ISBLANK(A105)),NOT(ISBLANK(B105)),ISBLANK(E105),IFERROR(FIND("FF--",A105)>1,FALSE)),"F.Comercializacion",IF(AND(NOT(ISBLANK(A105)),NOT(ISBLANK(B105)),NOT(ISBLANK(E105)),ISERROR(VLOOKUP(A105,'ListaN68 02-02-2025'!$A$12:$E$13375,5,0))),"Nuevo",IF(AND(NOT(ISBLANK(A105)),NOT(ISBLANK(B105)),NOT(ISBLANK(E105)),AND(E105-VLOOKUP(A105,'ListaN68 02-02-2025'!$A$12:$E$13375,5,0)>=-2,E105-VLOOKUP(A105,'ListaN68 02-02-2025'!$A$12:$E$13375,5,0)<=2)),"Igual",IF(AND(NOT(ISBLANK(A105)),NOT(ISBLANK(B105)),NOT(ISBLANK(E105)),E105-VLOOKUP(A105,'ListaN68 02-02-2025'!$A$12:$E$13375,5,0)>2),"Aumento",IF(AND(NOT(ISBLANK(A105)),NOT(ISBLANK(B105)),NOT(ISBLANK(E105)),E105-VLOOKUP(A105,'ListaN68 02-02-2025'!$A$12:$E$13375,5,0)<2),"Bajo","Error en codigo"))))))) -> Bajo
...

Sheet ListaN68 02-02-2025
E1: $
B8: DISTRI-SAL
A14: CODIGO | B14: DESCRIPCION | C14: Cantidad x bulto | D14: IVA | E14: PRECIO SIN IVA | F14: variacion respecto a lista anterior (aplicado en lista)
B16: ELECTRONICA
A18: CRJ-11 | B18: CONECTOR MACHO RJ-11 6 CONTACTOS | C18: UM 1u | D18: 21 | E18: 56.26
A19: CRJ-45 | B19: CONECTOR MACHO RJ-45 8 CONTACTOS | C19: UM 1u | D19: 21 | E19: 118.77
A20: CRJ-9 | B20: CONECTOR MACHO RJ-9 4 CONTACTOS | C20: UM 1u | D20: 21 | E20: 56.26
A21: HDMI | B21: CABLE HDMI A HDMI X1.5MTS | C21: UM 1u | 10u | D21: 21 | E21: 3375.54
A22: USBM | B22: CABLE USB MACHO A MICRO USB 5 PINES | C22: UM 1u | D22: 21 | E22: 1931.56
A23: USBU | B23: CABLE MACHO USB A USB C 1,5MTS | C23: UM 1u | 25u | D23: 21 | E23: 2187.85
E24: 0
B25: TRIPLES Y ADAPTADORES | E25: 0
E26: 0
A27: 200 | B27: ADAPTADOR 2A3 T/ KALOP (M 2P - H 3P) | C27: UM 1u | 50u | 500u | D27: 21 | E27: 534.293
A28: 201 | B28: ADAPTADOR 2A3 T/ EXULT (M 2P - H 3P) | C28: UM 1u | 100u | D28: 21 | E28: 348.874
A29: 210 | B29: ADAPTADOR FICHA TURISTA | C29: UM 1u | 100u | D29: 21 | E29: 972.822
A30: 212 | B30: ADAPTADOR 3A2 MIG (PARED A F.MACHO) | C30: UM 1u | 100u | D30: 21 | E30: 919.636
A31: 215 | B31: TRIPLE IRROMPIBLE MIG | C31: UM 1u | 50u | D31: 21 | E31: 1249.887
A32: 216 | B32: TRIPLE IRROMPIBLE MIG ***CON NEUTRO**** 216 | C32: UM 1u | 50u | D32: 21 | E32: 1249.887
A33: 223 | B33: ADAPTADOR AMERICANO/ALEMAN BCO | C33: UM 1u | 100u | D33: 21 | E33: 892.423
A34: 223-N | B34: ADAPTADOR AMERICANO/ALEMAN NEGRO | C34: UM 1u | 100u | D34: 21 | E34: 892.423
A35: 224 | B35: ADAPTADOR AMERICANO/ALEMAN P/PLANA BCO | C35: UM 1u | 100u | D35: 21 | E35: 919.636
A36: 224-N | B36: ADAPTADOR AMERICANO/ALEMAN P/PLANA NEGRO | C36: UM 1u | 100u | D36: 21 | E36: 919.636
A37: 230 | B37: ADAPTADOR MULTIFUNCION | C37: UM 1u | 100u | D37: 21 | E37: 941.899
A38: LWW-K3 | B38: ADAPTADOR VIAJERO UNIVERSAL C/ FICHA | C38: UM 1u | 20u | 600u | D38: 21 | E38: 1571.945 | F38: 0.0068728522
A39: MU-A3 | B39: ADAPTADOR VIAJERO S/USB | C39: UM 1u | 20u | 200u | D39: 21 | E39: 3441.285 | F39: 0.0068728522
A40: MU-A4 | B40: ADAPTADOR VIAJERO C/USB | C40: UM 1u | 20u | 200u | D40: 21 | E40: 8581.97 | F40: 0.0068728522
A41: PE-727 | B41: ADAPTADOR VIAJERO UNIVERSAL | C41: UM 1u | 20u | 1000u | D41: 21 | E41: 597.72 | F41: 0.0068728522
E42: 0
B43: MULTI-FICHAS | E43: 0
E44: 0
A45: 127-60001 | B45: TOMA MULTIPLE DOBLE PATA CHATA BLANCA RICHI | C45: UM 1u | 150u | D45: 21 | E45: 1598.136
A46: 127-61001 | B46: TOMA MULTIPLE DOBLE PATA REDONDA BLANCA RICHI | C46: UM 1u | 150u | D46: 21 | E46: 1598.136
A47: 3001 | B47: MULTIFICHA TRIPLE PIRAMIDE PREMIUM C/NEU | C47: UM 1u | 100u | D47: 21 | E47: 2707.25
A48: 3002 | B48: MULTIFICHA TRIPLE PIRAMIDE PREMIUM | C48: UM 1u | 100u | D48: 21 | E48: 2436
E49: 0
B50: FICHAS | E50: 0
E51: 0
A52: 121 | B52: FICHA LONGITUDINAL C/NEU MACHO BLANCO MIG | C52: UM 1u | 50u | D52: 21 | E52: 957.856
A53: 121/N | B53: FICHA LONGITUDINAL C/NEU MACHO NEGRO MIG | C53: UM 1u | 50u | D53: 21 | E53: 957.856
A54: 227 | B54: FICHA LONGITUDINAL C/NEU HEMBRA BLANCO MIG | C54: UM 1u | 50u | D54: 21 | E54: 1030.586
A55: 227/N | B55: FICHA LONGITUDINAL C/NEU HEMBRA NEGRO MIG | C55: UM 1u | 50u | D55: 21 | E55: 1030.586
A56: 103-27302 | B56: FICHA LONGITUDINAL C/NEU MACHO GRAFITO RICHI | C56: UM 1u | 50u | 150u | D56: 21 | E56: 1012.52
A57: 125-27702 | B57: FICHA LONGITUDINAL C/NEU HEMBRA GRAFITO RICHI | C57: UM 1u | 50u | 150u | D57: 21 | E57: 1012.52
A58: K-3 | B58: FICHA LONGITUDINAL C/NEU MACHO T/K-3 ECO | C58: UM 1u | 100u | D58: 21 | E58: 490.05
A59: K-3H | B59: FICHA LONGITUDINAL C/NEU HEMBRA T/K-3 ECO | C59: UM 1u | 100u | D59: 21 | E59: 490.05
A60: F160 | B60: FICHA LONGITUDINAL C/NEU MACHO T/RICHI ECO | C60: UM 1u | 200u | D60: 21 | E60: 616.996
A61: F161 | B61: FICHA LONGITUDINAL C/NEU HEMBRA T/RICHI ECO | C61: UM 1u | 200u | D61: 21 | E61: 616.996
A62: F170N | B62: FICHA AXIAL C/NEU MACHO ECO NEGRA ALAN | C62: UM 1u | 300u | D62: 21 | E62: 430.064
A63: F171N | B63: FICHA AXIAL C/NEU HEMBRA ECO NEGRA ALAN | C63: UM 1u | 300u | D63: 21 | E63: 430.064
A64: 113 | B64: FICHA S/90º MACHO C/NEU BLANCO MIG | C64: UM 1u | 100u | D64: 21 | E64: 1074.866
A65: 113N | B65: FICHA S/90º MACHO C/NEU NEGRA MIG | C65: UM 1u | 100u | D65: 21 | E65: 1074.866
A66: 120 | B66: FICHA S/90º HEMBRA C/NEU BLANCO MIG | C66: UM 1u | 100u | D66: 21 | E66: 916.543
A67: 120N | B67: FICHA S/90º HEMBRA C/NEU NEGRA MIG | C67: UM 1u | 100u | D67: 21 | E67: 916.543
A68: F137B | B68: FICHA S/90º MACHO C/NEU BLANCO ALAN ECO | C68: UM 1u | 100u | D68: 21 | E68: 456.962
A69: F138B | B69: FICHA S/90º HEMBRA C/NEU BLANCO ALAN ECO BINORMA | C69: UM 1u | 100u | D69: 21 | E69: 456.962
A70: 103-28302 | B70: FICHA S/90º MACHO C/NEU GRAFITO 10A RICHI | C70: UM 1u | 200u | D70: 21 | E70: 1110.148
A71: 103-28305 | B71: FICHA S/90º MACHO C/NEU MARFIL 10A RICHI | C71: UM 1u | 200u | D71: 21 | E71: 1110.148
A72: 125-28702 | B72: FICHA S/90º HEMBRA GRAFITO 10A RICHI | C72: UM 1u | 200u | D72: 21 | E72: 1110.148
A73: 125-28705 | B73: FICHA S/90º HEMBRA MARFIL 10A RICHI | C73: UM 1u | 200u | D73: 21 | E73: 1110.148
A74: 141 | B74: FICHA S/90º MACHO C/AZA C/NEU | C74: UM 1u | 40u | D74: 21 | E74: 1366.157
A75: 142 | B75: FICHA S/90º MACHO C/AZA C/NEU 20A | C75: UM 1u | 40u | D75: 21 | E75: 1636.418
A76: 218 | B76: FICHA S/90º MACHO CON AZA PERNO REDONDO | C76: UM 1u | 40u | D76: 21 | E76: 1299.363
A77: 242 | B77: FICHA S/90º HEMBRA C/AZA C/NEU 20A | C77: UM 1u | 40u | D77: 21 | E77: 1653.736
A78: 250 | B78: FICHA S/90º HEMBRA C/AZA (BINORMA) | C78: UM 1u | 40u | D78: 21 | E78: 1270.915
A79: 219 | B79: INTERRUPTOR P/VELADOR BCO | C79: UM 1u | 100u | D79: 21 | E79: 716.165
A80: 219-N | B80: INTERRUPTOR P/VELADOR NEGRO | C80: UM 1u | 100u | D80: 21 | E80: 716.165
A81: 102-25502 | B81: FICHA VELADOR GRAFITO 10A RICHI | C81: UM 1u | 300u | D81: 21 | E81: 781.85
A82: 102-25505 | B82: FICHA VELADOR MARFIL 10A RICHI | C82: UM 1u | 300u | D82: 21 | E82: 781.85
A83: 115-25002 | B83: INTERRUPTOR VELADOR GRIS 4A RICHI | C83: UM 1u | 300u | D83: 10.5 | E83: 621.435
A84: 115-25005 | B84: INTERRUPTOR VELADOR MARFIL 4A RICHI | C84: UM 1u | 300u | D84: 21 | E84: 621.435
A85: T-131 | B85: FICHA MACHO P/VELADOR REDONDO BCO | C85: UM 1u | 100u | D85: 21 | E85: 1020.367
A86: T132 | B86: FICHA MACHO P/VELADOR P/CHATA BCO | C86: UM 1u | 100 | D86: 21 | E86: 783.377
A87: T132-N | B87: FICHA MACHO P/VELADOR P/CHATA NEGRO | C87: UM 1u | 100 | D87: 21 | E87: 783.377
A88: 974310 | B88: FICHA MACHO MARFIL 10A | C88: UM 1u | 100u | 1000u | D88: 21 | E88: 348.867
A89: 974315 | B89: FICHA HEMBRA MARFIL 10A | C89: UM 1u | 100u | 1000u | D89: 21 | E89: 348.867
A90: F104B | B90: FICHA MACHO 2 PATAS PLANAS ECO | C90: UM 1u | 200u | D90: 21 | E90: 312.93
A91: F106B | B91: FICHA MACHO BIPOLAR ECO | C91: UM 1u | 300u | D91: 21 | E91: 309.548
A92: F107B | B92: FICHA HEMBRA BIPOLAR ECO | C92: UM 1u | 300u | D92: 21 | E92: 309.548
A93: PCT-840 | B93: PONCHITO C/NEU | C93: UM 1u | 100u | D93: 21 | E93: 154.613
E94: 0
B95: PORTALAMPARAS | E95: 0
E96: 0
A97: P-224P | B97: PORTALAMPARAS CON CHICOTE PREMIUM | C97: UM 1u | 100u | D97: 21 | E97: 363.248 | F97: 0.039327273
A98: PCC-E27 | B98: PORTALAMPARAS CON CHICOTE | C98: UM 1u | 12u | 300u | D98: 21 | E98: 676.6835 | F98: 0.0068728522
A99: P-P2P | B99: PORTALAMPARAS 2 PIEZAS NEGRO | C99: UM 1u | 100u | D99: 21 | E99: 385.487
A100: P-P3P | B100: PORTALAMPARAS 3 PIEZAS SUPER NEGRO | C100: UM 1u | 100u | D100: 21 | E100: 606.798
A101: P-P3PB | B101: PORTALAMPARAS 3 PIEZAS BLANCO | C101: UM 1u | 100u | D101: 21 | E101: 767.934
A102: P-P3PM | B102: PORTALAMPARAS 3 PIEZAS MIGNON NEGRO | C102: UM 1u | 200 | D102: 21 | E102: 884.998
A103: P-P3PMB | B103: PORTALAMPARAS 3 PIEZAS MIGNON BLANCO MARFIL | C103: UM 1u | 200 | D103: 21 | E103: 962.897
A104: P-P560 | B104: PORTALAMPARAS CON FICHA | C104: UM 1u | 85u | D104: 21 | E104: 1271.393
A105: PE-E27 | B105: PORTALAMPARAS CON FICHA MOVIBLE Y LLAVE | C105: UM 1u | 20u | 800u | D105: 21 | E105: 713.0155 | F105: 0.0068728522
A106: PP-E14 | B106: PORTALAMPARAS CON CLIP E14 | C106: UM 25u | 1000u | D106: 21 | E106: 435.105 | F106: 0.0068728522
A107: PP-E27 | B107: PORTALAMPARAS CON CLIP E27 | C107: UM 25u | 500u | D107: 21 | E107: 379.435 | F107: 0.0068728522
A108: CR-E27 | B108: PORTALAMPARAS CERAMICO "L" | C108: UM 1u | 400u | D108: 21 | E108: 548.6425 | F108: 0.0068728522
A109: CRP-E27 | B109: PORTALAMPARAS CERAMICO C/PUENTE | C109: UM 1u | 400u | D109: 21 | E109: 548.6425 | F109: 0.0068728522
A110: PC-E40 | B110: PORTALAMPARAS CERAMICO E40 COMUN | C110: UM 1u | 120u | D110: 21 | E110: 2369.198 | F110: 0.0068728522
A111: 8026 | B111: PORTALAMPARAS RECEPTACULO RECTO NEGRO 1 PIEZA | C111: UM 1u | 96u | D111: 21 | E111: 623.001
A112: 8027 | B112: PORTALAMPARAS RECEPTACULO RECTO MARFIL 1 PIEZA | C112: UM 1u | 96u | D112: 21 | E112: 814.096
A113: 8028 | B113: PORTALAMPARAS RECEPTACULO CURVO NEGRO 1 PIEZA | C113: UM 1u | 96u | D113: 21 | E113: 641.923
...

Sheet Indice
A1: =HYPERLINK('ListaN69 09-02-2025'!$B$9,"Electronica") -> Electronica | C1: =HYPERLINK('ListaN69 09-02-2025'!B9,"Electronica") -> Electronica | H1: CABLE TIPO TALLER ECONOMICO | M1: ARTEFACTOS DE INTERIOR P/LAMPARAS DE BAJO CONSUMO | S1: ANAFES Y CALENTADORES | X1: SOPAPAS PVC | AC1: VARIOS
A2: =HYPERLINK('ListaN69 09-02-2025'!$B$9,"Electronica") -> Electronica | C2: CAÑO RIGIDO PVC DOBLADO EN FRIO | H2: CABLE ECONOMICO TIPO TALLER 5X1 ROLLO | M2: ILUMINACION/LISTONES | S2: REGULADORES GAS ENVASADO | X2: TUBOS EXTENSIBLES SANITARIOS | AC2: PISTOLAS Y BARRAS DE SICLICONA
A3: MULTI-FICHAS | C3: ACCESORIOS PARA CAÑO CURVABLE EN FRIO | H3: CABLE TIPO TALLER NORMALIZADO | M3: LISTONES BAJO MESADA | S3: SOPLETES | X3: SIFONES | AC3: CABALLETES
A4: FICHAS | C4: ACCESORIOS DE PVC (BLANCOS) | H4: CABLE TIPO TALLER EN BOBINA NORMALIZADO | M4: TUBOS FLUORESCENTES Y LED | S4: SOPLETES PARA GAS BUTANO | X4: ACCESORIOS PARA MOCHILAS E INODORO | AC4: GABINETES
A5: PORTALAMPARAS Y ZOCALOS | C5: ACCESORIOS DE HIERRO | H5: CABLE UNIPOLAR ECONOMICO | M5: BALASTROS/ARRANCADORES/CAPASITORES | S5: ACCESORIOS P/SOPLETES | X5: AUTOMATICOS PARA TANQUE | AC5: GABINETES METALICOS IP65
A6: FICHAS INDUSTRIALES | C6: GRAMPAS OMEGA Y 1/2 OMEGA | H6: CABLE UNIPOLAR EN BOBINA ECONOMICO | M6: LUMINARIAS DE EMRGENCIA LED | S6: MANGUERA GAS | X6: TERMOFUSORAS Y MAQUINA DE PINTAR | AC6: ALARMAS/TIMBRES/SENSORES
A7: INTERRUPTORES ESPECIALES | C7: CABLE CANAL | H7: CABLE UNIPOLAR NORMALIZADO | M7: ILUMINACION/PROYECTORES | S7: MANGUERA CRISTAL | X7: EXTRACTORES DE BAÑO
A8: INTERRUPTORES MINI | C8: ACCESORIOS PARA CABLE CANAL | H8: CABLE UNIPOLAR EN BOBINA NORMALIZADO | M8: iNTERRUPTORES HORARIOS/ SENSORES DE MOV | S8: MANGUERAS PARA HIDROCARBURO | X8: ACOPLES RAPIDOS
A9: INSTRUM.DE MEDICION | C9: PILAR/MEDIDOR | H9: CABLE PARA BOMBA SUMERGIBLE | M9: PROYECTORES DE CUARZO Y LAMPARAS | S9: MANGUERAS DE ALTA PRESION | X9: TERRAJAS
A10: PROTECTORES DE TENSION | C10: CAÑO PILAR | H10: CABLE SUBTERRANEO NORMALIZADO | M10: FOTOCELULAS | S10: ACCESORIOS PARA MANGUERA | X10: CAÑA Y ACCESORIOS DESTAPACION
A11: CAPSULADOS | C11: JABALINAS | H11: CABLE SOLDADURA | M11: ILUMINACION/INTERIOR | S11: MANGUERA AUTO-FLOTANTE PARA PILETA | X11: CINTAS DESTAPACION
A12: LINEA DE SUPERFICIE TAAD | C12: TERMICAS JELUZ | H12: CABLE AUTOMOTOR | M12: ILUMINACION/TORTUGAS Y FAROLES | S12: MEDIA SOMBRA 80% | X12: TEFLON "IGMA PLAST"
A13: LINEA DE SUPERFICIE CIOCCA PLAST | C13: DISYUNTORES JELUZ | H13: CABLE COAXIL/DATOS/COMUNICACION | M13: LUMINARIA DE CALLE | S13: MEDIA SOMBRA PREMIUM | X13: CINTA DE TEFLON TACSA
A14: LINEA DE SUPERFICIE MIG | C14: CONTACTORES MODULARES BAW | H14: ZAPATILLAS | M14: PORTATILES | S14: MEDIA SOMBRA 90% | X14: CINTA REFRIGERACION
A15: MODULOS LINEA VIEJA | C15: Contactores tripolares (bobina CA 50-60Hz) BAW | H15: ZAPATILLAS TOMACORRIENTE GENESIS | M15: LAMPARAS LED | S15: RAFIAS/CUBRE CERCOS | X15: CINTAS DE PAPEL TACSA
A16: MODULOS VERONA 2000 | C16: INTERRUPTORES DIFERENCIALES | H16: CINTAS PASACABLE PROFESIONAL VIYILANT | M16: LAMPARAS INCANDESC/BAJO CONS. | S16: MOSQUITEROS PLASTICOS | X16: CINTA MULTI PROPOSITO TACSA
A17: LINEA ARMADA DALY (MIG) | C17: Reles de protección | H17: CINTA PASACABLE VIYILANT | M17: LAMPARAS LED C/FUNCIONES | S17: TEJIDO DE ALAMBRE ELECTROSOLDADO | X17: TANZA
A18: LINEA ARMADA JELUZ | C18: Interruptores termomagnéticos | H18: CINTA PASA CABLE ALMA DE ACERO VIYILANT | M18: LAMPARAS LED FANTASIA | S18: POLIETILENO CRISTAL | X18: NIVELES
... A27: CAÑOS DE HIERRO | C27: CABLE TIPO TALLER EN BOBINA ECONOMICO | H27: CLIPS PARA BATERIA AISLADOS | M27: QUEMADORES INFRARROJOS | S27: GRIFERIAS | X27: ACCESORIOS PARA COMPRESOR Y SOLDADORA

Sheet Mis precios
AC1: ='ListaN69 09-02-2025'!AF1 -> 0
B3: Ver precios con iva? | C3: NO | AC3: ='ListaN69 09-02-2025'!AF2 -> 0
B4: Aplicar descuento por factura? | C4: NO
B5: Mi descuento | C5: 0 | AC5: ='ListaN69 09-02-2025'!AF3 -> 0
B6: Mi Ganancia | C6: 0 | AC6: ='ListaN69 09-02-2025'!AF4 -> 0
AC7: ='ListaN69 09-02-2025'!AF5 -> 0
AC8: ='ListaN69 09-02-2025'!AF6 -> 0
A9: CODIGO | B9: DESCRIPCION | C9: Cantidad x bulto | D9: Alicuota IVA | E9: Mi costo | F9: Mi precio de venta | AC9: ='ListaN69 09-02-2025'!AF7 -> 0
AC10: ='ListaN69 09-02-2025'!AF8 -> Blanco
B11: ELECTRONICA | AC11: ='ListaN69 09-02-2025'!AF9 -> Titulo
AC12: ='ListaN69 09-02-2025'!AF10 -> Blanco
A13: CRJ-11 | B13: CONECTOR MACHO RJ-11 6 CONTACTOS | C13: UM 1u | D13: 21 | E13: =IFERROR(VLOOKUP(A13,'ListaN69 09-02-2025'!$A$9:$E$9716,5,0)*IF($C$3="SI",((D4010/100)+1),1)*IF(AND($C$3="SI",$C$4="SI"),IF(D4010=21,0.92,IF(D4010=10.5,0.96,1)),1)*IF(ISNUMBER($C$5),1-$C$5,1),"-") -> 56.26 | F13: =IFERROR(E13*IF(ISNUMBER($C$6),1+$C$6,1),"-") -> 56.26 | AC13: ='ListaN69 09-02-2025'!AF11 -> Igual
A14: CRJ-45 | B14: CONECTOR MACHO RJ-45 8 CONTACTOS | C14: UM 1u | D14: 21 | E14: =IFERROR(VLOOKUP(A14,'ListaN69 09-02-2025'!$A$9:$E$9716,5,0)*IF($C$3="SI",((D4011/100)+1),1)*IF(AND($C$3="SI",$C$4="SI"),IF(D4011=21,0.92,IF(D4011=10.5,0.96,1)),1)*IF(ISNUMBER($C$5),1-$C$5,1),"-") -> 118.77 | F14: =IFERROR(E14*IF(ISNUMBER($C$6),1+$C$6,1),"-") -> 118.77 | AC14: ='ListaN69 09-02-2025'!AF12 -> Igual
A15: CRJ-9 | B15: CONECTOR MACHO RJ-9 4 CONTACTOS | C15: UM 1u | D15: 21 | E15: =IFERROR(VLOOKUP(A15,'ListaN69 09-02-2025'!$A$9:$E$9716,5,0)*IF($C$3="SI",((D4012/100)+1),1)*IF(AND($C$3="SI",$C$4="SI"),IF(D4012=21,0.92,IF(D4012=10.5,0.96,1)),1)*IF(ISNUMBER($C$5),1-$C$5,1),"-") -> 56.26 | F15: =IFERROR(E15*IF(ISNUMBER($C$6),1+$C$6,1),"-") -> 56.26 | AC15: ='ListaN69 09-02-2025'!AF13 -> Igual
A16: HDMI | B16: CABLE HDMI A HDMI X1.5MTS | C16: UM 1u | 10u | D16: 21 | E16: =IFERROR(VLOOKUP(A16,'ListaN69 09-02-2025'!$A$9:$E$9716,5,0)*IF($C$3="SI",((D4013/100)+1),1)*IF(AND($C$3="SI",$C$4="SI"),IF(D4013=21,0.92,IF(D4013=10.5,0.96,1)),1)*IF(ISNUMBER($C$5),1-$C$5,1),"-") -> 3375.54 | F16: =IFERROR(E16*IF(ISNUMBER($C$6),1+$C$6,1),"-") -> 3375.54 | AC16: ='ListaN69 09-02-2025'!AF14 -> Igual
A17: USBM | B17: CABLE USB MACHO A MICRO USB 5 PINES | C17: UM 1u | D17: 21 | E17: =IFERROR(VLOOKUP(A17,'ListaN69 09-02-2025'!$A$9:$E$9716,5,0)*IF($C$3="SI",((D4014/100)+1),1)*IF(AND($C$3="SI",$C$4="SI"),IF(D4014=21,0.92,IF(D4014=10.5,0.96,1)),1)*IF(ISNUMBER($C$5),1-$C$5,1),"-") -> 1931.56 | F17: =IFERROR(E17*IF(ISNUMBER($C$6),1+$C$6,1),"-") -> 1931.56 | AC17: ='ListaN69 09-02-2025'!AF15 -> Igual
A18: USBU | B18: CABLE MACHO USB A USB C 1,5MTS | C18: UM 1u | 25u | D18: 21 | E18: =IFERROR(VLOOKUP(A18,'ListaN69 09-02-2025'!$A$9:$E$9716,5,0)*IF($C$3="SI",((D4015/100)+1),1)*IF(AND($C$3="SI",$C$4="SI"),IF(D4015=21,0.92,IF(D4015=10.5,0.96,1)),1)*IF(ISNUMBER($C$5),1-$C$5,1),"-") -> 2187.85 | F18: =IFERROR(E18*IF(ISNUMBER($C$6),1+$C$6,1),"-") -> 2187.85 | AC18: ='ListaN69 09-02-2025'!AF16 -> Igual
E19: =IFERROR(VLOOKUP(A19,'ListaN69 09-02-2025'!$A$9:$E$9716,5,0)*IF($C$3="SI",((D4016/100)+1),1)*IF(AND($C$3="SI",$C$4="SI"),IF(D4016=21,0.92,IF(D4016=10.5,0.96,1)),1)*IF(ISNUMBER($C$5),1-$C$5,1),"-") -> - | F19: =IFERROR(E19*IF(ISNUMBER($C$6),1+$C$6,1),"-") -> - | AC19: ='ListaN69 09-02-2025'!AF17 -> Blanco
B20: TRIPLES Y ADAPTADORES | E20: =IFERROR(VLOOKUP(A20,'ListaN69 09-02-2025'!$A$9:$E$9716,5,0)*IF($C$3="SI",((D4017/100)+1),1)*IF(AND($C$3="SI",$C$4="SI"),IF(D4017=21,0.92,IF(D4017=10.5,0.96,1)),1)*IF(ISNUMBER($C$5),1-$C$5,1),"-") -> - | F20: =IFERROR(E20*IF(ISNUMBER($C$6),1+$C$6,1),"-") -> - | AC20: ='ListaN69 09-02-2025'!AF18 -> Titulo
E21: =IFERROR(VLOOKUP(A21,'ListaN69 09-02-2025'!$A$9:$E$9716,5,0)*IF($C$3="SI",((D4018/100)+1),1)*IF(AND($C$3="SI",$C$4="SI"),IF(D4018=21,0.92,IF(D4018=10.5,0.96,1)),1)*IF(ISNUMBER($C$5),1-$C$5,1),"-") -> - | F21: =IFERROR(E21*IF(ISNUMBER($C$6),1+$C$6,1),"-") -> - | AC21: ='ListaN69 09-02-2025'!AF19 -> Blanco
A22: 200 | B22: ADAPTADOR 2A3 T/ KALOP (M 2P - H 3P) | C22: UM 1u | 50u | 500u | D22: 21 | E22: =IFERROR(VLOOKUP(A22,'ListaN69 09-02-2025'!$A$9:$E$9716,5,0)*IF($C$3="SI",((D4019/100)+1),1)*IF(AND($C$3="SI",$C$4="SI"),IF(D4019=21,0.92,IF(D4019=10.5,0.96,1)),1)*IF(ISNUMBER($C$5),1-$C$5,1),"-") -> 534.293 | F22: =IFERROR(E22*IF(ISNUMBER($C$6),1+$C$6,1),"-") -> 534.293 | AC22: ='ListaN69 09-02-2025'!AF20 -> Igual
A23: 201 | B23: ADAPTADOR 2A3 T/ EXULT (M 2P - H 3P) | C23: UM 1u | 100u | D23: 21 | E23: =IFERROR(VLOOKUP(A23,'ListaN69 09-02-2025'!$A$9:$E$9716,5,0)*IF($C$3="SI",((D4020/100)+1),1)*IF(AND($C$3="SI",$C$4="SI"),IF(D4020=21,0.92,IF(D4020=10.5,0.96,1)),1)*IF(ISNUMBER($C$5),1-$C$5,1),"-") -> 348.874 | F23: =IFERROR(E23*IF(ISNUMBER($C$6),1+$C$6,1),"-") -> 348.874 | AC23: ='ListaN69 09-02-2025'!AF21 -> Igual
A24: 210 | B24: ADAPTADOR FICHA TURISTA | C24: UM 1u | 100u | D24: 21 | E24: =IFERROR(VLOOKUP(A24,'ListaN69 09-02-2025'!$A$9:$E$9716,5,0)*IF($C$3="SI",((D4021/100)+1),1)*IF(AND($C$3="SI",$C$4="SI"),IF(D4021=21,0.92,IF(D4021=10.5,0.96,1)),1)*IF(ISNUMBER($C$5),1-$C$5,1),"-") -> 972.822 | F24: =IFERROR(E24*IF(ISNUMBER($C$6),1+$C$6,1),"-") -> 972.822 | AC24: ='ListaN69 09-02-2025'!AF22 -> Igual
A25: 212 | B25: ADAPTADOR 3A2 MIG (PARED A F.MACHO) | C25: UM 1u | 100u | D25: 21 | E25: =IFERROR(VLOOKUP(A25,'ListaN69 09-02-2025'!$A$9:$E$9716,5,0)*IF($C$3="SI",((D4022/100)+1),1)*IF(AND($C$3="SI",$C$4="SI"),IF(D4022=21,0.92,IF(D4022=10.5,0.96,1)),1)*IF(ISNUMBER($C$5),1-$C$5,1),"-") -> 919.636 | F25: =IFERROR(E25*IF(ISNUMBER($C$6),1+$C$6,1),"-") -> 919.636 | AC25: ='ListaN69 09-02-2025'!AF23 -> Igual
A26: 215 | B26: TRIPLE IRROMPIBLE MIG | C26: UM 1u | 50u | D26: 21 | E26: =IFERROR(VLOOKUP(A26,'ListaN69 09-02-2025'!$A$9:$E$9716,5,0)*IF($C$3="SI",((D4023/100)+1),1)*IF(AND($C$3="SI",$C$4="SI"),IF(D4023=21,0.92,IF(D4023=10.5,0.96,1)),1)*IF(ISNUMBER($C$5),1-$C$5,1),"-") -> 1249.887 | F26: =IFERROR(E26*IF(ISNUMBER($C$6),1+$C$6,1),"-") -> 1249.887 | AC26: ='ListaN69 09-02-2025'!AF24 -> Igual
A27: 216 | B27: TRIPLE IRROMPIBLE MIG ***CON NEUTRO**** 216 | C27: UM 1u | 50u | D27: 21 | E27: =IFERROR(VLOOKUP(A27,'ListaN69 09-02-2025'!$A$9:$E$9716,5,0)*IF($C$3="SI",((D4024/100)+1),1)*IF(AND($C$3="SI",$C$4="SI"),IF(D4024=21,0.92,IF(D4024=10.5,0.96,1)),1)*IF(ISNUMBER($C$5),1-$C$5,1),"-") -> 1249.887 | F27: =IFERROR(E27*IF(ISNUMBER($C$6),1+$C$6,1),"-") -> 1249.887 | AC27: ='ListaN69 09-02-2025'!AF25 -> Igual
A28: 223 | B28: ADAPTADOR AMERICANO/ALEMAN BCO | C28: UM 1u | 100u | D28: 21 | E28: =IFERROR(VLOOKUP(A28,'ListaN69 09-02-2025'!$A$9:$E$9716,5,0)*IF($C$3="SI",((D4025/100)+1),1)*IF(AND($C$3="SI",$C$4="SI"),IF(D4025=21,0.92,IF(D4025=10.5,0.96,1)),1)*IF(ISNUMBER($C$5),1-$C$5,1),"-") -> 892.423 | F28: =IFERROR(E28*IF(ISNUMBER($C$6),1+$C$6,1),"-") -> 892.423 | AC28: ='ListaN69 09-02-2025'!AF26 -> Igual
A29: 223-N | B29: ADAPTADOR AMERICANO/ALEMAN NEGRO | C29: UM 1u | 100u | D29: 21 | E29: =IFERROR(VLOOKUP(A29,'ListaN69 09-02-2025'!$A$9:$E$9716,5,0)*IF($C$3="SI",((D4026/100)+1),1)*IF(AND($C$3="SI",$C$4="SI"),IF(D4026=21,0.92,IF(D4026=10.5,0.96,1)),1)*IF(ISNUMBER($C$5),1-$C$5,1),"-") -> 892.423 | F29: =IFERROR(E29*IF(ISNUMBER($C$6),1+$C$6,1),"-") -> 892.423 | AC29: ='ListaN69 09-02-2025'!AF27 -> Igual
A30: 224 | B30: ADAPTADOR AMERICANO/ALEMAN P/PLANA BCO | C30: UM 1u | 100u | D30: 21 | E30: =IFERROR(VLOOKUP(A30,'ListaN69 09-02-2025'!$A$9:$E$9716,5,0)*IF($C$3="SI",((D4027/100)+1),1)*IF(AND($C$3="SI",$C$4="SI"),IF(D4027=21,0.92,IF(D4027=10.5,0.96,1)),1)*IF(ISNUMBER($C$5),1-$C$5,1),"-") -> 919.636 | F30: =IFERROR(E30*IF(ISNUMBER($C$6),1+$C$6,1),"-") -> 919.636 | AC30: ='ListaN69 09-02-2025'!AF28 -> Igual
A31: 224-N | B31: ADAPTADOR AMERICANO/ALEMAN P/PLANA NEGRO | C31: UM 1u | 100u | D31: 21 | E31: =IFERROR(VLOOKUP(A31,'ListaN69 09-02-2025'!$A$9:$E$9716,5,0)*IF($C$3="SI",((D4028/100)+1),1)*IF(AND($C$3="SI",$C$4="SI"),IF(D4028=21,0.92,IF(D4028=10.5,0.96,1)),1)*IF(ISNUMBER($C$5),1-$C$5,1),"-") -> 919.636 | F31: =IFERROR(E31*IF(ISNUMBER($C$6),1+$C$6,1),"-") -> 919.636 | AC31: ='ListaN69 09-02-2025'!AF29 -> Igual
A32: 230 | B32: ADAPTADOR MULTIFUNCION | C32: UM 1u | 100u | D32: 21 | E32: =IFERROR(VLOOKUP(A32,'ListaN69 09-02-2025'!$A$9:$E$9716,5,0)*IF($C$3="SI",((D4029/100)+1),1)*IF(AND($C$3="SI",$C$4="SI"),IF(D4029=21,0.92,IF(D4029=10.5,0.96,1)),1)*IF(ISNUMBER($C$5),1-$C$5,1),"-") -> 941.899 | F32: =IFERROR(E32*IF(ISNUMBER($C$6),1+$C$6,1),"-") -> 941.899 | AC32: ='ListaN69 09-02-2025'!AF30 -> Igual
A33: LWW-K3 | B33: ADAPTADOR VIAJERO UNIVERSAL C/ FICHA | C33: UM 1u | 20u | 600u | D33: 21 | E33: =IFERROR(VLOOKUP(A33,'ListaN69 09-02-2025'!$A$9:$E$9716,5,0)*IF($C$3="SI",((D4030/100)+1),1)*IF(AND($C$3="SI",$C$4="SI"),IF(D4030=21,0.92,IF(D4030=10.5,0.96,1)),1)*IF(ISNUMBER($C$5),1-$C$5,1),"-") -> 1561.215 | F33: =IFERROR(E33*IF(ISNUMBER($C$6),1+$C$6,1),"-") -> 1561.215 | AC33: ='ListaN69 09-02-2025'!AF31 -> Bajo
A34: MU-A3 | B34: ADAPTADOR VIAJERO S/USB | C34: UM 1u | 20u | 200u | D34: 21 | E34: =IFERROR(VLOOKUP(A34,'ListaN69 09-02-2025'!$A$9:$E$9716,5,0)*IF($C$3="SI",((D4031/100)+1),1)*IF(AND($C$3="SI",$C$4="SI"),IF(D4031=21,0.92,IF(D4031=10.5,0.96,1)),1)*IF(ISNUMBER($C$5),1-$C$5,1),"-") -> 3417.795 | F34: =IFERROR(E34*IF(ISNUMBER($C$6),1+$C$6,1),"-") -> 3417.795 | AC34: ='ListaN69 09-02-2025'!AF32 -> Bajo
A35: MU-A4 | B35: ADAPTADOR VIAJERO C/USB | C35: UM 1u | 20u | 200u | D35: 21 | E35: =IFERROR(VLOOKUP(A35,'ListaN69 09-02-2025'!$A$9:$E$9716,5,0)*IF($C$3="SI",((D4032/100)+1),1)*IF(AND($C$3="SI",$C$4="SI"),IF(D4032=21,0.92,IF(D4032=10.5,0.96,1)),1)*IF(ISNUMBER($C$5),1-$C$5,1),"-") -> 8523.39 | F35: =IFERROR(E35*IF(ISNUMBER($C$6),1+$C$6,1),"-") -> 8523.39 | AC35: ='ListaN69 09-02-2025'!AF33 -> Bajo
A36: PE-727 | B36: ADAPTADOR VIAJERO UNIVERSAL | C36: UM 1u | 20u | 1000u | D36: 21 | E36: =IFERROR(VLOOKUP(A36,'ListaN69 09-02-2025'!$A$9:$E$9716,5,0)*IF($C$3="SI",((D4033/100)+1),1)*IF(AND($C$3="SI",$C$4="SI"),IF(D4033=21,0.92,IF(D4033=10.5,0.96,1)),1)*IF(ISNUMBER($C$5),1-$C$5,1),"-") -> 593.64 | F36: =IFERROR(E36*IF(ISNUMBER($C$6),1+$C$6,1),"-") -> 593.64 | AC36: ='ListaN69 09-02-2025'!AF34 -> Bajo
E37: =IFERROR(VLOOKUP(A37,'ListaN69 09-02-2025'!$A$9:$E$9716,5,0)*IF($C$3="SI",((D4034/100)+1),1)*IF(AND($C$3="SI",$C$4="SI"),IF(D4034=21,0.92,IF(D4034=10.5,0.96,1)),1)*IF(ISNUMBER($C$5),1-$C$5,1),"-") -> - | F37: =IFERROR(E37*IF(ISNUMBER($C$6),1+$C$6,1),"-") -> - | AC37: ='ListaN69 09-02-2025'!AF35 -> Blanco
B38: MULTI-FICHAS | E38: =IFERROR(VLOOKUP(A38,'ListaN69 09-02-2025'!$A$9:$E$9716,5,0)*IF($C$3="SI",((D4035/100)+1),1)*IF(AND($C$3="SI",$C$4="SI"),IF(D4035=21,0.92,IF(D4035=10.5,0.96,1)),1)*IF(ISNUMBER($C$5),1-$C$5,1),"-") -> - | F38: =IFERROR(E38*IF(ISNUMBER($C$6),1+$C$6,1),"-") -> - | AC38: ='ListaN69 09-02-2025'!AF36 -> Titulo
E39: =IFERROR(VLOOKUP(A39,'ListaN69 09-02-2025'!$A$9:$E$9716,5,0)*IF($C$3="SI",((D4036/100)+1),1)*IF(AND($C$3="SI",$C$4="SI"),IF(D4036=21,0.92,IF(D4036=10.5,0.96,1)),1)*IF(ISNUMBER($C$5),1-$C$5,1),"-") -> - | F39: =IFERROR(E39*IF(ISNUMBER($C$6),1+$C$6,1),"-") -> - | AC39: ='ListaN69 09-02-2025'!AF37 -> Blanco
A40: 127-60001 | B40: TOMA MULTIPLE DOBLE PATA CHATA BLANCA RICHI | C40: UM 1u | 150u | D40: 21 | E40: =IFERROR(VLOOKUP(A40,'ListaN69 09-02-2025'!$A$9:$E$9716,5,0)*IF($C$3="SI",((D4037/100)+1),1)*IF(AND($C$3="SI",$C$4="SI"),IF(D4037=21,0.92,IF(D4037=10.5,0.96,1)),1)*IF(ISNUMBER($C$5),1-$C$5,1),"-") -> 1598.136 | F40: =IFERROR(E40*IF(ISNUMBER($C$6),1+$C$6,1),"-") -> 1598.136 | AC40: ='ListaN69 09-02-2025'!AF38 -> Igual
A41: 127-61001 | B41: TOMA MULTIPLE DOBLE PATA REDONDA BLANCA RICHI | C41: UM 1u | 150u | D41: 21 | E41: =IFERROR(VLOOKUP(A41,'ListaN69 09-02-2025'!$A$9:$E$9716,5,0)*IF($C$3="SI",((D4038/100)+1),1)*IF(AND($C$3="SI",$C$4="SI"),IF(D4038=21,0.92,IF(D4038=10.5,0.96,1)),1)*IF(ISNUMBER($C$5),1-$C$5,1),"-") -> 1598.136 | F41: =IFERROR(E41*IF(ISNUMBER($C$6),1+$C$6,1),"-") -> 1598.136 | AC41: ='ListaN69 09-02-2025'!AF39 -> Igual
A42: 3001 | B42: MULTIFICHA TRIPLE PIRAMIDE PREMIUM C/NEU | C42: UM 1u | 100u | D42: 21 | E42: =IFERROR(VLOOKUP(A42,'ListaN69 09-02-2025'!$A$9:$E$9716,5,0)*IF($C$3="SI",((D4039/100)+1),1)*IF(AND($C$3="SI",$C$4="SI"),IF(D4039=21,0.92,IF(D4039=10.5,0.96,1)),1)*IF(ISNUMBER($C$5),1-$C$5,1),"-") -> 2707.25 | F42: =IFERROR(E42*IF(ISNUMBER($C$6),1+$C$6,1),"-") -> 2707.25 | AC42: ='ListaN69 09-02-2025'!AF40 -> Igual
A43: 3002 | B43: MULTIFICHA TRIPLE PIRAMIDE PREMIUM | C43: UM 1u | 100u | D43: 21 | E43: =IFERROR(VLOOKUP(A43,'ListaN69 09-02-2025'!$A$9:$E$9716,5,0)*IF($C$3="SI",((D4040/100)+1),1)*IF(AND($C$3="SI",$C$4="SI"),IF(D4040=21,0.92,IF(D4040=10.5,0.96,1)),1)*IF(ISNUMBER($C$5),1-$C$5,1),"-") -> 2436 | F43: =IFERROR(E43*IF(ISNUMBER($C$6),1+$C$6,1),"-") -> 2436 | AC43: ='ListaN69 09-02-2025'!AF41 -> Igual
A44: MF2 | B44: MULTI-FICHA DOBLE | C44: UM 1u | 80u | D44: 21 | E44: =IFERROR(VLOOKUP(A44,'ListaN69 09-02-2025'!$A$9:$E$9716,5,0)*IF($C$3="SI",((D4041/100)+1),1)*IF(AND($C$3="SI",$C$4="SI"),IF(D4041=21,0.92,IF(D4041=10.5,0.96,1)),1)*IF(ISNUMBER($C$5),1-$C$5,1),"-") -> 1551.919 | F44: =IFERROR(E44*IF(ISNUMBER($C$6),1+$C$6,1),"-") -> 1551.919 | AC44: ='ListaN69 09-02-2025'!AF42 -> Nuevo
A45: MF2C | B45: MULTI-FICHA DOBLE C/NEU | C45: UM 1u | 80u | D45: 21 | E45: =IFERROR(VLOOKUP(A45,'ListaN69 09-02-2025'!$A$9:$E$9716,5,0)*IF($C$3="SI",((D4042/100)+1),1)*IF(AND($C$3="SI",$C$4="SI"),IF(D4042=21,0.92,IF(D4042=10.5,0.96,1)),1)*IF(ISNUMBER($C$5),1-$C$5,1),"-") -> 1551.919 | F45: =IFERROR(E45*IF(ISNUMBER($C$6),1+$C$6,1),"-") -> 1551.919 | AC45: ='ListaN69 09-02-2025'!AF43 -> Nuevo
E46: =IFERROR(VLOOKUP(A46,'ListaN69 09-02-2025'!$A$9:$E$9716,5,0)*IF($C$3="SI",((D4043/100)+1),1)*IF(AND($C$3="SI",$C$4="SI"),IF(D4043=21,0.92,IF(D4043=10.5,0.96,1)),1)*IF(ISNUMBER($C$5),1-$C$5,1),"-") -> - | F46: =IFERROR(E46*IF(ISNUMBER($C$6),1+$C$6,1),"-") -> - | AC46: ='ListaN69 09-02-2025'!AF44 -> Blanco
B47: FICHAS | E47: =IFERROR(VLOOKUP(A47,'ListaN69 09-02-2025'!$A$9:$E$9716,5,0)*IF($C$3="SI",((D4044/100)+1),1)*IF(AND($C$3="SI",$C$4="SI"),IF(D4044=21,0.92,IF(D4044=10.5,0.96,1)),1)*IF(ISNUMBER($C$5),1-$C$5,1),"-") -> - | F47: =IFERROR(E47*IF(ISNUMBER($C$6),1+$C$6,1),"-") -> - | AC47: ='ListaN69 09-02-2025'!AF45 -> Titulo
E48: =IFERROR(VLOOKUP(A48,'ListaN69 09-02-2025'!$A$9:$E$9716,5,0)*IF($C$3="SI",((D4045/100)+1),1)*IF(AND($C$3="SI",$C$4="SI"),IF(D4045=21,0.92,IF(D4045=10.5,0.96,1)),1)*IF(ISNUMBER($C$5),1-$C$5,1),"-") -> - | F48: =IFERROR(E48*IF(ISNUMBER($C$6),1+$C$6,1),"-") -> - | AC48: ='ListaN69 09-02-2025'!AF46 -> Blanco
A49: 121 | B49: FICHA LONGITUDINAL C/NEU MACHO BLANCO MIG | C49: UM 1u | 50u | D49: 21 | E49: =IFERROR(VLOOKUP(A49,'ListaN69 09-02-2025'!$A$9:$E$9716,5,0)*IF($C$3="SI",((D4046/100)+1),1)*IF(AND($C$3="SI",$C$4="SI"),IF(D4046=21,0.92,IF(D4046=10.5,0.96,1)),1)*IF(ISNUMBER($C$5),1-$C$5,1),"-") -> 957.856 | F49: =IFERROR(E49*IF(ISNUMBER($C$6),1+$C$6,1),"-") -> 957.856 | AC49: ='ListaN69 09-02-2025'!AF47 -> Igual
A50: 121/N | B50: FICHA LONGITUDINAL C/NEU MACHO NEGRO MIG | C50: UM 1u | 50u | D50: 21 | E50: =IFERROR(VLOOKUP(A50,'ListaN69 09-02-2025'!$A$9:$E$9716,5,0)*IF($C$3="SI",((D4047/100)+1),1)*IF(AND($C$3="SI",$C$4="SI"),IF(D4047=21,0.92,IF(D4047=10.5,0.96,1)),1)*IF(ISNUMBER($C$5),1-$C$5,1),"-") -> 957.856 | F50: =IFERROR(E50*IF(ISNUMBER($C$6),1+$C$6,1),"-") -> 957.856 | AC50: ='ListaN69 09-02-2025'!AF48 -> Igual
A51: 227 | B51: FICHA LONGITUDINAL C/NEU HEMBRA BLANCO MIG | C51: UM 1u | 50u | D51: 21 | E51: =IFERROR(VLOOKUP(A51,'ListaN69 09-02-2025'!$A$9:$E$9716,5,0)*IF($C$3="SI",((D4048/100)+1),1)*IF(AND($C$3="SI",$C$4="SI"),IF(D4048=21,0.92,IF(D4048=10.5,0.96,1)),1)*IF(ISNUMBER($C$5),1-$C$5,1),"-") -> 1030.586 | F51: =IFERROR(E51*IF(ISNUMBER($C$6),1+$C$6,1),"-") -> 1030.586 | AC51: ='ListaN69 09-02-2025'!AF49 -> Igual
A52: 227/N | B52: FICHA LONGITUDINAL C/NEU HEMBRA NEGRO MIG | C52: UM 1u | 50u | D52: 21 | E52: =IFERROR(VLOOKUP(A52,'ListaN69 09-02-2025'!$A$9:$E$9716,5,0)*IF($C$3="SI",((D4049/100)+1),1)*IF(AND($C$3="SI",$C$4="SI"),IF(D4049=21,0.92,IF(D4049=10.5,0.96,1)),1)*IF(ISNUMBER($C$5),1-$C$5,1),"-") -> 1030.586 | F52: =IFERROR(E52*IF(ISNUMBER($C$6),1+$C$6,1),"-") -> 1030.586 | AC52: ='ListaN69 09-02-2025'!AF50 -> Igual
A53: 103-27302 | B53: FICHA LONGITUDINAL C/NEU MACHO GRAFITO RICHI | C53: UM 1u | 50u | 150u | D53: 21 | E53: =IFERROR(VLOOKUP(A53,'ListaN69 09-02-2025'!$A$9:$E$9716,5,0)*IF($C$3="SI",((D4050/100)+1),1)*IF(AND($C$3="SI",$C$4="SI"),IF(D4050=21,0.92,IF(D4050=10.5,0.96,1)),1)*IF(ISNUMBER($C$5),1-$C$5,1),"-") -> 1012.52 | F53: =IFERROR(E53*IF(ISNUMBER($C$6),1+$C$6,1),"-") -> 1012.52 | AC53: ='ListaN69 09-02-2025'!AF51 -> Igual
A54: 125-27702 | B54: FICHA LONGITUDINAL C/NEU HEMBRA GRAFITO RICHI | C54: UM 1u | 50u | 150u | D54: 21 | E54: =IFERROR(VLOOKUP(A54,'ListaN69 09-02-2025'!$A$9:$E$9716,5,0)*IF($C$3="SI",((D4051/100)+1),1)*IF(AND($C$3="SI",$C$4="SI"),IF(D4051=21,0.92,IF(D4051=10.5,0.96,1)),1)*IF(ISNUMBER($C$5),1-$C$5,1),"-") -> 1012.52 | F54: =IFERROR(E54*IF(ISNUMBER($C$6),1+$C$6,1),"-") -> 1012.52 | AC54: ='ListaN69 09-02-2025'!AF52 -> Igual
A55: K-3 | B55: FICHA LONGITUDINAL C/NEU MACHO T/K-3 ECO | C55: UM 1u | 100u | D55: 21 | E55: =IFERROR(VLOOKUP(A55,'ListaN69 09-02-2025'!$A$9:$E$9716,5,0)*IF($C$3="SI",((D4052/100)+1),1)*IF(AND($C$3="SI",$C$4="SI"),IF(D4052=21,0.92,IF(D4052=10.5,0.96,1)),1)*IF(ISNUMBER($C$5),1-$C$5,1),"-") -> 490.05 | F55: =IFERROR(E55*IF(ISNUMBER($C$6),1+$C$6,1),"-") -> 490.05 | AC55: ='ListaN69 09-02-2025'!AF53 -> Igual
A56: K-3H | B56: FICHA LONGITUDINAL C/NEU HEMBRA T/K-3 ECO | C56: UM 1u | 100u | D56: 21 | E56: =IFERROR(VLOOKUP(A56,'ListaN69 09-02-2025'!$A$9:$E$9716,5,0)*IF($C$3="SI",((D4053/100)+1),1)*IF(AND($C$3="SI",$C$4="SI"),IF(D4053=21,0.92,IF(D4053=10.5,0.96,1)),1)*IF(ISNUMBER($C$5),1-$C$5,1),"-") -> 490.05 | F56: =IFERROR(E56*IF(ISNUMBER($C$6),1+$C$6,1),"-") -> 490.05 | AC56: ='ListaN69 09-02-2025'!AF54 -> Igual
A57: F160 | B57: FICHA LONGITUDINAL C/NEU MACHO T/RICHI ECO | C57: UM 1u | 200u | D57: 21 | E57: =IFERROR(VLOOKUP(A57,'ListaN69 09-02-2025'!$A$9:$E$9716,5,0)*IF($C$3="SI",((D4054/100)+1),1)*IF(AND($C$3="SI",$C$4="SI"),IF(D4054=21,0.92,IF(D4054=10.5,0.96,1)),1)*IF(ISNUMBER($C$5),1-$C$5,1),"-") -> 616.996 | F57: =IFERROR(E57*IF(ISNUMBER($C$6),1+$C$6,1),"-") -> 616.996 | AC57: ='ListaN69 09-02-2025'!AF55 -> Igual
A58: F161 | B58: FICHA LONGITUDINAL C/NEU HEMBRA T/RICHI ECO | C58: UM 1u | 200u | D58: 21 | E58: =IFERROR(VLOOKUP(A58,'ListaN69 09-02-2025'!$A$9:$E$9716,5,0)*IF($C$3="SI",((D4055/100)+1),1)*IF(AND($C$3="SI",$C$4="SI"),IF(D4055=21,0.92,IF(D4055=10.5,0.96,1)),1)*IF(ISNUMBER($C$5),1-$C$5,1),"-") -> 616.996 | F58: =IFERROR(E58*IF(ISNUMBER($C$6),1+$C$6,1),"-") -> 616.996 | AC58: ='ListaN69 09-02-2025'!AF56 -> Igual
A59: F170N | B59: FICHA AXIAL C/NEU MACHO ECO NEGRA ALAN | C59: UM 1u | 300u | D59: 21 | E59: =IFERROR(VLOOKUP(A59,'ListaN69 09-02-2025'!$A$9:$E$9716,5,0)*IF($C$3="SI",((D4056/100)+1),1)*IF(AND($C$3="SI",$C$4="SI"),IF(D4056=21,0.92,IF(D4056=10.5,0.96,1)),1)*IF(ISNUMBER($C$5),1-$C$5,1),"-") -> 430.064 | F59: =IFERROR(E59*IF(ISNUMBER($C$6),1+$C$6,1),"-") -> 430.064 | AC59: ='ListaN69 09-02-2025'!AF57 -> Igual
A60: F171N | B60: FICHA AXIAL C/NEU HEMBRA ECO NEGRA ALAN | C60: UM 1u | 300u | D60: 21 | E60: =IFERROR(VLOOKUP(A60,'ListaN69 09-02-2025'!$A$9:$E$9716,5,0)*IF($C$3="SI",((D4057/100)+1),1)*IF(AND($C$3="SI",$C$4="SI"),IF(D4057=21,0.92,IF(D4057=10.5,0.96,1)),1)*IF(ISNUMBER($C$5),1-$C$5,1),"-") -> 430.064 | F60: =IFERROR(E60*IF(ISNUMBER($C$6),1+$C$6,1),"-") -> 430.064 | AC60: ='ListaN69 09-02-2025'!AF58 -> Igual
A61: 113 | B61: FICHA S/90º MACHO C/NEU BLANCO MIG | C61: UM 1u | 100u | D61: 21 | E61: =IFERROR(VLOOKUP(A61,'ListaN69 09-02-2025'!$A$9:$E$9716,5,0)*IF($C$3="SI",((D4058/100)+1),1)*IF(AND($C$3="SI",$C$4="SI"),IF(D4058=21,0.92,IF(D4058=10.5,0.96,1)),1)*IF(ISNUMBER($C$5),1-$C$5,1),"-") -> 1074.866 | F61: =IFERROR(E61*IF(ISNUMBER($C$6),1+$C$6,1),"-") -> 1074.866 | AC61: ='ListaN69 09-02-2025'!AF59 -> Igual
A62: 113N | B62: FICHA S/90º MACHO C/NEU NEGRA MIG | C62: UM 1u | 100u | D62: 21 | E62: =IFERROR(VLOOKUP(A62,'ListaN69 09-02-2025'!$A$9:$E$9716,5,0)*IF($C$3="SI",((D4059/100)+1),1)*IF(AND($C$3="SI",$C$4="SI"),IF(D4059=21,0.92,IF(D4059=10.5,0.96,1)),1)*IF(ISNUMBER($C$5),1-$C$5,1),"-") -> 1074.866 | F62: =IFERROR(E62*IF(ISNUMBER($C$6),1+$C$6,1),"-") -> 1074.866 | AC62: ='ListaN69 09-02-2025'!AF60 -> Igual
A63: 120 | B63: FICHA S/90º HEMBRA C/NEU BLANCO MIG | C63: UM 1u | 100u | D63: 21 | E63: =IFERROR(VLOOKUP(A63,'ListaN69 09-02-2025'!$A$9:$E$9716,5,0)*IF($C$3="SI",((D4060/100)+1),1)*IF(AND($C$3="SI",$C$4="SI"),IF(D4060=21,0.92,IF(D4060=10.5,0.96,1)),1)*IF(ISNUMBER($C$5),1-$C$5,1),"-") -> 916.543 | F63: =IFERROR(E63*IF(ISNUMBER($C$6),1+$C$6,1),"-") -> 916.543 | AC63: ='ListaN69 09-02-2025'!AF61 -> Igual
A64: 120N | B64: FICHA S/90º HEMBRA C/NEU NEGRA MIG | C64: UM 1u | 100u | D64: 21 | E64: =IFERROR(VLOOKUP(A64,'ListaN69 09-02-2025'!$A$9:$E$9716,5,0)*IF($C$3="SI",((D4061/100)+1),1)*IF(AND($C$3="SI",$C$4="SI"),IF(D4061=21,0.92,IF(D4061=10.5,0.96,1)),1)*IF(ISNUMBER($C$5),1-$C$5,1),"-") -> 916.543 | F64: =IFERROR(E64*IF(ISNUMBER($C$6),1+$C$6,1),"-") -> 916.543 | AC64: ='ListaN69 09-02-2025'!AF62 -> Igual
A65: F137B | B65: FICHA S/90º MACHO C/NEU BLANCO ALAN ECO | C65: UM 1u | 100u | D65: 21 | E65: =IFERROR(VLOOKUP(A65,'ListaN69 09-02-2025'!$A$9:$E$9716,5,0)*IF($C$3="SI",((D4062/100)+1),1)*IF(AND($C$3="SI",$C$4="SI"),IF(D4062=21,0.92,IF(D4062=10.5,0.96,1)),1)*IF(ISNUMBER($C$5),1-$C$5,1),"-") -> 456.962 | F65: =IFERROR(E65*IF(ISNUMBER($C$6),1+$C$6,1),"-") -> 456.962 | AC65: ='ListaN69 09-02-2025'!AF63 -> Igual
A66: F138B | B66: FICHA S/90º HEMBRA C/NEU BLANCO ALAN ECO BINORMA | C66: UM 1u | 100u | D66: 21 | E66: =IFERROR(VLOOKUP(A66,'ListaN69 09-02-2025'!$A$9:$E$9716,5,0)*IF($C$3="SI",((D4063/100)+1),1)*IF(AND($C$3="SI",$C$4="SI"),IF(D4063=21,0.92,IF(D4063=10.5,0.96,1)),1)*IF(ISNUMBER($C$5),1-$C$5,1),"-") -> 456.962 | F66: =IFERROR(E66*IF(ISNUMBER($C$6),1+$C$6,1),"-") -> 456.962 | AC66: ='ListaN69 09-02-2025'!AF64 -> Igual
A67: 103-28302 | B67: FICHA S/90º MACHO C/NEU GRAFITO 10A RICHI | C67: UM 1u | 200u | D67: 21 | E67: =IFERROR(VLOOKUP(A67,'ListaN69 09-02-2025'!$A$9:$E$9716,5,0)*IF($C$3="SI",((D4064/100)+1),1)*IF(AND($C$3="SI",$C$4="SI"),IF(D4064=21,0.92,IF(D4064=10.5,0.96,1)),1)*IF(ISNUMBER($C$5),1-$C$5,1),"-") -> 1110.148 | F67: =IFERROR(E67*IF(ISNUMBER($C$6),1+$C$6,1),"-") -> 1110.148 | AC67: ='ListaN69 09-02-2025'!AF65 -> Igual
A68: 103-28305 | B68: FICHA S/90º MACHO C/NEU MARFIL 10A RICHI | C68: UM 1u | 200u | D68: 21 | E68: =IFERROR(VLOOKUP(A68,'ListaN69 09-02-2025'!$A$9:$E$9716,5,0)*IF($C$3="SI",((D4065/100)+1),1)*IF(AND($C$3="SI",$C$4="SI"),IF(D4065=21,0.92,IF(D4065=10.5,0.96,1)),1)*IF(ISNUMBER($C$5),1-$C$5,1),"-") -> 1110.148 | F68: =IFERROR(E68*IF(ISNUMBER($C$6),1+$C$6,1),"-") -> 1110.148 | AC68: ='ListaN69 09-02-2025'!AF66 -> Igual
A69: 125-28702 | B69: FICHA S/90º HEMBRA GRAFITO 10A RICHI | C69: UM 1u | 200u | D69: 21 | E69: =IFERROR(VLOOKUP(A69,'ListaN69 09-02-2025'!$A$9:$E$9716,5,0)*IF($C$3="SI",((D4066/100)+1),1)*IF(AND($C$3="SI",$C$4="SI"),IF(D4066=21,0.92,IF(D4066=10.5,0.96,1)),1)*IF(ISNUMBER($C$5),1-$C$5,1),"-") -> 1110.148 | F69: =IFERROR(E69*IF(ISNUMBER($C$6),1+$C$6,1),"-") -> 1110.148 | AC69: ='ListaN69 09-02-2025'!AF67 -> Igual
A70: 125-28705 | B70: FICHA S/90º HEMBRA MARFIL 10A RICHI | C70: UM 1u | 200u | D70: 21 | E70: =IFERROR(VLOOKUP(A70,'ListaN69 09-02-2025'!$A$9:$E$9716,5,0)*IF($C$3="SI",((D4067/100)+1),1)*IF(AND($C$3="SI",$C$4="SI"),IF(D4067=21,0.92,IF(D4067=10.5,0.96,1)),1)*IF(ISNUMBER($C$5),1-$C$5,1),"-") -> 1110.148 | F70: =IFERROR(E70*IF(ISNUMBER($C$6),1+$C$6,1),"-") -> 1110.148 | AC70: ='ListaN69 09-02-2025'!AF68 -> Igual
A71: 141 | B71: FICHA S/90º MACHO C/AZA C/NEU | C71: UM 1u | 40u | D71: 21 | E71: =IFERROR(VLOOKUP(A71,'ListaN69 09-02-2025'!$A$9:$E$9716,5,0)*IF($C$3="SI",((D4068/100)+1),1)*IF(AND($C$3="SI",$C$4="SI"),IF(D4068=21,0.92,IF(D4068=10.5,0.96,1)),1)*IF(ISNUMBER($C$5),1-$C$5,1),"-") -> 1366.157 | F71: =IFERROR(E71*IF(ISNUMBER($C$6),1+$C$6,1),"-") -> 1366.157 | AC71: ='ListaN69 09-02-2025'!AF69 -> Igual
A72: 142 | B72: FICHA S/90º MACHO C/AZA C/NEU 20A | C72: UM 1u | 40u | D72: 21 | E72: =IFERROR(VLOOKUP(A72,'ListaN69 09-02-2025'!$A$9:$E$9716,5,0)*IF($C$3="SI",((D4069/100)+1),1)*IF(AND($C$3="SI",$C$4="SI"),IF(D4069=21,0.92,IF(D4069=10.5,0.96,1)),1)*IF(ISNUMBER($C$5),1-$C$5,1),"-") -> 1636.418 | F72: =IFERROR(E72*IF(ISNUMBER($C$6),1+$C$6,1),"-") -> 1636.418 | AC72: ='ListaN69 09-02-2025'!AF70 -> Igual
A73: 218 | B73: FICHA S/90º MACHO CON AZA PERNO REDONDO | C73: UM 1u | 40u | D73: 21 | E73: =IFERROR(VLOOKUP(A73,'ListaN69 09-02-2025'!$A$9:$E$9716,5,0)*IF($C$3="SI",((D4070/100)+1),1)*IF(AND($C$3="SI",$C$4="SI"),IF(D4070=21,0.92,IF(D4070=10.5,0.96,1)),1)*IF(ISNUMBER($C$5),1-$C$5,1),"-") -> 1299.363 | F73: =IFERROR(E73*IF(ISNUMBER($C$6),1+$C$6,1),"-") -> 1299.363 | AC73: ='ListaN69 09-02-2025'!AF71 -> Igual
A74: 242 | B74: FICHA S/90º HEMBRA C/AZA C/NEU 20A | C74: UM 1u | 40u | D74: 21 | E74: =IFERROR(VLOOKUP(A74,'ListaN69 09-02-2025'!$A$9:$E$9716,5,0)*IF($C$3="SI",((D4071/100)+1),1)*IF(AND($C$3="SI",$C$4="SI"),IF(D4071=21,0.92,IF(D4071=10.5,0.96,1)),1)*IF(ISNUMBER($C$5),1-$C$5,1),"-") -> 1653.736 | F74: =IFERROR(E74*IF(ISNUMBER($C$6),1+$C$6,1),"-") -> 1653.736 | AC74: ='ListaN69 09-02-2025'!AF72 -> Igual
A75: 250 | B75: FICHA S/90º HEMBRA C/AZA (BINORMA) | C75: UM 1u | 40u | D75: 21 | E75: =IFERROR(VLOOKUP(A75,'ListaN69 09-02-2025'!$A$9:$E$9716,5,0)*IF($C$3="SI",((D4072/100)+1),1)*IF(AND($C$3="SI",$C$4="SI"),IF(D4072=21,0.92,IF(D4072=10.5,0.96,1)),1)*IF(ISNUMBER($C$5),1-$C$5,1),"-") -> 1270.915 | F75: =IFERROR(E75*IF(ISNUMBER($C$6),1+$C$6,1),"-") -> 1270.915 | AC75: ='ListaN69 09-02-2025'!AF73 -> Igual
A76: 219 | B76: INTERRUPTOR P/VELADOR BCO | C76: UM 1u | 100u | D76: 21 | E76: =IFERROR(VLOOKUP(A76,'ListaN69 09-02-2025'!$A$9:$E$9716,5,0)*IF($C$3="SI",((D4073/100)+1),1)*IF(AND($C$3="SI",$C$4="SI"),IF(D4073=21,0.92,IF(D4073=10.5,0.96,1)),1)*IF(ISNUMBER($C$5),1-$C$5,1),"-") -> 716.165 | F76: =IFERROR(E76*IF(ISNUMBER($C$6),1+$C$6,1),"-") -> 716.165 | AC76: ='ListaN69 09-02-2025'!AF74 -> Igual
A77: 219-N | B77: INTERRUPTOR P/VELADOR NEGRO | C77: UM 1u | 100u | D77: 21 | E77: =IFERROR(VLOOKUP(A77,'ListaN69 09-02-2025'!$A$9:$E$9716,5,0)*IF($C$3="SI",((D4074/100)+1),1)*IF(AND($C$3="SI",$C$4="SI"),IF(D4074=21,0.92,IF(D4074=10.5,0.96,1)),1)*IF(ISNUMBER($C$5),1-$C$5,1),"-") -> 716.165 | F77: =IFERROR(E77*IF(ISNUMBER($C$6),1+$C$6,1),"-") -> 716.165 | AC77: ='ListaN69 09-02-2025'!AF75 -> Igual
A78: 102-25502 | B78: FICHA VELADOR GRAFITO 10A RICHI | C78: UM 1u | 300u | D78: 21 | E78: =IFERROR(VLOOKUP(A78,'ListaN69 09-02-2025'!$A$9:$E$9716,5,0)*IF($C$3="SI",((D4075/100)+1),1)*IF(AND($C$3="SI",$C$4="SI"),IF(D4075=21,0.92,IF(D4075=10.5,0.96,1)),1)*IF(ISNUMBER($C$5),1-$C$5,1),"-") -> 781.85 | F78: =IFERROR(E78*IF(ISNUMBER($C$6),1+$C$6,1),"-") -> 781.85 | AC78: ='ListaN69 09-02-2025'!AF76 -> Igual
A79: 102-25505 | B79: FICHA VELADOR MARFIL 10A RICHI | C79: UM 1u | 300u | D79: 21 | E79: =IFERROR(VLOOKUP(A79,'ListaN69 09-02-2025'!$A$9:$E$9716,5,0)*IF($C$3="SI",((D4076/100)+1),1)*IF(AND($C$3="SI",$C$4="SI"),IF(D4076=21,0.92,IF(D4076=10.5,0.96,1)),1)*IF(ISNUMBER($C$5),1-$C$5,1),"-") -> 781.85 | F79: =IFERROR(E79*IF(ISNUMBER($C$6),1+$C$6,1),"-") -> 781.85 | AC79: ='ListaN69 09-02-2025'!AF77 -> Igual
A80: 115-25002 | B80: INTERRUPTOR VELADOR GRIS 4A RICHI | C80: UM 1u | 300u | D80: 10.5 | E80: =IFERROR(VLOOKUP(A80,'ListaN69 09-02-2025'!$A$9:$E$9716,5,0)*IF($C$3="SI",((D4077/100)+1),1)*IF(AND($C$3="SI",$C$4="SI"),IF(D4077=21,0.92,IF(D4077=10.5,0.96,1)),1)*IF(ISNUMBER($C$5),1-$C$5,1),"-") -> 621.435 | F80: =IFERROR(E80*IF(ISNUMBER($C$6),1+$C$6,1),"-") -> 621.435 | AC80: ='ListaN69 09-02-2025'!AF78 -> Igual
A81: 115-25005 | B81: INTERRUPTOR VELADOR MARFIL 4A RICHI | C81: UM 1u | 300u | D81: 21 | E81: =IFERROR(VLOOKUP(A81,'ListaN69 09-02-2025'!$A$9:$E$9716,5,0)*IF($C$3="SI",((D4078/100)+1),1)*IF(AND($C$3="SI",$C$4="SI"),IF(D4078=21,0.92,IF(D4078=10.5,0.96,1)),1)*IF(ISNUMBER($C$5),1-$C$5,1),"-") -> 621.435 | F81: =IFERROR(E81*IF(ISNUMBER($C$6),1+$C$6,1),"-") -> 621.435 | AC81: ='ListaN69 09-02-2025'!AF79 -> Igual
A82: T-131 | B82: FICHA MACHO P/VELADOR REDONDO BCO | C82: UM 1u | 100u | D82: 21 | E82: =IFERROR(VLOOKUP(A82,'ListaN69 09-02-2025'!$A$9:$E$9716,5,0)*IF($C$3="SI",((D4079/100)+1),1)*IF(AND($C$3="SI",$C$4="SI"),IF(D4079=21,0.92,IF(D4079=10.5,0.96,1)),1)*IF(ISNUMBER($C$5),1-$C$5,1),"-") -> 1020.367 | F82: =IFERROR(E82*IF(ISNUMBER($C$6),1+$C$6,1),"-") -> 1020.367 | AC82: ='ListaN69 09-02-2025'!AF80 -> Igual
A83: T132 | B83: FICHA MACHO P/VELADOR P/CHATA BCO | C83: UM 1u | 100 | D83: 21 | E83: =IFERROR(VLOOKUP(A83,'ListaN69 09-02-2025'!$A$9:$E$9716,5,0)*IF($C$3="SI",((D4080/100)+1),1)*IF(AND($C$3="SI",$C$4="SI"),IF(D4080=21,0.92,IF(D4080=10.5,0.96,1)),1)*IF(ISNUMBER($C$5),1-$C$5,1),"-") -> 783.377 | F83: =IFERROR(E83*IF(ISNUMBER($C$6),1+$C$6,1),"-") -> 783.377 | AC83: ='ListaN69 09-02-2025'!AF81 -> Igual
A84: T132-N | B84: FICHA MACHO P/VELADOR P/CHATA NEGRO | C84: UM 1u | 100 | D84: 21 | E84: =IFERROR(VLOOKUP(A84,'ListaN69 09-02-2025'!$A$9:$E$9716,5,0)*IF($C$3="SI",((D4081/100)+1),1)*IF(AND($C$3="SI",$C$4="SI"),IF(D4081=21,0.92,IF(D4081=10.5,0.96,1)),1)*IF(ISNUMBER($C$5),1-$C$5,1),"-") -> 783.377 | F84: =IFERROR(E84*IF(ISNUMBER($C$6),1+$C$6,1),"-") -> 783.377 | AC84: ='ListaN69 09-02-2025'!AF82 -> Igual
A85: 974310 | B85: FICHA MACHO MARFIL 10A | C85: UM 1u | 100u | 1000u | D85: 21 | E85: =IFERROR(VLOOKUP(A85,'ListaN69 09-02-2025'!$A$9:$E$9716,5,0)*IF($C$3="SI",((D4082/100)+1),1)*IF(AND($C$3="SI",$C$4="SI"),IF(D4082=21,0.92,IF(D4082=10.5,0.96,1)),1)*IF(ISNUMBER($C$5),1-$C$5,1),"-") -> 348.867 | F85: =IFERROR(E85*IF(ISNUMBER($C$6),1+$C$6,1),"-") -> 348.867 | AC85: ='ListaN69 09-02-2025'!AF83 -> Igual
A86: 974315 | B86: FICHA HEMBRA MARFIL 10A | C86: UM 1u | 100u | 1000u | D86: 21 | E86: =IFERROR(VLOOKUP(A86,'ListaN69 09-02-2025'!$A$9:$E$9716,5,0)*IF($C$3="SI",((D4083/100)+1),1)*IF(AND($C$3="SI",$C$4="SI"),IF(D4083=21,0.92,IF(D4083=10.5,0.96,1)),1)*IF(ISNUMBER($C$5),1-$C$5,1),"-") -> 348.867 | F86: =IFERROR(E86*IF(ISNUMBER($C$6),1+$C$6,1),"-") -> 348.867 | AC86: ='ListaN69 09-02-2025'!AF84 -> Igual
A87: F104B | B87: FICHA MACHO 2 PATAS PLANAS ECO | C87: UM 1u | 200u | D87: 21 | E87: =IFERROR(VLOOKUP(A87,'ListaN69 09-02-2025'!$A$9:$E$9716,5,0)*IF($C$3="SI",((D4084/100)+1),1)*IF(AND($C$3="SI",$C$4="SI"),IF(D4084=21,0.92,IF(D4084=10.5,0.96,1)),1)*IF(ISNUMBER($C$5),1-$C$5,1),"-") -> 312.93 | F87: =IFERROR(E87*IF(ISNUMBER($C$6),1+$C$6,1),"-") -> 312.93 | AC87: ='ListaN69 09-02-2025'!AF85 -> Igual
A88: F106B | B88: FICHA MACHO BIPOLAR ECO | C88: UM 1u | 300u | D88: 21 | E88: =IFERROR(VLOOKUP(A88,'ListaN69 09-02-2025'!$A$9:$E$9716,5,0)*IF($C$3="SI",((D4085/100)+1),1)*IF(AND($C$3="SI",$C$4="SI"),IF(D4085=21,0.92,IF(D4085=10.5,0.96,1)),1)*IF(ISNUMBER($C$5),1-$C$5,1),"-") -> 309.548 | F88: =IFERROR(E88*IF(ISNUMBER($C$6),1+$C$6,1),"-") -> 309.548 | AC88: ='ListaN69 09-02-2025'!AF86 -> Igual
A89: F107B | B89: FICHA HEMBRA BIPOLAR ECO | C89: UM 1u | 300u | D89: 21 | E89: =IFERROR(VLOOKUP(A89,'ListaN69 09-02-2025'!$A$9:$E$9716,5,0)*IF($C$3="SI",((D4086/100)+1),1)*IF(AND($C$3="SI",$C$4="SI"),IF(D4086=21,0.92,IF(D4086=10.5,0.96,1)),1)*IF(ISNUMBER($C$5),1-$C$5,1),"-") -> 309.548 | F89: =IFERROR(E89*IF(ISNUMBER($C$6),1+$C$6,1),"-") -> 309.548 | AC89: ='ListaN69 09-02-2025'!AF87 -> Igual
A90: PCT-840 | B90: PONCHITO C/NEU | C90: UM 1u | 100u | D90: 21 | E90: =IFERROR(VLOOKUP(A90,'ListaN69 09-02-2025'!$A$9:$E$9716,5,0)*IF($C$3="SI",((D4087/100)+1),1)*IF(AND($C$3="SI",$C$4="SI"),IF(D4087=21,0.92,IF(D4087=10.5,0.96,1)),1)*IF(ISNUMBER($C$5),1-$C$5,1),"-") -> 154.613 | F90: =IFERROR(E90*IF(ISNUMBER($C$6),1+$C$6,1),"-") -> 154.613 | AC90: ='ListaN69 09-02-2025'!AF88 -> Igual
E91: =IFERROR(VLOOKUP(A91,'ListaN69 09-02-2025'!$A$9:$E$9716,5,0)*IF($C$3="SI",((D4088/100)+1),1)*IF(AND($C$3="SI",$C$4="SI"),IF(D4088=21,0.92,IF(D4088=10.5,0.96,1)),1)*IF(ISNUMBER($C$5),1-$C$5,1),"-") -> - | F91: =IFERROR(E91*IF(ISNUMBER($C$6),1+$C$6,1),"-") -> - | AC91: ='ListaN69 09-02-2025'!AF89 -> Blanco
B92: PORTALAMPARAS | E92: =IFERROR(VLOOKUP(A92,'ListaN69 09-02-2025'!$A$9:$E$9716,5,0)*IF($C$3="SI",((D4089/100)+1),1)*IF(AND($C$3="SI",$C$4="SI"),IF(D4089=21,0.92,IF(D4089=10.5,0.96,1)),1)*IF(ISNUMBER($C$5),1-$C$5,1),"-") -> - | F92: =IFERROR(E92*IF(ISNUMBER($C$6),1+$C$6,1),"-") -> - | AC92: ='ListaN69 09-02-2025'!AF90 -> Titulo
E93: =IFERROR(VLOOKUP(A93,'ListaN69 09-02-2025'!$A$9:$E$9716,5,0)*IF($C$3="SI",((D4090/100)+1),1)*IF(AND($C$3="SI",$C$4="SI"),IF(D4090=21,0.92,IF(D4090=10.5,0.96,1)),1)*IF(ISNUMBER($C$5),1-$C$5,1),"-") -> - | F93: =IFERROR(E93*IF(ISNUMBER($C$6),1+$C$6,1),"-") -> - | AC93: ='ListaN69 09-02-2025'!AF91 -> Blanco
A94: P-224P | B94: PORTALAMPARAS CON CHICOTE PREMIUM | C94: UM 1u | 100u | D94: 21 | E94: =IFERROR(VLOOKUP(A94,'ListaN69 09-02-2025'!$A$9:$E$9716,5,0)*IF($C$3="SI",((D4091/100)+1),1)*IF(AND($C$3="SI",$C$4="SI"),IF(D4091=21,0.92,IF(D4091=10.5,0.96,1)),1)*IF(ISNUMBER($C$5),1-$C$5,1),"-") -> 363.248 | F94: =IFERROR(E94*IF(ISNUMBER($C$6),1+$C$6,1),"-") -> 363.248 | AC94: ='ListaN69 09-02-2025'!AF92 -> Igual
A95: PCC-E27 | B95: PORTALAMPARAS CON CHICOTE | C95: UM 1u | 12u | 300u | D95: 21 | E95: =IFERROR(VLOOKUP(A95,'ListaN69 09-02-2025'!$A$9:$E$9716,5,0)*IF($C$3="SI",((D4092/100)+1),1)*IF(AND($C$3="SI",$C$4="SI"),IF(D4092=21,0.92,IF(D4092=10.5,0.96,1)),1)*IF(ISNUMBER($C$5),1-$C$5,1),"-") -> 672.0645 | F95: =IFERROR(E95*IF(ISNUMBER($C$6),1+$C$6,1),"-") -> 672.0645 | AC95: ='ListaN69 09-02-2025'!AF93 -> Bajo
A96: P-P2P | B96: PORTALAMPARAS 2 PIEZAS NEGRO | C96: UM 1u | 100u | D96: 21 | E96: =IFERROR(VLOOKUP(A96,'ListaN69 09-02-2025'!$A$9:$E$9716,5,0)*IF($C$3="SI",((D4093/100)+1),1)*IF(AND($C$3="SI",$C$4="SI"),IF(D4093=21,0.92,IF(D4093=10.5,0.96,1)),1)*IF(ISNUMBER($C$5),1-$C$5,1),"-") -> 385.487 | F96: =IFERROR(E96*IF(ISNUMBER($C$6),1+$C$6,1),"-") -> 385.487 | AC96: ='ListaN69 09-02-2025'!AF94 -> Igual
A97: P-P3P | B97: PORTALAMPARAS 3 PIEZAS SUPER NEGRO | C97: UM 1u | 100u | D97: 21 | E97: =IFERROR(VLOOKUP(A97,'ListaN69 09-02-2025'!$A$9:$E$9716,5,0)*IF($C$3="SI",((D4094/100)+1),1)*IF(AND($C$3="SI",$C$4="SI"),IF(D4094=21,0.92,IF(D4094=10.5,0.96,1)),1)*IF(ISNUMBER($C$5),1-$C$5,1),"-") -> 606.798 | F97: =IFERROR(E97*IF(ISNUMBER($C$6),1+$C$6,1),"-") -> 606.798 | AC97: ='ListaN69 09-02-2025'!AF95 -> Igual
A98: P-P3PB | B98: PORTALAMPARAS 3 PIEZAS BLANCO | C98: UM 1u | 100u | D98: 21 | E98: =IFERROR(VLOOKUP(A98,'ListaN69 09-02-2025'!$A$9:$E$9716,5,0)*IF($C$3="SI",((D4095/100)+1),1)*IF(AND($C$3="SI",$C$4="SI"),IF(D4095=21,0.92,IF(D4095=10.5,0.96,1)),1)*IF(ISNUMBER($C$5),1-$C$5,1),"-") -> 767.934 | F98: =IFERROR(E98*IF(ISNUMBER($C$6),1+$C$6,1),"-") -> 767.934 | AC98: ='ListaN69 09-02-2025'!AF96 -> Igual
A99: P-P3PM | B99: PORTALAMPARAS 3 PIEZAS MIGNON NEGRO | C99: UM 1u | 200 | D99: 21 | E99: =IFERROR(VLOOKUP(A99,'ListaN69 09-02-2025'!$A$9:$E$9716,5,0)*IF($C$3="SI",((D4096/100)+1),1)*IF(AND($C$3="SI",$C$4="SI"),IF(D4096=21,0.92,IF(D4096=10.5,0.96,1)),1)*IF(ISNUMBER($C$5),1-$C$5,1),"-") -> 884.998 | F99: =IFERROR(E99*IF(ISNUMBER($C$6),1+$C$6,1),"-") -> 884.998 | AC99: ='ListaN69 09-02-2025'!AF97 -> Igual
A100: P-P3PMB | B100: PORTALAMPARAS 3 PIEZAS MIGNON BLANCO MARFIL | C100: UM 1u | 200 | D100: 21 | E100: =IFERROR(VLOOKUP(A100,'ListaN69 09-02-2025'!$A$9:$E$9716,5,0)*IF($C$3="SI",((D4097/100)+1),1)*IF(AND($C$3="SI",$C$4="SI"),IF(D4097=21,0.92,IF(D4097=10.5,0.96,1)),1)*IF(ISNUMBER($C$5),1-$C$5,1),"-") -> 962.897 | F100: =IFERROR(E100*IF(ISNUMBER($C$6),1+$C$6,1),"-") -> 962.897 | AC100: ='ListaN69 09-02-2025'!AF98 -> Igual
A101: P-P560 | B101: PORTALAMPARAS CON FICHA | C101: UM 1u | 85u | D101: 21 | E101: =IFERROR(VLOOKUP(A101,'ListaN69 09-02-2025'!$A$9:$E$9716,5,0)*IF($C$3="SI",((D4098/100)+1),1)*IF(AND($C$3="SI",$C$4="SI"),IF(D4098=21,0.92,IF(D4098=10.5,0.96,1)),1)*IF(ISNUMBER($C$5),1-$C$5,1),"-") -> 1271.393 | F101: =IFERROR(E101*IF(ISNUMBER($C$6),1+$C$6,1),"-") -> 1271.393 | AC101: ='ListaN69 09-02-2025'!AF99 -> Igual
...

Sheet Mi pedido
C13: Ver precios con iva?
C14: Aplicar descuento por factura?
C15: Mi descuento
B18: Codigo | C18: Descripcion | D18: bulto | E18: iva | F18: Cantidad | G18: Precio | I18: Total
C19: =IF(ISBLANK(B19),"",IFERROR(VLOOKUP(B19,'ListaN69 09-02-2025'!$A$11:$E$10140,2,0),"No se encuentra el articulo en la lista")) | D19: =IF(ISBLANK(B19),"",IFERROR(VLOOKUP(B19,'ListaN69 09-02-2025'!$A$11:$E$10140,3,0),"-")) | E19: =IF(ISBLANK(B19),"",IFERROR(VLOOKUP(B19,'ListaN69 09-02-2025'!$A$11:$E$10140,4,0),"-")) | G19: =IF(ISBLANK(B19),"",IFERROR(VLOOKUP(B19,'ListaN69 09-02-2025'!$A$11:$E$10140,5,0)*IF(ISNUMBER($D$15),1-$D$15,1)*IF($D$13="SI",((E19/100)+1),1)*IF(AND($D$13="SI",$D$14="SI"),IF(E19=21,0.92,IF(E19=10.5,0.96,1)),1),"-")) | I19: =IF(AND(ISNUMBER(F19),ISNUMBER(G19)),G19*F19,0) -> 0
C20: =IF(ISBLANK(B20),"",IFERROR(VLOOKUP(B20,'ListaN69 09-02-2025'!$A$11:$E$10140,2,0),"No se encuentra el articulo en la lista")) | D20: =IF(ISBLANK(B20),"",IFERROR(VLOOKUP(B20,'ListaN69 09-02-2025'!$A$11:$E$10140,3,0),"-")) | E20: =IF(ISBLANK(B20),"",IFERROR(VLOOKUP(B20,'ListaN69 09-02-2025'!$A$11:$E$10140,4,0),"-")) | G20: =IF(ISBLANK(B20),"",IFERROR(VLOOKUP(B20,'ListaN69 09-02-2025'!$A$11:$E$10140,5,0)*IF(ISNUMBER($D$15),1-$D$15,1)*IF($D$13="SI",((E20/100)+1),1)*IF(AND($D$13="SI",$D$14="SI"),IF(E20=21,0.92,IF(E20=10.5,0.96,1)),1),"-")) | I20: =IF(AND(ISNUMBER(F20),ISNUMBER(G20)),G20*F20,0) -> 0
C21: =IF(ISBLANK(B21),"",IFERROR(VLOOKUP(B21,'ListaN69 09-02-2025'!$A$11:$E$10140,2,0),"No se encuentra el articulo en la lista")) | D21: =IF(ISBLANK(B21),"",IFERROR(VLOOKUP(B21,'ListaN69 09-02-2025'!$A$11:$E$10140,3,0),"-")) | E21: =IF(ISBLANK(B21),"",IFERROR(VLOOKUP(B21,'ListaN69 09-02-2025'!$A$11:$E$10140,4,0),"-")) | G21: =IF(ISBLANK(B21),"",IFERROR(VLOOKUP(B21,'ListaN69 09-02-2025'!$A$11:$E$10140,5,0)*IF(ISNUMBER($D$15),1-$D$15,1)*IF($D$13="SI",((E21/100)+1),1)*IF(AND($D$13="SI",$D$14="SI"),IF(E21=21,0.92,IF(E21=10.5,0.96,1)),1),"-")) | I21: =IF(AND(ISNUMBER(F21),ISNUMBER(G21)),G21*F21,0) -> 0
C22: =IF(ISBLANK(B22),"",IFERROR(VLOOKUP(B22,'ListaN69 09-02-2025'!$A$11:$E$10140,2,0),"No se encuentra el articulo en la lista")) | D22: =IF(ISBLANK(B22),"",IFERROR(VLOOKUP(B22,'ListaN69 09-02-2025'!$A$11:$E$10140,3,0),"-")) | E22: =IF(ISBLANK(B22),"",IFERROR(VLOOKUP(B22,'ListaN69 09-02-2025'!$A$11:$E$10140,4,0),"-")) | G22: =IF(ISBLANK(B22),"",IFERROR(VLOOKUP(B22,'ListaN69 09-02-2025'!$A$11:$E$10140,5,0)*IF(ISNUMBER($D$15),1-$D$15,1)*IF($D$13="SI",((E22/100)+1),1)*IF(AND($D$13="SI",$D$14="SI"),IF(E22=21,0.92,IF(E22=10.5,0.96,1)),1),"-")) | I22: =IF(AND(ISNUMBER(F22),ISNUMBER(G22)),G22*F22,0) -> 0
C23: =IF(ISBLANK(B23),"",IFERROR(VLOOKUP(B23,'ListaN69 09-02-2025'!$A$11:$E$10140,2,0),"No se encuentra el articulo en la lista")) | D23: =IF(ISBLANK(B23),"",IFERROR(VLOOKUP(B23,'ListaN69 09-02-2025'!$A$11:$E$10140,3,0),"-")) | E23: =IF(ISBLANK(B23),"",IFERROR(VLOOKUP(B23,'ListaN69 09-02-2025'!$A$11:$E$10140,4,0),"-")) | G23: =IF(ISBLANK(B23),"",IFERROR(VLOOKUP(B23,'ListaN69 09-02-2025'!$A$11:$E$10140,5,0)*IF(ISNUMBER($D$15),1-$D$15,1)*IF($D$13="SI",((E23/100)+1),1)*IF(AND($D$13="SI",$D$14="SI"),IF(E23=21,0.92,IF(E23=10.5,0.96,1)),1),"-")) | I23: =IF(AND(ISNUMBER(F23),ISNUMBER(G23)),G23*F23,0) -> 0
C24: =IF(ISBLANK(B24),"",IFERROR(VLOOKUP(B24,'ListaN69 09-02-2025'!$A$11:$E$10140,2,0),"No se encuentra el articulo en la lista")) | D24: =IF(ISBLANK(B24),"",IFERROR(VLOOKUP(B24,'ListaN69 09-02-2025'!$A$11:$E$10140,3,0),"-")) | E24: =IF(ISBLANK(B24),"",IFERROR(VLOOKUP(B24,'ListaN69 09-02-2025'!$A$11:$E$10140,4,0),"-")) | G24: =IF(ISBLANK(B24),"",IFERROR(VLOOKUP(B24,'ListaN69 09-02-2025'!$A$11:$E$10140,5,0)*IF(ISNUMBER($D$15),1-$D$15,1)*IF($D$13="SI",((E24/100)+1),1)*IF(AND($D$13="SI",$D$14="SI"),IF(E24=21,0.92,IF(E24=10.5,0.96,1)),1),"-")) | I24: =IF(AND(ISNUMBER(F24),ISNUMBER(G24)),G24*F24,0) -> 0
C25: =IF(ISBLANK(B25),"",IFERROR(VLOOKUP(B25,'ListaN69 09-02-2025'!$A$11:$E$10140,2,0),"No se encuentra el articulo en la lista")) | D25: =IF(ISBLANK(B25),"",IFERROR(VLOOKUP(B25,'ListaN69 09-02-2025'!$A$11:$E$10140,3,0),"-")) | E25: =IF(ISBLANK(B25),"",IFERROR(VLOOKUP(B25,'ListaN69 09-02-2025'!$A$11:$E$10140,4,0),"-")) | G25: =IF(ISBLANK(B25),"",IFERROR(VLOOKUP(B25,'ListaN69 09-02-2025'!$A$11:$E$10140,5,0)*IF(ISNUMBER($D$15),1-$D$15,1)*IF($D$13="SI",((E25/100)+1),1)*IF(AND($D$13="SI",$D$14="SI"),IF(E25=21,0.92,IF(E25=10.5,0.96,1)),1),"-")) | I25: =IF(AND(ISNUMBER(F25),ISNUMBER(G25)),G25*F25,0) -> 0
C26: =IF(ISBLANK(B26),"",IFERROR(VLOOKUP(B26,'ListaN69 09-02-2025'!$A$11:$E$10140,2,0),"No se encuentra el articulo en la lista")) | D26: =IF(ISBLANK(B26),"",IFERROR(VLOOKUP(B26,'ListaN69 09-02-2025'!$A$11:$E$10140,3,0),"-")) | E26: =IF(ISBLANK(B26),"",IFERROR(VLOOKUP(B26,'ListaN69 09-02-2025'!$A$11:$E$10140,4,0),"-")) | G26: =IF(ISBLANK(B26),"",IFERROR(VLOOKUP(B26,'ListaN69 09-02-2025'!$A$11:$E$10140,5,0)*IF(ISNUMBER($D$15),1-$D$15,1)*IF($D$13="SI",((E26/100)+1),1)*IF(AND($D$13="SI",$D$14="SI"),IF(E26=21,0.92,IF(E26=10.5,0.96,1)),1),"-")) | I26: =IF(AND(ISNUMBER(F26),ISNUMBER(G26)),G26*F26,0) -> 0
C27: =IF(ISBLANK(B27),"",IFERROR(VLOOKUP(B27,'ListaN69 09-02-2025'!$A$11:$E$10140,2,0),"No se encuentra el articulo en la lista")) | D27: =IF(ISBLANK(B27),"",IFERROR(VLOOKUP(B27,'ListaN69 09-02-2025'!$A$11:$E$10140,3,0),"-")) | E27: =IF(ISBLANK(B27),"",IFERROR(VLOOKUP(B27,'ListaN69 09-02-2025'!$A$11:$E$10140,4,0),"-")) | G27: =IF(ISBLANK(B27),"",IFERROR(VLOOKUP(B27,'ListaN69 09-02-2025'!$A$11:$E$10140,5,0)*IF(ISNUMBER($D$15),1-$D$15,1)*IF($D$13="SI",((E27/100)+1),1)*IF(AND($D$13="SI",$D$14="SI"),IF(E27=21,0.92,IF(E27=10.5,0.96,1)),1),"-")) | I27: =IF(AND(ISNUMBER(F27),ISNUMBER(G27)),G27*F27,0) -> 0
C28: =IF(ISBLANK(B28),"",IFERROR(VLOOKUP(B28,'ListaN69 09-02-2025'!$A$11:$E$10140,2,0),"No se encuentra el articulo en la lista")) | D28: =IF(ISBLANK(B28),"",IFERROR(VLOOKUP(B28,'ListaN69 09-02-2025'!$A$11:$E$10140,3,0),"-")) | E28: =IF(ISBLANK(B28),"",IFERROR(VLOOKUP(B28,'ListaN69 09-02-2025'!$A$11:$E$10140,4,0),"-")) | G28: =IF(ISBLANK(B28),"",IFERROR(VLOOKUP(B28,'ListaN69 09-02-2025'!$A$11:$E$10140,5,0)*IF(ISNUMBER($D$15),1-$D$15,1)*IF($D$13="SI",((E28/100)+1),1)*IF(AND($D$13="SI",$D$14="SI"),IF(E28=21,0.92,IF(E28=10.5,0.96,1)),1),"-")) | I28: =IF(AND(ISNUMBER(F28),ISNUMBER(G28)),G28*F28,0) -> 0
C29: =IF(ISBLANK(B29),"",IFERROR(VLOOKUP(B29,'ListaN69 09-02-2025'!$A$11:$E$10140,2,0),"No se encuentra el articulo en la lista")) | D29: =IF(ISBLANK(B29),"",IFERROR(VLOOKUP(B29,'ListaN69 09-02-2025'!$A$11:$E$10140,3,0),"-")) | E29: =IF(ISBLANK(B29),"",IFERROR(VLOOKUP(B29,'ListaN69 09-02-2025'!$A$11:$E$10140,4,0),"-")) | G29: =IF(ISBLANK(B29),"",IFERROR(VLOOKUP(B29,'ListaN69 09-02-2025'!$A$11:$E$10140,5,0)*IF(ISNUMBER($D$15),1-$D$15,1)*IF($D$13="SI",((E29/100)+1),1)*IF(AND($D$13="SI",$D$14="SI"),IF(E29=21,0.92,IF(E29=10.5,0.96,1)),1),"-")) | I29: =IF(AND(ISNUMBER(F29),ISNUMBER(G29)),G29*F29,0) -> 0
C30: =IF(ISBLANK(B30),"",IFERROR(VLOOKUP(B30,'ListaN69 09-02-2025'!$A$11:$E$10140,2,0),"No se encuentra el articulo en la lista")) | D30: =IF(ISBLANK(B30),"",IFERROR(VLOOKUP(B30,'ListaN69 09-02-2025'!$A$11:$E$10140,3,0),"-")) | E30: =IF(ISBLANK(B30),"",IFERROR(VLOOKUP(B30,'ListaN69 09-02-2025'!$A$11:$E$10140,4,0),"-")) | G30: =IF(ISBLANK(B30),"",IFERROR(VLOOKUP(B30,'ListaN69 09-02-2025'!$A$11:$E$10140,5,0)*IF(ISNUMBER($D$15),1-$D$15,1)*IF($D$13="SI",((E30/100)+1),1)*IF(AND($D$13="SI",$D$14="SI"),IF(E30=21,0.92,IF(E30=10.5,0.96,1)),1),"-")) | I30: =IF(AND(ISNUMBER(F30),ISNUMBER(G30)),G30*F30,0) -> 0
... C68: =IF(ISBLANK(B68),"",IFERROR(VLOOKUP(B68,'ListaN69 09-02-2025'!$A$11:$E$10140,2,0),"No se encuentra el articulo en la lista")) | D68: =IF(ISBLANK(B68),"",IFERROR(VLOOKUP(B68,'ListaN69 09-02-2025'!$A$11:$E$10140,3,0),"-")) | E68: =IF(ISBLANK(B68),"",IFERROR(VLOOKUP(B68,'ListaN69 09-02-2025'!$A$11:$E$10140,4,0),"-")) | G68: =IF(ISBLANK(B68),"",IFERROR(VLOOKUP(B68,'ListaN69 09-02-2025'!$A$11:$E$10140,5,0)*IF(ISNUMBER($D$15),1-$D$15,1)*IF($D$13="SI",((E68/100)+1),1)*IF(AND($D$13="SI",$D$14="SI"),IF(E68=21,0.92,IF(E68=10.5,0.96,1)),1),"-")) | I68: =IF(AND(ISNUMBER(F68),ISNUMBER(G68)),G68*F68,0) -> 0
F70: Total: | I70: =SUM(I19:I68) -> 0
